Workbook
Name ____tc1: [1]GG!$J$2
Name ___EPP2: [2]EPP!$J$22
Name ___f: 0.8
Name ___TSP4: [3]TSP4!$A$2:$G$165
Name ___VIZ4: [4]VIZ4!$A$2:$J$416
Name ___VIZ7: [4]VIZ7!$A$2:$J$476
Name __123Graph_A: [5]Zn!#REF!
Name __123Graph_ASECPRED: [6]LEAD!#REF!
Name __123Graph_BSECOND: [6]LEAD!#REF!
Name __123Graph_CSECOND: [6]LEAD!#REF!
Name __EPP2: [2]EPP!$J$22
Name __f: 0.8
Name __tc1: [7]GG!$J$2
Name __TSP4: [3]TSP4!$A$2:$G$165
Name __VIZ4: [4]VIZ4!$A$2:$J$416
Name __VIZ7: [4]VIZ7!$A$2:$J$476
Name _10__123Graph_ACHART_9: '[8]Load 2'!#REF!
Name _12__123Graph_BCHART_15: '[8]Material Forecast'!#REF!
Name _14__123Graph_BCHART_16: '[8]Material Forecast'!#REF!
Name _16__123Graph_BCHART_9: '[8]Load 2'!#REF!
Name _18__123Graph_CCHART_11: '[8]Material Forecast'!#REF!
Name _2__123Graph_ACHART_11: '[8]Material Forecast'!#REF!
Name _20__123Graph_CCHART_12: '[8]Material Forecast'!#REF!
Name _22__123Graph_CCHART_15: '[8]Material Forecast'!#REF!
Name _24__123Graph_CCHART_16: '[8]Material Forecast'!#REF!
Name _26__123Graph_DCHART_15: '[8]Material Forecast'!#REF!
Name _28__123Graph_ECHART_15: '[8]Material Forecast'!#REF!
Name _30__123Graph_XCHART_12: '[8]Material Forecast'!#REF!
Name _32__123Graph_XCHART_15: '[8]Material Forecast'!#REF!
Name _34__123Graph_XCHART_16: '[8]Material Forecast'!#REF!
Name _4__123Graph_ACHART_12: '[8]Material Forecast'!#REF!
Name _6__123Graph_ACHART_15: '[8]Material Forecast'!#REF!
Name _8__123Graph_ACHART_16: '[8]Material Forecast'!#REF!
Name _EPP2: [2]EPP!$J$22
Name _f: 0.8
Name _Order1: 255
Name _Order2: 255
Name _Regression_Out: '[9]loading equipment'!#REF!
Name _Regression_X: '[9]loading equipment'!$O$118:$O$120
Name _Regression_Y: '[9]loading equipment'!$Q$118:$Q$120
Name _res1: '[10]Resumen Ejec'!$B$2:$G$66
Name _res2: '[10]Resumen Ejec'!$B$70:$G$125
Name _res3: '[10]Resumen Ejec'!$B$142:$E$189
Name _res4: '[10]Resumen Ejec'!$B$198:$D$261
Name _tc1: [11]GG!$J$2
Name _TSP4: [3]TSP4!$A$2:$G$165
Name _VIZ4: [4]VIZ4!$A$2:$J$416
Name _VIZ7: [4]VIZ7!$A$2:$J$476
Name accesorio: [2]Insumos!$A$105:$E$129
Name accesorios: [12]Insumos!$A$105:$G$129
Name aceros: [2]Insumos!$A$77:$F$100
Name aguilar: [13]Parametros!#REF!
Name avance: [2]Insumos!$J$1
Name b: [13]Parametros!#REF!
Name banana: '[15]Balance Sheet Consolidated'!$C$5:$J$59
Name BSE: [16]BBSS!$K$38
Name Cálculos: [17]ANALISIS!$A$112:$L$198
Name cambio: '[18]GGAESA (2)'!$F$1
Name camion2: [13]Parametros!#REF!
Name categorias: [2]Insumos!$H$3:$J$21

Sheet Estimación de pérdidas
B2: Budget Salares Norte
C4: Y01 | D4: Y02 | E4: Y03 | F4: Y04 | G4: Y05 | H4: Y06 | I4: Y07 | J4: Y08 | K4: Y09 | L4: Y10 | M4: Y11 | N4: Y12 | O4: total
B5: Beneficio ton | C5: 1276070 | D5: 2000000 | E5: 2000000 | F5: 2000000 | G5: 2000000 | H5: 2000000 | I5: 2000000 | J5: 2000000 | K5: 2000000 | L5: 2000000 | M5: 2000000 | N5: 890000 | O5: =SUM(C5:N5) -> 22166070
B6: Oz Au | C6: 333918.29 | D6: 546538.54 | E6: 543926.66 | F6: 390327.47 | G6: 355319.26 | H6: 316562.44 | I6: 434351.76 | J6: 103293.13 | K6: 86389.12 | L6: 61957.465 | M6: 59278.731 | N6: 45324.223 | O6: =SUM(C6:N6) -> 3277187.1
B7: Oz Ag | C7: 1329033.3 | D7: 3609336.6 | E7: 3822391.4 | F7: 2418013.2 | G7: 3505080.7 | H7: 2433967.2 | I7: 1519056.7 | J7: 3495626.2 | K7: 1139234.1 | L7: 2664213.9 | M7: 611561.53 | N7: 184386.94 | O7: =SUM(C7:N7) -> 26731902
B8: Precious Oz Gold (US$) | C8: 1300 | D8: =+C8 -> 1300 | E8: =+D8 -> 1300 | F8: =+E8 -> 1300 | G8: =+F8 -> 1300 | H8: =+G8 -> 1300 | I8: =+H8 -> 1300 | J8: =+I8 -> 1300 | K8: =+J8 -> 1300 | ... N8: =+M8 -> 1300
B9: Precious Oz Silver (US$) | C9: 17.5 | D9: =+C9 -> 17.5 | E9: =+D9 -> 17.5 | F9: =+E9 -> 17.5 | G9: =+F9 -> 17.5 | H9: =+G9 -> 17.5 | I9: =+H9 -> 17.5 | J9: =+I9 -> 17.5 | K9: =+J9 -> 17.5 | ... N9: =+M9 -> 17.5
B10: Oz Equivalentes | C10: =+C6+C7/(C8/C9) -> 351809.12 | D10: =+D6+D7/(D8/D9) -> 595125.76 | E10: =+E6+E7/(E8/E9) -> 595381.93 | F10: =+F6+F7/(F8/F9) -> 422877.65 | G10: =+G6+G7/(G8/G9) -> 402503.04 | H10: =+H6+H7/(H8/H9) -> 349327.39 | I10: =+I6+I7/(I8/I9) -> 454800.6 | J10: =+J6+J7/(J8/J9) -> 150349.64 | ... N10: =+N6+N7/(N8/N9) -> 47806.355 | O10: =SUM(C10:N10) -> 3637039.6
A12: Ingresos | B12: Ingresos Ventas
B13: Ingresos Au US$ | C13: =+C8*C6 -> 4.3409377e+08 | D13: =+D8*D6 -> 7.105001e+08 | E13: =+E8*E6 -> 7.0710466e+08 | F13: =+F8*F6 -> 5.0742571e+08 | G13: =+G8*G6 -> 4.6191503e+08 | H13: =+H8*H6 -> 4.1153118e+08 | I13: =+I8*I6 -> 5.6465729e+08 | J13: =+J8*J6 -> 1.3428107e+08 | ... N13: =+N8*N6 -> 58921490 | O13: =SUM(C13:N13) -> 4260343230
B14: Ingresos Ag US$ | C14: =+C9*C7 -> 23258083 | D14: =+D9*D7 -> 63163390 | E14: =+E9*E7 -> 66891849 | F14: =+F9*F7 -> 42315230 | G14: =+G9*G7 -> 61338912 | H14: =+H9*H7 -> 42594427 | I14: =+I9*I7 -> 26583492 | J14: =+J9*J7 -> 61173458 | ... N14: =+N9*N7 -> 3226771.4 | O14: =SUM(C14:N14) -> 4.6780828e+08
B15: Total Ingresos US$ | C15: =+C14+C13 -> 4.5735186e+08 | D15: =+D14+D13 -> 7.7366349e+08 | E15: =+E14+E13 -> 7.7399651e+08 | F15: =+F14+F13 -> 5.4974094e+08 | G15: =+G14+G13 -> 5.2325395e+08 | H15: =+H14+H13 -> 4.541256e+08 | I15: =+I14+I13 -> 5.9124078e+08 | J15: =+J14+J13 -> 1.9545453e+08 | ... N15: =+N14+N13 -> 62148262 | O15: =SUM(C15:N15) -> 4728151509
B16: Total Ingresos MUS$ | C16: =+C15/1000000 -> 457.35186 | D16: =+D15/1000000 -> 773.66349 | E16: =+E15/1000000 -> 773.99651 | F16: =+F15/1000000 -> 549.74094 | G16: =+G15/1000000 -> 523.25395 | H16: =+H15/1000000 -> 454.1256 | I16: =+I15/1000000 -> 591.24078 | J16: =+J15/1000000 -> 195.45453 | ... N16: =+N15/1000000 -> 62.148262
A19: Egresos | B19: Egresos Operacionales
B20: Gestión Operacional MUS$ | C20: =+C4 -> Y01 | D20: =+D4 -> Y02 | E20: =+E4 -> Y03 | F20: =+F4 -> Y04 | G20: =+G4 -> Y05 | H20: =+H4 -> Y06 | I20: =+I4 -> Y07 | J20: =+J4 -> Y08 | ... N20: =+N4 -> Y12 | O20: Total MUS$ | P20: USD/ton ore | Q20: USD/Oz Equivalente
B21: G&A | C21: 39.8 | D21: 32.15 | E21: 32.15 | F21: 31.92 | G21: 31.92 | H21: 32.03 | I21: 30.49 | J21: 25.3 | K21: 24.77 | L21: 20.96 | M21: 12.66 | N21: 3.73 | O21: =SUM(C21:N21)*1000000 -> 317880000 | P21: =+O21/$O$5 -> 14.340837 | Q21: =+O21/$O$10 -> 87.400753
B22: Mining | C22: 82.57 | D22: 94.09 | E22: 100.27 | F22: 106.94 | G22: 106.79 | H22: 101.06 | I22: 71.57 | J22: 0 | K22: 0 | L22: 0 | M22: 0 | N22: 0 | O22: =SUM(C22:N22)*1000000 -> 663290000 | P22: =+O22/$O$5 -> 29.923663 | Q22: =+O22/$O$10 -> 182.37085
B23: Ore Re-handle | C23: 0.94 | D23: 1.56 | E23: 1.59 | F23: 1.64 | G23: 1.82 | H23: 1.42 | I23: 1.63 | J23: 6.42 | K23: 6.34 | L23: 6.34 | M23: 6.21 | N23: 3.17 | O23: =SUM(C23:N23)*1000000 -> 39080000 | P23: =+O23/$O$5 -> 1.763055 | Q23: =+O23/$O$10 -> 10.745003
B24: Processing | C24: 44.2 | D24: 59.48 | E24: 59.7 | F24: 59.94 | G24: 61.71 | H24: 57.77 | I24: 57.92 | J24: 58.77 | K24: 54.32 | L24: 55.91 | M24: 53.92 | N24: 26.37 | O24: =SUM(C24:N24)*1000000 -> 650010000 | P24: =+O24/$O$5 -> 29.324549 | Q24: =+O24/$O$10 -> 178.71953
B25: Tailings Transport | C25: 1.9 | D25: 2.65 | E25: 2.7 | F25: 2.75 | G25: 2.99 | H25: 2.55 | I25: 2.78 | J25: 4.6 | K25: 4.5 | L25: 4.6 | M25: 4.45 | N25: 2.22 | O25: =SUM(C25:N25)*1000000 -> 38690000 | P25: =+O25/$O$5 -> 1.7454605 | Q25: =+O25/$O$10 -> 10.637772
B26: Total MUS$ | C26: =SUM(C21:C25) -> 169.41 | D26: =SUM(D21:D25) -> 189.93 | E26: =SUM(E21:E25) -> 196.41 | F26: =SUM(F21:F25) -> 203.19 | G26: =SUM(G21:G25) -> 205.23 | H26: =SUM(H21:H25) -> 194.83 | I26: =SUM(I21:I25) -> 164.39 | J26: =SUM(J21:J25) -> 95.09 | ... N26: =SUM(N21:N25) -> 35.49 | O26: =SUM(C26:N26)*1000000 -> 1708950000 | P26: =+O26/$O$5 -> 77.097564
B28: Cash Cost US$/Oz equivalentes | C28: =+C26*1000000/C10 -> 481.53953 | D28: =+D26*1000000/D10 -> 319.14263 | E28: =+E26*1000000/E10 -> 329.88908 | F28: =+F26*1000000/F10 -> 480.49359 | G28: =+G26*1000000/G10 -> 509.88435 | H28: =+H26*1000000/H10 -> 557.72896 | I28: =+I26*1000000/I10 -> 361.45511 | J28: =+J26*1000000/J10 -> 632.45911 | ... N28: =+N26*1000000/N10 -> 742.36992 | O28: =+O26/O10 -> 469.8739 | Q28: =SUM(Q21:Q26) -> 469.8739
B30: Total Egresos US$ | C30: =+C26*1000000*-1 -> -169410000 | D30: =+D26*1000000*-1 -> -189930000 | E30: =+E26*1000000*-1 -> -196410000 | F30: =+F26*1000000*-1 -> -203190000 | G30: =+G26*1000000*-1 -> -205230000 | H30: =+H26*1000000*-1 -> -194830000 | I30: =+I26*1000000*-1 -> -164390000 | J30: =+J26*1000000*-1 -> -95090000 | ... N30: =+N26*1000000*-1 -> -35490000 | O30: =SUM(C30:N30) -> -1708950000
A32: Margen | B32: Margen Contribución Operacional US$ | C32: =+C15+C30 -> 2.8794186e+08 | D32: =+D15+D30 -> 5.8373349e+08 | E32: =+E15+E30 -> 5.7758651e+08 | F32: =+F15+F30 -> 3.4655094e+08 | G32: =+G15+G30 -> 3.1802395e+08 | H32: =+H15+H30 -> 2.592956e+08 | I32: =+I15+I30 -> 4.2685078e+08 | J32: =+J15+J30 -> 1.0036453e+08 | ... N32: =+N15+N30 -> 26658262 | O32: =SUM(C32:N32) -> 3019201509
B33: Margen Contribución Operacional MUS$ | C33: =+C32/1000000 -> 287.94186 | D33: =+D32/1000000 -> 583.73349 | E33: =+E32/1000000 -> 577.58651 | F33: =+F32/1000000 -> 346.55094 | G33: =+G32/1000000 -> 318.02395 | H33: =+H32/1000000 -> 259.2956 | I33: =+I32/1000000 -> 426.85078 | J33: =+J32/1000000 -> 100.36453 | ... N33: =+N32/1000000 -> 26.658262
D34: =+D32/D15 -> 0.75450567 | E34: =+E32/E15 -> 0.74623917 | F34: =+F32/F15 -> 0.63038955 | G34: =+G32/G15 -> 0.60778127 | H34: =+H32/H15 -> 0.57097773 | I34: =+I32/I15 -> 0.72195761 | J34: =+J32/J15 -> 0.51349299 | K34: =+K32/K15 -> 0.31996119 | ... N34: =+N32/N15 -> 0.42894621
A39: Op. Data | B39: Datos Operacionales | C39: Y01 | D39: Y02 | E39: Y03 | F39: Y04 | G39: Y05 | H39: Y06 | I39: Y07 | J39: Y08 | K39: Y09 | L39: Y10 | M39: Y11 | N39: Y12
B40: Utilización % | C40: 91.3 | D40: 91.3 | E40: 91.3 | F40: 91.3 | G40: 91.3 | H40: 91.3 | I40: 91.3 | J40: 91.3 | K40: 91.3 | L40: 91.3 | M40: 91.3 | N40: 91.3
B41: días año | C41: 365 | D41: 365 | E41: 365 | F41: 365 | G41: 365 | H41: 365 | I41: 365 | J41: 365 | K41: 365 | L41: 365 | M41: 365 | N41: 365
B42: dias efectivos | C42: =+C41*C40/100 -> 333.245 | D42: =+D41*D40/100 -> 333.245 | E42: =+E41*E40/100 -> 333.245 | F42: =+F41*F40/100 -> 333.245 | G42: =+G41*G40/100 -> 333.245 | H42: =+H41*H40/100 -> 333.245 | I42: =+I41*I40/100 -> 333.245 | J42: =+J41*J40/100 -> 333.245 | ... N42: =+N41*N40/100 -> 333.245
B43: Oz día Au | C43: =+C6/C42 -> 1002.0204 | D43: =+D6/D42 -> 1640.0502 | E43: =+E6/E42 -> 1632.2125 | F43: =+F6/F42 -> 1171.2928 | G43: =+G6/G42 -> 1066.2403 | H43: =+H6/H42 -> 949.93907 | I43: =+I6/I42 -> 1303.4007 | J43: =+J6/J42 -> 309.96154 | ... N43: =+N6/N42 -> 136.00871
B44: Oz hr Au | C44: =+C43/(24*C40%) -> 45.729299 | D44: =+D43/(24*D40%) -> 74.847126 | E44: =+E43/(24*E40%) -> 74.489436 | F44: =+F43/(24*F40%) -> 53.4544 | G44: =+G43/(24*G40%) -> 48.66011 | H44: =+H43/(24*H40%) -> 43.352458 | I44: =+I43/(24*I40%) -> 59.483419 | J44: =+J43/(24*J40%) -> 14.145744 | ... N44: =+N43/(24*N40%) -> 6.2070423
A45: Ingresos Hr | B45: Ingreso hr Au US$ | C45: =+C44*C8 -> 59448.089 | D45: =+D44*D8 -> 97301.264 | E45: =+E44*E8 -> 96836.267 | F45: =+F44*F8 -> 69490.72 | G45: =+G44*G8 -> 63258.143 | H45: =+H44*H8 -> 56358.196 | I45: =+I44*I8 -> 77328.445 | J45: =+J44*J8 -> 18389.467 | ... N45: =+N44*N8 -> 8069.155
B46: Oz día Ag | C46: =+C7/C42 -> 3988.1569 | D46: =+D7/D42 -> 10830.88 | E46: =+E7/E42 -> 11470.214 | F46: =+F7/F42 -> 7255.9623 | G46: =+G7/G42 -> 10518.029 | H46: =+H7/H42 -> 7303.8372 | I46: =+I7/I42 -> 4558.3781 | J46: =+J7/J42 -> 10489.658 | ... N46: =+N7/N42 -> 553.30744
B47: Oz hr Ag US$ | C47: =+C46/(24*C40%) -> 182.00789 | D47: =+D46/(24*D40%) -> 494.28988 | E47: =+E46/(24*E40%) -> 523.46722 | F47: =+F46/(24*F40%) -> 331.14103 | G47: =+G46/(24*G40%) -> 480.01229 | H47: =+H46/(24*H40%) -> 333.32591 | I47: =+I46/(24*I40%) -> 208.03113 | J47: =+J46/(24*J40%) -> 478.71752 | ... N47: =+N46/(24*N40%) -> 25.251344
B48: Ingreso hr Ag | C48: =+C47*C9 -> 3185.1381 | D48: =+D47*D9 -> 8650.0729 | E48: =+E47*E9 -> 9160.6763 | F48: =+F47*F9 -> 5794.9681 | G48: =+G47*G9 -> 8400.2151 | H48: =+H47*H9 -> 5833.2033 | I48: =+I47*I9 -> 3640.5447 | J48: =+J47*J9 -> 8377.5565 | ... N48: =+N47*N9 -> 441.89851
B49: Ingreso total Hr Au, Ag | C49: =+C48+C45 -> 62633.227 | D49: =+D48+D45 -> 105951.34 | E49: =+E48+E45 -> 105996.94 | F49: =+F48+F45 -> 75285.688 | G49: =+G48+G45 -> 71658.358 | H49: =+H48+H45 -> 62191.399 | I49: =+I48+I45 -> 80968.99 | J49: =+J48+J45 -> 26767.024 | ... N49: =+N48+N45 -> 8511.0536
B50: Oz Equivalentes día | C50: =+C10/C42 -> 1055.7071 | D50: =+D10/D42 -> 1785.8505 | E50: =+E10/E42 -> 1786.6193 | F50: =+F10/F42 -> 1268.9692 | G50: =+G10/G42 -> 1207.8292 | H50: =+H10/H42 -> 1048.26 | I50: =+I10/I42 -> 1364.7635 | J50: =+J10/J42 -> 451.16848 | ... N50: =+N10/N42 -> 143.45708
B51: Oz Equivalentes hr | C51: =+C50/(24*C40%) -> 48.179405 | D51: =+D50/(24*D40%) -> 81.501029 | E51: =+E50/(24*E40%) -> 81.53611 | F51: =+F50/(24*F40%) -> 57.912067 | G51: =+G50/(24*G40%) -> 55.121814 | H51: =+H50/(24*H40%) -> 47.839538 | I51: =+I50/(24*I40%) -> 62.283838 | J51: =+J50/(24*J40%) -> 20.590018 | ... N51: =+N50/(24*N40%) -> 6.5469643
B52: Ingreso Oz Equivalentes hr | C52: =+C51*C8 -> 62633.227 | D52: =+D51*D8 -> 105951.34 | E52: =+E51*E8 -> 105996.94 | F52: =+F51*F8 -> 75285.688 | G52: =+G51*G8 -> 71658.358 | H52: =+H51*H8 -> 62191.399 | I52: =+I51*I8 -> 80968.99 | J52: =+J51*J8 -> 26767.024 | ... N52: =+N51*N8 -> 8511.0536
A54: Costos Hr | B54: Costos fijos MUS$ | C54: Y01 | D54: Y02 | E54: Y03 | F54: Y04 | G54: Y05 | H54: Y06 | I54: Y07 | J54: Y08 | K54: Y09 | L54: Y10 | M54: Y11 | N54: Y12 | O54: Total | Q54: US$/ton ore | R54: US$/Oz Equivalente
B55: G&A | C55: =+C21 -> 39.8 | D55: =+D21 -> 32.15 | E55: =+E21 -> 32.15 | F55: =+F21 -> 31.92 | G55: =+G21 -> 31.92 | H55: =+H21 -> 32.03 | I55: =+I21 -> 30.49 | J55: =+J21 -> 25.3 | ... N55: =+N21 -> 3.73 | O55: =SUM(C55:N55)*1000000 -> 317880000 | Q55: =+O55/$O$5 -> 14.340837 | R55: =+O55/$O$10 -> 87.400753
B56: Mining | C56: =+C22 -> 82.57 | D56: =+D22 -> 94.09 | E56: =+E22 -> 100.27 | F56: =+F22 -> 106.94 | G56: =+G22 -> 106.79 | H56: =+H22 -> 101.06 | I56: =+I22 -> 71.57 | J56: =+J22 -> 0 | ... N56: =+N22 -> 0 | O56: =SUM(C56:N56)*1000000 -> 663290000 | Q56: =+O56/$O$5 -> 29.923663 | R56: =+O56/$O$10 -> 182.37085
B57: Ore Re-handle | C57: =+C23 -> 0.94 | D57: =+D23 -> 1.56 | E57: =+E23 -> 1.59 | F57: =+F23 -> 1.64 | G57: =+G23 -> 1.82 | H57: =+H23 -> 1.42 | I57: =+I23 -> 1.63 | J57: =+J23 -> 6.42 | ... N57: =+N23 -> 3.17 | O57: =SUM(C57:N57)*1000000 -> 39080000 | Q57: =+O57/$O$5 -> 1.763055 | R57: =+O57/$O$10 -> 10.745003
B58: Processing | C58: =+C24-13.4 -> 30.8 | D58: =+D24-22.2 -> 37.28 | E58: =+E24-22.4 -> 37.3 | F58: =+F24-22.9 -> 37.04 | G58: =+G24-25 -> 36.71 | H58: =+H24-21.1 -> 36.67 | I58: =+I24-21.2 -> 36.72 | J58: =+J24-23 -> 35.77 | K58: =+K24-18.6 -> 35.72 | L58: =+L24-20.2 -> 35.71 | M58: =+M24-18.7 -> 35.22 | N58: =+N24-7.9 -> 18.47 | O58: =SUM(C58:N58)*1000000 -> 413410000 | Q58: =+O58/$O$5 -> 18.650577 | R58: =+O58/$O$10 -> 113.66662
B59: Tailings Transport | C59: =+C25 -> 1.9 | D59: =+D25 -> 2.65 | E59: =+E25 -> 2.7 | F59: =+F25 -> 2.75 | G59: =+G25 -> 2.99 | H59: =+H25 -> 2.55 | I59: =+I25 -> 2.78 | J59: =+J25 -> 4.6 | ... N59: =+N25 -> 2.22 | O59: =SUM(C59:N59)*1000000 -> 38690000 | Q59: =+O59/$O$5 -> 1.7454605 | R59: =+O59/$O$10 -> 10.637772
B60: Total MUS$ | C60: =SUM(C55:C59) -> 156.01 | D60: =SUM(D55:D59) -> 167.73 | E60: =SUM(E55:E59) -> 174.01 | F60: =SUM(F55:F59) -> 180.29 | G60: =SUM(G55:G59) -> 180.23 | H60: =SUM(H55:H59) -> 173.73 | I60: =SUM(I55:I59) -> 143.19 | J60: =SUM(J55:J59) -> 72.09 | ... N60: =SUM(N55:N59) -> 27.59 | O60: =SUM(C60:N60)*1000000 -> 1472350000 | Q60: =+O60/$O$5 -> 66.423592
B61: Cash Cost US$/Oz equivalentes | C61: =+C60*1000000/C10 -> 443.4507 | D61: =+D60*1000000/D10 -> 281.83959 | E61: =+E60*1000000/E10 -> 292.26617 | F61: =+F60*1000000/F10 -> 426.34081 | G61: =+G60*1000000/G10 -> 447.77302 | H61: =+H60*1000000/H10 -> 497.32717 | I61: =+I60*1000000/I10 -> 314.84127 | J61: =+J60*1000000/J10 -> 479.48236 | ... N61: =+N60*1000000/N10 -> 577.11992 | O61: =+O60/O10 -> 404.821 | R61: =SUM(R55:R60) -> 404.821
A63: Perdidas Hr | B63: Costos e Ingresos por detencion Planta | C63: Y01 | D63: Y02 | E63: Y03 | F63: Y04 | G63: Y05 | H63: Y06 | I63: Y07 | J63: Y08 | K63: Y09 | L63: Y10 | M63: Y11 | N63: Y12
B65: Costos US$/Oz | C65: =+C61*C51 -> 21365.191 | D65: =+D61*D51 -> 22970.216 | E65: =+E61*E51 -> 23830.247 | F65: =+F61*F51 -> 24690.278 | G65: =+G61*G51 -> 24682.061 | H65: =+H61*H51 -> 23791.902 | I65: =+I61*I51 -> 19609.523 | J65: =+J61*J51 -> 9872.5505 | ... N65: =+N61*N51 -> 3778.3835
B66: ingresos US$/hr | C66: =+C52 -> 62633.227 | D66: =+D52 -> 105951.34 | E66: =+E52 -> 105996.94 | F66: =+F52 -> 75285.688 | G66: =+G52 -> 71658.358 | H66: =+H52 -> 62191.399 | I66: =+I52 -> 80968.99 | J66: =+J52 -> 26767.024 | ... N66: =+N52 -> 8511.0536
B68: Margen Operacional US$/hr | C68: =+C66-C65 -> 41268.036 | D68: =+D66-D65 -> 82981.121 | E68: =+E66-E65 -> 82166.696 | F68: =+F66-F65 -> 50595.41 | G68: =+G66-G65 -> 46976.297 | H68: =+H66-H65 -> 38399.497 | I68: =+I66-I65 -> 61359.467 | J68: =+J66-J65 -> 16894.473 | ... N68: =+N66-N65 -> 4732.67
F71: =+MAX(C68:I68) -> 82981.121 | G71: Max | L71: =+MAX(J68:N68) -> 16894.473 | M71: Max
F72: =+AVERAGE(C68:I68) -> 57678.075 | G72: Promedio | L72: =+AVERAGE(J68:N68) -> 8425.5178 | M72: Promedio

Sheet Plantilla criticidad de activos
A1: Análisis de criticidad de activos / equipos
A2: Sub área | B2: Sistema | C2: Descripción UT | D2: Cod. TAG UT | E2: Descripción UT | F2: Función principal | G2: Evento / Falla | H2: Consecuencia de falla / evento | I2: # equipos instalados | J2: # equipos requeridos para operación | K2: Redundancia | L2: Tipo Redundancia | M2: Down time equipo (Días) | N2: Afectación a capacidad del proceso | O2: Factor de utilización | P2: Demora en afectación del proceso (Horas) | Q2: Pérdida del proceso [Tiempo en horas] | R2: Pérdida del proceso [USD] | S2: ¿Es SCE*? Safety Critical Equipment | T2: Evaluación de Riesgo | AH2: Probabilidad | AI2: Criticidad
T3: Probabilidad / Frecuencia de falla | U3: Consecuencias consideradas | Z3: Consecuencia dominante | AA3: Consideración de riesgo / criticidad | AB3: Coeficiente de riesgo | AC3: Valoración de riesgo | AH3: 5-Casi seguro | AI3: Moderado | AJ3: 5
L4: Tipo Redundancia | M4: Down time equipo (Días) | N4: Afectación a capacidad del proceso | O4: Factor de utilización | P4: Demora en afectación del proceso (Horas) | Q4: Pérdida del proceso [Tiempo en horas] | R4: Pérdida del proceso [USD] | U4: Margen operacional | V4: Costo operacional | W4: Seguridad y Salud | X4: Medio Ambiente | Y4: RSC (Comunidad / Imagen / Cumplimento legal) | AH4: 4-Probable | AI4: Bajo | AJ4: 4
A5: 2100 Chancado Primario & Acopio Mineral Mina | B5: 2110 Estación de chancador primario | C5: Acumulador aire de Chancado | D5: 2110AR0003 | E5: Acumulador de aire Chancado | F5: Acumular el aire comprimido proveniente del compresor 2110CP0003 y a ser distribuido a supresor de polvo 2110DT0001 | G5: Rotura de acumulador | H5: No afectación a producción, Área contaminada de polvo sin efectos posteriores en salud de personas, Costos de cambio de acumulador | I5: 1 | J5: 1 | K5: =+IF(I5="","",IF((I5-J5)>0,"Si","No")) -> No | L5: Ninguna | M5: 0.25 | N5: 0 | O5: 70 | P5: 10 | Q5: =+IF(M5="","",(IF(((M5*24)-P5)<0,0,(M5*24)-P5)*N5)) -> 0 | R5: =+(IF(((M5*24)-P5)<0,0,((M5*24)-P5)*'Estimación de pérdidas'!$F$72))*N5 -> 0 | S5: No | T5: 2-Improbable | U5: =+IF(R5="","",IF(R5<50001,1,IF(R5<200001,2,IF(R5<500001,3,IF(R5<1000001,4,5))))) -> 1 | V5: 1 | Z5: =MAX(U5:Y5) -> 1 | AA5: =IF(Z5=1,VLOOKUP(T5,$AH$3:$AI$7,2,FALSE),IF(Z5=2,VLOOKUP(T5,$AH$8:$AI$12,2, FALSE),IF(Z5=3,VLOOKUP(T5,$AH$13:$AI$17,2,FALSE),IF(Z5=4,VLOOKUP(T5,$AH$18:$AI$22,2,FALSE),IF(Z5=5,VLOOKUP(T5,$AH$23:$AI$27,2,FALSE),""))))) -> Bajo | AB5: =IF(T5="1-Raro",IF(Z5=1,1,IF(Z5=2,3,IF(Z5=3,6,IF(Z5=4,10,15)))),IF(T5="2-Improbable",IF(Z5=1,2,IF(Z5=2,5,IF(Z5=3,9,IF(Z5=4,14,19)))),IF(T5="3-Posible",IF(Z5=1,4,IF(Z5=2,8,IF(Z5=3,13,IF(Z5=4,18,21)))),IF(T5="4-Probable",IF(Z5=1,7,IF(Z5=2,12,IF(Z5=3,17,IF(Z5=4,22,23)))),IF(T5="5-Casi Seguro",IF(Z5=1,11,IF(Z5=2,16,IF(Z5=3,20,IF(Z5=4,24,25))))))))) -> 2 | AC5: =((VLOOKUP(T5,$AH$3:$AJ$7,3,FALSE)*SQRT(U5^2+V5^2+W5^2+X5^2+Y5^2))/(5*SQRT((5)*5^2))) -> 0.050596443 | AH5: 3-Posible | AI5: Bajo | AJ5: 3
A6: 2100 Chancado Primario & Acopio Mineral Mina | B6: 2110 Estación de chancador primario | C6: Tolva Room | D6: 2110BN0001 | E6: Tolva room | F6: Recepcionar material de camiones (40 Ton) provenientes de mina, tiene una plataforma de descarga y una capacidad es de 80 toneladas (2 camiones) para alimentar chancador de mandíbulas | G6: Soltura de revestimientos internos de tolva por presencia de inchancables (puntas de pala) en tolva provenientes de camiones de mina | H6: Afectación a producción, Parada de chancador y alimentación de Stock pile para remover inchancables, Costos reparación de tolva | I6: 1 | J6: 1 | K6: =+IF(I6="","",IF((I6-J6)>0,"Si","No")) -> No | L6: Ninguna | M6: 1 | N6: 1 | O6: 70 | P6: 10 | Q6: =+IF(M6="","",(IF(((M6*24)-P6)<0,0,(M6*24)-P6)*N6)) -> 14 | R6: =+(IF(((M6*24)-P6)<0,0,((M6*24)-P6)*'Estimación de pérdidas'!$F$72))*N6 -> 807493.05 | S6: No | T6: 4-Probable | U6: =+IF(R6="","",IF(R6<50001,1,IF(R6<200001,2,IF(R6<500001,3,IF(R6<1000001,4,5))))) -> 4 | V6: 1 | Z6: =MAX(U6:Y6) -> 4 | AA6: =IF(Z6=1,VLOOKUP(T6,$AH$3:$AI$7,2,FALSE),IF(Z6=2,VLOOKUP(T6,$AH$8:$AI$12,2, FALSE),IF(Z6=3,VLOOKUP(T6,$AH$13:$AI$17,2,FALSE),IF(Z6=4,VLOOKUP(T6,$AH$18:$AI$22,2,FALSE),IF(Z6=5,VLOOKUP(T6,$AH$23:$AI$27,2,FALSE),""))))) -> Alto | AB6: =IF(T6="1-Raro",IF(Z6=1,1,IF(Z6=2,3,IF(Z6=3,6,IF(Z6=4,10,15)))),IF(T6="2-Improbable",IF(Z6=1,2,IF(Z6=2,5,IF(Z6=3,9,IF(Z6=4,14,19)))),IF(T6="3-Posible",IF(Z6=1,4,IF(Z6=2,8,IF(Z6=3,13,IF(Z6=4,18,21)))),IF(T6="4-Probable",IF(Z6=1,7,IF(Z6=2,12,IF(Z6=3,17,IF(Z6=4,22,23)))),IF(T6="5-Casi Seguro",IF(Z6=1,11,IF(Z6=2,16,IF(Z6=3,20,IF(Z6=4,24,25))))))))) -> 22 | AC6: =((VLOOKUP(T6,$AH$3:$AJ$7,3,FALSE)*SQRT(U6^2+V6^2+W6^2+X6^2+Y6^2))/(5*SQRT((5)*5^2))) -> 0.29502542 | AH6: 2-Improbable | AI6: Bajo | AJ6: 2
A7: 2100 Chancado Primario & Acopio Mineral Mina | B7: 2110 Estación de chancador primario | C7: Alimentador bandeja Chancador | D7: 2110FE0021 | E7: Alimentador bandeja chancado | F7: Descargar material proveniente de Tolva Room hacia el chute 2110-CH-0002 que alimenta chancador de mandíbulas | G7: Rotura de bandeja por inchancables | H7: No afectación a producción, Suspensión alimentación a tolva room, Parada de chancador y alimentación de Stock pile, Costo por cambio de bandeja | I7: 1 | J7: 1 | K7: =+IF(I7="","",IF((I7-J7)>0,"Si","No")) -> No | L7: Ninguna | M7: 0.25 | N7: 1 | O7: 70 | P7: 10 | Q7: =+IF(M7="","",(IF(((M7*24)-P7)<0,0,(M7*24)-P7)*N7)) -> 0 | R7: =+(IF(((M7*24)-P7)<0,0,((M7*24)-P7)*'Estimación de pérdidas'!$F$72))*N7 -> 0 | S7: No | T7: 4-Probable | U7: =+IF(R7="","",IF(R7<50001,1,IF(R7<200001,2,IF(R7<500001,3,IF(R7<1000001,4,5))))) -> 1 | V7: 1 | Z7: =MAX(U7:Y7) -> 1 | AA7: =IF(Z7=1,VLOOKUP(T7,$AH$3:$AI$7,2,FALSE),IF(Z7=2,VLOOKUP(T7,$AH$8:$AI$12,2, FALSE),IF(Z7=3,VLOOKUP(T7,$AH$13:$AI$17,2,FALSE),IF(Z7=4,VLOOKUP(T7,$AH$18:$AI$22,2,FALSE),IF(Z7=5,VLOOKUP(T7,$AH$23:$AI$27,2,FALSE),""))))) -> Bajo | AB7: =IF(T7="1-Raro",IF(Z7=1,1,IF(Z7=2,3,IF(Z7=3,6,IF(Z7=4,10,15)))),IF(T7="2-Improbable",IF(Z7=1,2,IF(Z7=2,5,IF(Z7=3,9,IF(Z7=4,14,19)))),IF(T7="3-Posible",IF(Z7=1,4,IF(Z7=2,8,IF(Z7=3,13,IF(Z7=4,18,21)))),IF(T7="4-Probable",IF(Z7=1,7,IF(Z7=2,12,IF(Z7=3,17,IF(Z7=4,22,23)))),IF(T7="5-Casi Seguro",IF(Z7=1,11,IF(Z7=2,16,IF(Z7=3,20,IF(Z7=4,24,25))))))))) -> 7 | AC7: =((VLOOKUP(T7,$AH$3:$AJ$7,3,FALSE)*SQRT(U7^2+V7^2+W7^2+X7^2+Y7^2))/(5*SQRT((5)*5^2))) -> 0.10119289 | AH7: 1-Raro | AI7: Bajo | AJ7: 1
A8: 2100 Chancado Primario & Acopio Mineral Mina | B8: 2110 Estación de chancador primario | C8: Chancador de mandíbula | D8: 2110CR0001 | E8: Chancador de mandíbula | F8: Trituración de mineral proveniente de tolva room 2110BN0001 y ser transferido posteriormente a correa 2110CV0001 | G8: Parada de chancador por presencia de inchancables | H8: Afectación a producción, Parada de chancador y alimentación Stock pile, Retiro de inchancables | I8: 1 | J8: 1 | K8: =+IF(I8="","",IF((I8-J8)>0,"Si","No")) -> No | L8: Ninguna | M8: 1 | N8: 1 | O8: 70 | P8: 10 | Q8: =+IF(M8="","",(IF(((M8*24)-P8)<0,0,(M8*24)-P8)*N8)) -> 14 | R8: =+(IF(((M8*24)-P8)<0,0,((M8*24)-P8)*'Estimación de pérdidas'!$F$72))*N8 -> 807493.05 | S8: No | T8: 4-Probable | U8: =+IF(R8="","",IF(R8<50001,1,IF(R8<200001,2,IF(R8<500001,3,IF(R8<1000001,4,5))))) -> 4 | V8: 1 | Z8: =MAX(U8:Y8) -> 4 | AA8: =IF(Z8=1,VLOOKUP(T8,$AH$3:$AI$7,2,FALSE),IF(Z8=2,VLOOKUP(T8,$AH$8:$AI$12,2, FALSE),IF(Z8=3,VLOOKUP(T8,$AH$13:$AI$17,2,FALSE),IF(Z8=4,VLOOKUP(T8,$AH$18:$AI$22,2,FALSE),IF(Z8=5,VLOOKUP(T8,$AH$23:$AI$27,2,FALSE),""))))) -> Alto | AB8: =IF(T8="1-Raro",IF(Z8=1,1,IF(Z8=2,3,IF(Z8=3,6,IF(Z8=4,10,15)))),IF(T8="2-Improbable",IF(Z8=1,2,IF(Z8=2,5,IF(Z8=3,9,IF(Z8=4,14,19)))),IF(T8="3-Posible",IF(Z8=1,4,IF(Z8=2,8,IF(Z8=3,13,IF(Z8=4,18,21)))),IF(T8="4-Probable",IF(Z8=1,7,IF(Z8=2,12,IF(Z8=3,17,IF(Z8=4,22,23)))),IF(T8="5-Casi Seguro",IF(Z8=1,11,IF(Z8=2,16,IF(Z8=3,20,IF(Z8=4,24,25))))))))) -> 22 | AC8: =((VLOOKUP(T8,$AH$3:$AJ$7,3,FALSE)*SQRT(U8^2+V8^2+W8^2+X8^2+Y8^2))/(5*SQRT((5)*5^2))) -> 0.29502542 | AH8: 5-Casi seguro | AI8: Moderado
A9: 2100 Chancado Primario & Acopio Mineral Mina | B9: 2110 Estación de chancador primario | C9: Rompedor roca | D9: 2110RK0001 | E9: Rompedor roca | F9: Fracturar las rocas de gran tamaño provenientes de Tolva room (2100BN0001) para introducirlas en el chancador de mandíbulas (2110-CR-0001). | G9: Falla cilindro hidráulico de brazo | H9: No afectación a producción, Parada de chancador, Costos por cambio de brazo hidráulico | I9: 1 | J9: 1 | K9: =+IF(I9="","",IF((I9-J9)>0,"Si","No")) -> No | L9: Ninguna | M9: 0.41666667 | N9: 0 | P9: 0 | Q9: =+IF(M9="","",(IF(((M9*24)-P9)<0,0,(M9*24)-P9)*N9)) -> 0 | R9: =+(IF(((M9*24)-P9)<0,0,((M9*24)-P9)*'Estimación de pérdidas'!$F$72))*N9 -> 0 | S9: No | T9: 3-Posible | U9: =+IF(R9="","",IF(R9<50001,1,IF(R9<200001,2,IF(R9<500001,3,IF(R9<1000001,4,5))))) -> 1 | V9: 1 | Z9: =MAX(U9:Y9) -> 1 | AA9: =IF(Z9=1,VLOOKUP(T9,$AH$3:$AI$7,2,FALSE),IF(Z9=2,VLOOKUP(T9,$AH$8:$AI$12,2, FALSE),IF(Z9=3,VLOOKUP(T9,$AH$13:$AI$17,2,FALSE),IF(Z9=4,VLOOKUP(T9,$AH$18:$AI$22,2,FALSE),IF(Z9=5,VLOOKUP(T9,$AH$23:$AI$27,2,FALSE),""))))) -> Bajo | AB9: =IF(T9="1-Raro",IF(Z9=1,1,IF(Z9=2,3,IF(Z9=3,6,IF(Z9=4,10,15)))),IF(T9="2-Improbable",IF(Z9=1,2,IF(Z9=2,5,IF(Z9=3,9,IF(Z9=4,14,19)))),IF(T9="3-Posible",IF(Z9=1,4,IF(Z9=2,8,IF(Z9=3,13,IF(Z9=4,18,21)))),IF(T9="4-Probable",IF(Z9=1,7,IF(Z9=2,12,IF(Z9=3,17,IF(Z9=4,22,23)))),IF(T9="5-Casi Seguro",IF(Z9=1,11,IF(Z9=2,16,IF(Z9=3,20,IF(Z9=4,24,25))))))))) -> 4 | AC9: =((VLOOKUP(T9,$AH$3:$AJ$7,3,FALSE)*SQRT(U9^2+V9^2+W9^2+X9^2+Y9^2))/(5*SQRT((5)*5^2))) -> 0.075894664 | AH9: 4-Probable | AI9: Moderado
A10: 2100 Chancado Primario & Acopio Mineral Mina | B10: 2110 Estación de chancador primario | C10: Correa descarga Chancador | D10: 2110CV0001 | E10: Correa descarga Chancador | F10: Recepcionar la descarga de producto de chancado (P80: 150 mm) a través del chute de transferencia (2110-CH-0004). Esta correa está equipada con un electroimán (2110-MA-0001) para retirar las piezas metálicas magnéticas que vienen con el mineral. | G10: Rotura correa transportadora (64 m) | H10: Afectación a producción, Parada de Chancador, Parada Molino SAG, Costos por cambio de correa | I10: 1 | J10: 1 | K10: =+IF(I10="","",IF((I10-J10)>0,"Si","No")) -> No | L10: Ninguna | M10: 1.5 | N10: 1 | O10: 70 | P10: 10 | Q10: =+IF(M10="","",(IF(((M10*24)-P10)<0,0,(M10*24)-P10)*N10)) -> 26 | R10: =+(IF(((M10*24)-P10)<0,0,((M10*24)-P10)*'Estimación de pérdidas'!$F$72))*N10 -> 1499629.9 | S10: No | T10: 3-Posible | U10: =+IF(R10="","",IF(R10<50001,1,IF(R10<200001,2,IF(R10<500001,3,IF(R10<1000001,4,5))))) -> 5 | V10: 1 | Z10: =MAX(U10:Y10) -> 5 | AA10: =IF(Z10=1,VLOOKUP(T10,$AH$3:$AI$7,2,FALSE),IF(Z10=2,VLOOKUP(T10,$AH$8:$AI$12,2, FALSE),IF(Z10=3,VLOOKUP(T10,$AH$13:$AI$17,2,FALSE),IF(Z10=4,VLOOKUP(T10,$AH$18:$AI$22,2,FALSE),IF(Z10=5,VLOOKUP(T10,$AH$23:$AI$27,2,FALSE),""))))) -> Alto | AB10: =IF(T10="1-Raro",IF(Z10=1,1,IF(Z10=2,3,IF(Z10=3,6,IF(Z10=4,10,15)))),IF(T10="2-Improbable",IF(Z10=1,2,IF(Z10=2,5,IF(Z10=3,9,IF(Z10=4,14,19)))),IF(T10="3-Posible",IF(Z10=1,4,IF(Z10=2,8,IF(Z10=3,13,IF(Z10=4,18,21)))),IF(T10="4-Probable",IF(Z10=1,7,IF(Z10=2,12,IF(Z10=3,17,IF(Z10=4,22,23)))),IF(T10="5-Casi Seguro",IF(Z10=1,11,IF(Z10=2,16,IF(Z10=3,20,IF(Z10=4,24,25))))))))) -> 21 | AC10: =((VLOOKUP(T10,$AH$3:$AJ$7,3,FALSE)*SQRT(U10^2+V10^2+W10^2+X10^2+Y10^2))/(5*SQRT((5)*5^2))) -> 0.2736421 | AH10: 3-Posible | AI10: Moderado
A11: 2100 Chancado Primario & Acopio Mineral Mina | B11: 2120 Alimentación acopio de gruesos | C11: Correa alimentación acopio | D11: 2120CV0002 | E11: Correa alimentación acopio | F11: Recibir el producto descargado de correa descarga de chancador 2120-CV-0001 y alimentar el acopio de mineral a través de chute 2120-CH-0006. La correa cuenta con un pesó metro (2120-SC-0001), el cual permite la medición y el registro de la masa de alimentación de mineral | G11: Rotura correa transportadora (295 m) | H11: Afectación a producción, Parada de Chancador, Parada Molino SAG, Costos por cambio de correa | I11: 1 | J11: 1 | K11: =+IF(I11="","",IF((I11-J11)>0,"Si","No")) -> No | L11: Ninguna | M11: 3 | N11: 1 | O11: 70 | P11: 10 | Q11: =+IF(M11="","",(IF(((M11*24)-P11)<0,0,(M11*24)-P11)*N11)) -> 62 | R11: =+(IF(((M11*24)-P11)<0,0,((M11*24)-P11)*'Estimación de pérdidas'!$F$72))*N11 -> 3576040.6 | S11: No | T11: 2-Improbable | U11: =+IF(R11="","",IF(R11<50001,1,IF(R11<200001,2,IF(R11<500001,3,IF(R11<1000001,4,5))))) -> 5 | V11: 2 | Z11: =MAX(U11:Y11) -> 5 | AA11: =IF(Z11=1,VLOOKUP(T11,$AH$3:$AI$7,2,FALSE),IF(Z11=2,VLOOKUP(T11,$AH$8:$AI$12,2, FALSE),IF(Z11=3,VLOOKUP(T11,$AH$13:$AI$17,2,FALSE),IF(Z11=4,VLOOKUP(T11,$AH$18:$AI$22,2,FALSE),IF(Z11=5,VLOOKUP(T11,$AH$23:$AI$27,2,FALSE),""))))) -> Alto | AB11: =IF(T11="1-Raro",IF(Z11=1,1,IF(Z11=2,3,IF(Z11=3,6,IF(Z11=4,10,15)))),IF(T11="2-Improbable",IF(Z11=1,2,IF(Z11=2,5,IF(Z11=3,9,IF(Z11=4,14,19)))),IF(T11="3-Posible",IF(Z11=1,4,IF(Z11=2,8,IF(Z11=3,13,IF(Z11=4,18,21)))),IF(T11="4-Probable",IF(Z11=1,7,IF(Z11=2,12,IF(Z11=3,17,IF(Z11=4,22,23)))),IF(T11="5-Casi Seguro",IF(Z11=1,11,IF(Z11=2,16,IF(Z11=3,20,IF(Z11=4,24,25))))))))) -> 19 | AC11: =((VLOOKUP(T11,$AH$3:$AJ$7,3,FALSE)*SQRT(U11^2+V11^2+W11^2+X11^2+Y11^2))/(5*SQRT((5)*5^2))) -> 0.19266551 | AH11: 2-Improbable | AI11: Bajo
A12: 2100 Chancado Primario & Acopio Mineral Mina | B12: 2110 Estación de chancador primario | C12: Sistema supresión de polvo | D12: 2110DT0001 | E12: Sistema supresión polvo | F12: Producir neblina a partir de aire comprimido inyectado a las boquillas de aspersión de agua encapsulando el polvo generado en Tolva Room, en chancador primario y su respectiva correa de descarga | G12: Rotura cámara de niebla | H12: Área contaminada de polvo sin efectos posteriores en salud de personas, No afectación en producción, Cambio cámara de niebla | I12: 1 | J12: 1 | K12: =+IF(I12="","",IF((I12-J12)>0,"Si","No")) -> No | L12: Ninguna | M12: 0.25 | N12: 0 | O12: 70 | P12: 10 | Q12: =+IF(M12="","",(IF(((M12*24)-P12)<0,0,(M12*24)-P12)*N12)) -> 0 | R12: =+(IF(((M12*24)-P12)<0,0,((M12*24)-P12)*'Estimación de pérdidas'!$F$72))*N12 -> 0 | S12: No | T12: 3-Posible | U12: =+IF(R12="","",IF(R12<50001,1,IF(R12<200001,2,IF(R12<500001,3,IF(R12<1000001,4,5))))) -> 1 | V12: 1 | Z12: =MAX(U12:Y12) -> 1 | AA12: =IF(Z12=1,VLOOKUP(T12,$AH$3:$AI$7,2,FALSE),IF(Z12=2,VLOOKUP(T12,$AH$8:$AI$12,2, FALSE),IF(Z12=3,VLOOKUP(T12,$AH$13:$AI$17,2,FALSE),IF(Z12=4,VLOOKUP(T12,$AH$18:$AI$22,2,FALSE),IF(Z12=5,VLOOKUP(T12,$AH$23:$AI$27,2,FALSE),""))))) -> Bajo | AB12: =IF(T12="1-Raro",IF(Z12=1,1,IF(Z12=2,3,IF(Z12=3,6,IF(Z12=4,10,15)))),IF(T12="2-Improbable",IF(Z12=1,2,IF(Z12=2,5,IF(Z12=3,9,IF(Z12=4,14,19)))),IF(T12="3-Posible",IF(Z12=1,4,IF(Z12=2,8,IF(Z12=3,13,IF(Z12=4,18,21)))),IF(T12="4-Probable",IF(Z12=1,7,IF(Z12=2,12,IF(Z12=3,17,IF(Z12=4,22,23)))),IF(T12="5-Casi Seguro",IF(Z12=1,11,IF(Z12=2,16,IF(Z12=3,20,IF(Z12=4,24,25))))))))) -> 4 | AC12: =((VLOOKUP(T12,$AH$3:$AJ$7,3,FALSE)*SQRT(U12^2+V12^2+W12^2+X12^2+Y12^2))/(5*SQRT((5)*5^2))) -> 0.075894664 | AH12: 1-Raro | AI12: Bajo
A13: 2100 Chancado Primario & Acopio Mineral Mina | B13: 2110 Estación de chancador primario | C13: Sistema supresión de polvo | D13: 2110DT0002 | E13: Sistema supresión polvo | F13: Producir neblina a partir de aire comprimido inyectado a las boquillas de aspersión de agua encapsulando el polvo generado en correa alimentación acopio | G13: Rotura cámara de niebla | H13: Área contaminada de polvo sin efectos posteriores en salud de personas, No afectación en producción, Cambio cámara de niebla | I13: 1 | J13: 1 | K13: =+IF(I13="","",IF((I13-J13)>0,"Si","No")) -> No | L13: Ninguna | M13: 0.25 | N13: 0 | O13: 70 | P13: 10 | Q13: =+IF(M13="","",(IF(((M13*24)-P13)<0,0,(M13*24)-P13)*N13)) -> 0 | R13: =+(IF(((M13*24)-P13)<0,0,((M13*24)-P13)*'Estimación de pérdidas'!$F$72))*N13 -> 0 | S13: No | T13: 3-Posible | U13: =+IF(R13="","",IF(R13<50001,1,IF(R13<200001,2,IF(R13<500001,3,IF(R13<1000001,4,5))))) -> 1 | V13: 1 | Z13: =MAX(U13:Y13) -> 1 | AA13: =IF(Z13=1,VLOOKUP(T13,$AH$3:$AI$7,2,FALSE),IF(Z13=2,VLOOKUP(T13,$AH$8:$AI$12,2, FALSE),IF(Z13=3,VLOOKUP(T13,$AH$13:$AI$17,2,FALSE),IF(Z13=4,VLOOKUP(T13,$AH$18:$AI$22,2,FALSE),IF(Z13=5,VLOOKUP(T13,$AH$23:$AI$27,2,FALSE),""))))) -> Bajo | AB13: =IF(T13="1-Raro",IF(Z13=1,1,IF(Z13=2,3,IF(Z13=3,6,IF(Z13=4,10,15)))),IF(T13="2-Improbable",IF(Z13=1,2,IF(Z13=2,5,IF(Z13=3,9,IF(Z13=4,14,19)))),IF(T13="3-Posible",IF(Z13=1,4,IF(Z13=2,8,IF(Z13=3,13,IF(Z13=4,18,21)))),IF(T13="4-Probable",IF(Z13=1,7,IF(Z13=2,12,IF(Z13=3,17,IF(Z13=4,22,23)))),IF(T13="5-Casi Seguro",IF(Z13=1,11,IF(Z13=2,16,IF(Z13=3,20,IF(Z13=4,24,25))))))))) -> 4 | AC13: =((VLOOKUP(T13,$AH$3:$AJ$7,3,FALSE)*SQRT(U13^2+V13^2+W13^2+X13^2+Y13^2))/(5*SQRT((5)*5^2))) -> 0.075894664 | AH13: 5-Casi seguro | AI13: Alto
A14: 2100 Chancado Primario & Acopio Mineral Mina | B14: 2110 Estación de chancador primario | C14: Tolva descarga electroimán | D14: 2110BN0002 | E14: Tolva descarga electroimán | F14: Almacenar la descarga de electroimán de correa descarga de chancador 2110CV0001 | G14: Rotura en paredes de tolva | H14: No afectación a producción, Costos reparación de tolva | I14: 1 | J14: 1 | K14: =+IF(I14="","",IF((I14-J14)>0,"Si","No")) -> No | L14: Ninguna | M14: 0.33333333 | N14: 0 | O14: 70 | P14: 10 | Q14: =+IF(M14="","",(IF(((M14*24)-P14)<0,0,(M14*24)-P14)*N14)) -> 0 | R14: =+(IF(((M14*24)-P14)<0,0,((M14*24)-P14)*'Estimación de pérdidas'!$F$72))*N14 -> 0 | S14: No | T14: 2-Improbable | U14: =+IF(R14="","",IF(R14<50001,1,IF(R14<200001,2,IF(R14<500001,3,IF(R14<1000001,4,5))))) -> 1 | V14: 1 | Z14: =MAX(U14:Y14) -> 1 | AA14: =IF(Z14=1,VLOOKUP(T14,$AH$3:$AI$7,2,FALSE),IF(Z14=2,VLOOKUP(T14,$AH$8:$AI$12,2, FALSE),IF(Z14=3,VLOOKUP(T14,$AH$13:$AI$17,2,FALSE),IF(Z14=4,VLOOKUP(T14,$AH$18:$AI$22,2,FALSE),IF(Z14=5,VLOOKUP(T14,$AH$23:$AI$27,2,FALSE),""))))) -> Bajo | AB14: =IF(T14="1-Raro",IF(Z14=1,1,IF(Z14=2,3,IF(Z14=3,6,IF(Z14=4,10,15)))),IF(T14="2-Improbable",IF(Z14=1,2,IF(Z14=2,5,IF(Z14=3,9,IF(Z14=4,14,19)))),IF(T14="3-Posible",IF(Z14=1,4,IF(Z14=2,8,IF(Z14=3,13,IF(Z14=4,18,21)))),IF(T14="4-Probable",IF(Z14=1,7,IF(Z14=2,12,IF(Z14=3,17,IF(Z14=4,22,23)))),IF(T14="5-Casi Seguro",IF(Z14=1,11,IF(Z14=2,16,IF(Z14=3,20,IF(Z14=4,24,25))))))))) -> 2 | AC14: =((VLOOKUP(T14,$AH$3:$AJ$7,3,FALSE)*SQRT(U14^2+V14^2+W14^2+X14^2+Y14^2))/(5*SQRT((5)*5^2))) -> 0.050596443 | AH14: 4-Probable | AI14: Moderado
A15: 2100 Chancado Primario & Acopio Mineral Mina | B15: 2110 Estación de chancador primario | C15: Tecle torre de transferencia | D15: 2110HT0003 | E15: Tecle descarga chancador | F15: Izar y desplazar cargas en el área de chancado primario | G15: Falla de cableado / cadena | H15: No afectación a operaciones, Cambiar el tecle | I15: 1 | J15: 1 | K15: =+IF(I15="","",IF((I15-J15)>0,"Si","No")) -> No | L15: Ninguna | M15: 0.33333333 | N15: 0 | P15: 0 | Q15: =+IF(M15="","",(IF(((M15*24)-P15)<0,0,(M15*24)-P15)*N15)) -> 0 | R15: =+(IF(((M15*24)-P15)<0,0,((M15*24)-P15)*'Estimación de pérdidas'!$F$72))*N15 -> 0 | S15: No | T15: 3-Posible | U15: =+IF(R15="","",IF(R15<50001,1,IF(R15<200001,2,IF(R15<500001,3,IF(R15<1000001,4,5))))) -> 1 | V15: 1 | Z15: =MAX(U15:Y15) -> 1 | AA15: =IF(Z15=1,VLOOKUP(T15,$AH$3:$AI$7,2,FALSE),IF(Z15=2,VLOOKUP(T15,$AH$8:$AI$12,2, FALSE),IF(Z15=3,VLOOKUP(T15,$AH$13:$AI$17,2,FALSE),IF(Z15=4,VLOOKUP(T15,$AH$18:$AI$22,2,FALSE),IF(Z15=5,VLOOKUP(T15,$AH$23:$AI$27,2,FALSE),""))))) -> Bajo | AB15: =IF(T15="1-Raro",IF(Z15=1,1,IF(Z15=2,3,IF(Z15=3,6,IF(Z15=4,10,15)))),IF(T15="2-Improbable",IF(Z15=1,2,IF(Z15=2,5,IF(Z15=3,9,IF(Z15=4,14,19)))),IF(T15="3-Posible",IF(Z15=1,4,IF(Z15=2,8,IF(Z15=3,13,IF(Z15=4,18,21)))),IF(T15="4-Probable",IF(Z15=1,7,IF(Z15=2,12,IF(Z15=3,17,IF(Z15=4,22,23)))),IF(T15="5-Casi Seguro",IF(Z15=1,11,IF(Z15=2,16,IF(Z15=3,20,IF(Z15=4,24,25))))))))) -> 4 | AC15: =((VLOOKUP(T15,$AH$3:$AJ$7,3,FALSE)*SQRT(U15^2+V15^2+W15^2+X15^2+Y15^2))/(5*SQRT((5)*5^2))) -> 0.075894664 | AH15: 3-Posible | AI15: Moderado
A16: 2100 Chancado Primario & Acopio Mineral Mina | B16: 2110 Estación de chancador primario | C16: Carro electroimán | D16: 2110HT0002 | E16: Carro electroimán | F16: Desplazar material recuperado a tolva electroimán de correa descarga de chancador 2110CV0001 | G16: Falla de cableado / cadena | H16: No afectación a operaciones, Cambiar el tecle | I16: 1 | J16: 1 | K16: =+IF(I16="","",IF((I16-J16)>0,"Si","No")) -> No | L16: Ninguna | M16: 0.33333333 | N16: 0 | P16: 0 | Q16: =+IF(M16="","",(IF(((M16*24)-P16)<0,0,(M16*24)-P16)*N16)) -> 0 | R16: =+(IF(((M16*24)-P16)<0,0,((M16*24)-P16)*'Estimación de pérdidas'!$F$72))*N16 -> 0 | S16: No | T16: 3-Posible | U16: =+IF(R16="","",IF(R16<50001,1,IF(R16<200001,2,IF(R16<500001,3,IF(R16<1000001,4,5))))) -> 1 | V16: 1 | Z16: =MAX(U16:Y16) -> 1 | AA16: =IF(Z16=1,VLOOKUP(T16,$AH$3:$AI$7,2,FALSE),IF(Z16=2,VLOOKUP(T16,$AH$8:$AI$12,2, FALSE),IF(Z16=3,VLOOKUP(T16,$AH$13:$AI$17,2,FALSE),IF(Z16=4,VLOOKUP(T16,$AH$18:$AI$22,2,FALSE),IF(Z16=5,VLOOKUP(T16,$AH$23:$AI$27,2,FALSE),""))))) -> Bajo | AB16: =IF(T16="1-Raro",IF(Z16=1,1,IF(Z16=2,3,IF(Z16=3,6,IF(Z16=4,10,15)))),IF(T16="2-Improbable",IF(Z16=1,2,IF(Z16=2,5,IF(Z16=3,9,IF(Z16=4,14,19)))),IF(T16="3-Posible",IF(Z16=1,4,IF(Z16=2,8,IF(Z16=3,13,IF(Z16=4,18,21)))),IF(T16="4-Probable",IF(Z16=1,7,IF(Z16=2,12,IF(Z16=3,17,IF(Z16=4,22,23)))),IF(T16="5-Casi Seguro",IF(Z16=1,11,IF(Z16=2,16,IF(Z16=3,20,IF(Z16=4,24,25))))))))) -> 4 | AC16: =((VLOOKUP(T16,$AH$3:$AJ$7,3,FALSE)*SQRT(U16^2+V16^2+W16^2+X16^2+Y16^2))/(5*SQRT((5)*5^2))) -> 0.075894664 | AH16: 2-Improbable | AI16: Moderado
A17: 2100 Chancado Primario & Acopio Mineral Mina | B17: 2110 Estación de chancador primario | C17: Chute descarga Chancador | D17: 2110CH0004 | E17: Chute descarga Chancador | F17: Almacenar la descarga de chancador 2110CR0001 y transferir a la correa descarga de chancador 2110CV0001 | G17: Rotura de chute | H17: No afectación a producción, Parada de chancador de mandíbula, Costos por reparación de chute | I17: 1 | J17: 1 | K17: =+IF(I17="","",IF((I17-J17)>0,"Si","No")) -> No | L17: Ninguna | M17: 0.41666667 | N17: 1 | O17: 70 | P17: 10 | Q17: =+IF(M17="","",(IF(((M17*24)-P17)<0,0,(M17*24)-P17)*N17)) -> 0 | R17: =+(IF(((M17*24)-P17)<0,0,((M17*24)-P17)*'Estimación de pérdidas'!$F$72))*N17 -> 0 | S17: No | T17: 3-Posible | U17: =+IF(R17="","",IF(R17<50001,1,IF(R17<200001,2,IF(R17<500001,3,IF(R17<1000001,4,5))))) -> 1 | V17: 1 | Z17: =MAX(U17:Y17) -> 1 | AA17: =IF(Z17=1,VLOOKUP(T17,$AH$3:$AI$7,2,FALSE),IF(Z17=2,VLOOKUP(T17,$AH$8:$AI$12,2, FALSE),IF(Z17=3,VLOOKUP(T17,$AH$13:$AI$17,2,FALSE),IF(Z17=4,VLOOKUP(T17,$AH$18:$AI$22,2,FALSE),IF(Z17=5,VLOOKUP(T17,$AH$23:$AI$27,2,FALSE),""))))) -> Bajo | AB17: =IF(T17="1-Raro",IF(Z17=1,1,IF(Z17=2,3,IF(Z17=3,6,IF(Z17=4,10,15)))),IF(T17="2-Improbable",IF(Z17=1,2,IF(Z17=2,5,IF(Z17=3,9,IF(Z17=4,14,19)))),IF(T17="3-Posible",IF(Z17=1,4,IF(Z17=2,8,IF(Z17=3,13,IF(Z17=4,18,21)))),IF(T17="4-Probable",IF(Z17=1,7,IF(Z17=2,12,IF(Z17=3,17,IF(Z17=4,22,23)))),IF(T17="5-Casi Seguro",IF(Z17=1,11,IF(Z17=2,16,IF(Z17=3,20,IF(Z17=4,24,25))))))))) -> 4 | AC17: =((VLOOKUP(T17,$AH$3:$AJ$7,3,FALSE)*SQRT(U17^2+V17^2+W17^2+X17^2+Y17^2))/(5*SQRT((5)*5^2))) -> 0.075894664 | AH17: 1-Raro | AI17: Bajo
A18: 2100 Chancado Primario & Acopio Mineral Mina | B18: 2110 Estación de chancador primario | C18: Chute descarga correa | D18: 2110CH0005 | E18: Chute descarga correa | F18: Recepcionar el producto descargado de correa descarga de chancador 2120-CV-0001 y alimentar la correa alimentación de acopio 2110-CV-0002 | G18: Rotura de chute | H18: No afectación a producción, Parada de chancador de mandíbula, Detención de correa, Costos por reparación de chute | I18: 1 | J18: 1 | K18: =+IF(I18="","",IF((I18-J18)>0,"Si","No")) -> No | L18: Ninguna | M18: 0.41666667 | N18: 1 | O18: 70 | P18: 10 | Q18: =+IF(M18="","",(IF(((M18*24)-P18)<0,0,(M18*24)-P18)*N18)) -> 0 | R18: =+(IF(((M18*24)-P18)<0,0,((M18*24)-P18)*'Estimación de pérdidas'!$F$72))*N18 -> 0 | S18: No | T18: 3-Posible | U18: =+IF(R18="","",IF(R18<50001,1,IF(R18<200001,2,IF(R18<500001,3,IF(R18<1000001,4,5))))) -> 1 | V18: 1 | Z18: =MAX(U18:Y18) -> 1 | AA18: =IF(Z18=1,VLOOKUP(T18,$AH$3:$AI$7,2,FALSE),IF(Z18=2,VLOOKUP(T18,$AH$8:$AI$12,2, FALSE),IF(Z18=3,VLOOKUP(T18,$AH$13:$AI$17,2,FALSE),IF(Z18=4,VLOOKUP(T18,$AH$18:$AI$22,2,FALSE),IF(Z18=5,VLOOKUP(T18,$AH$23:$AI$27,2,FALSE),""))))) -> Bajo | AB18: =IF(T18="1-Raro",IF(Z18=1,1,IF(Z18=2,3,IF(Z18=3,6,IF(Z18=4,10,15)))),IF(T18="2-Improbable",IF(Z18=1,2,IF(Z18=2,5,IF(Z18=3,9,IF(Z18=4,14,19)))),IF(T18="3-Posible",IF(Z18=1,4,IF(Z18=2,8,IF(Z18=3,13,IF(Z18=4,18,21)))),IF(T18="4-Probable",IF(Z18=1,7,IF(Z18=2,12,IF(Z18=3,17,IF(Z18=4,22,23)))),IF(T18="5-Casi Seguro",IF(Z18=1,11,IF(Z18=2,16,IF(Z18=3,20,IF(Z18=4,24,25))))))))) -> 4 | AC18: =((VLOOKUP(T18,$AH$3:$AJ$7,3,FALSE)*SQRT(U18^2+V18^2+W18^2+X18^2+Y18^2))/(5*SQRT((5)*5^2))) -> 0.075894664 | AH18: 5-Casi seguro | AI18: Alto
A19: 2100 Chancado Primario & Acopio Mineral Mina | B19: 2110 Estación de chancador primario | C19: Puente grúa Chancador | D19: 2110CN0003 | E19: Puente grúa chancador | F19: Izar y desplazar cargas en el área de chancado primario | G19: Falla de cable | H19: Fatalidad o incapacidad permanente a una persona, No afectación a operaciones, Cambio de cable | I19: 1 | J19: 1 | K19: =+IF(I19="","",IF((I19-J19)>0,"Si","No")) -> No | L19: Ninguna | M19: 0.5 | N19: 0 | P19: 0 | Q19: =+IF(M19="","",(IF(((M19*24)-P19)<0,0,(M19*24)-P19)*N19)) -> 0 | R19: =+(IF(((M19*24)-P19)<0,0,((M19*24)-P19)*'Estimación de pérdidas'!$F$72))*N19 -> 0 | S19: No | T19: 2-Improbable | U19: =+IF(R19="","",IF(R19<50001,1,IF(R19<200001,2,IF(R19<500001,3,IF(R19<1000001,4,5))))) -> 1 | V19: 2 | W19: 4 | Z19: =MAX(U19:Y19) -> 4 | AA19: =IF(Z19=1,VLOOKUP(T19,$AH$3:$AI$7,2,FALSE),IF(Z19=2,VLOOKUP(T19,$AH$8:$AI$12,2, FALSE),IF(Z19=3,VLOOKUP(T19,$AH$13:$AI$17,2,FALSE),IF(Z19=4,VLOOKUP(T19,$AH$18:$AI$22,2,FALSE),IF(Z19=5,VLOOKUP(T19,$AH$23:$AI$27,2,FALSE),""))))) -> Moderado | AB19: =IF(T19="1-Raro",IF(Z19=1,1,IF(Z19=2,3,IF(Z19=3,6,IF(Z19=4,10,15)))),IF(T19="2-Improbable",IF(Z19=1,2,IF(Z19=2,5,IF(Z19=3,9,IF(Z19=4,14,19)))),IF(T19="3-Posible",IF(Z19=1,4,IF(Z19=2,8,IF(Z19=3,13,IF(Z19=4,18,21)))),IF(T19="4-Probable",IF(Z19=1,7,IF(Z19=2,12,IF(Z19=3,17,IF(Z19=4,22,23)))),IF(T19="5-Casi Seguro",IF(Z19=1,11,IF(Z19=2,16,IF(Z19=3,20,IF(Z19=4,24,25))))))))) -> 14 | AC19: =((VLOOKUP(T19,$AH$3:$AJ$7,3,FALSE)*SQRT(U19^2+V19^2+W19^2+X19^2+Y19^2))/(5*SQRT((5)*5^2))) -> 0.16395121 | AH19: 4-Probable | AI19: Alto
A20: 2100 Chancado Primario & Acopio Mineral Mina | B20: 2110 Estación de chancador primario | C20: Puente grúa tolva ROM | D20: 2110CN0022 | E20: Puente grúa tolva ROM | F20: Izaje y traslado de cargas en tolva room 2110BN0001 | G20: Falla de cable | H20: Fatalidad o incapacidad permanente a una persona, No afectación a operaciones, Cambio de cable | I20: 1 | J20: 1 | K20: =+IF(I20="","",IF((I20-J20)>0,"Si","No")) -> No | L20: Ninguna | M20: 0.5 | N20: 0 | P20: 0 | Q20: =+IF(M20="","",(IF(((M20*24)-P20)<0,0,(M20*24)-P20)*N20)) -> 0 | R20: =+(IF(((M20*24)-P20)<0,0,((M20*24)-P20)*'Estimación de pérdidas'!$F$72))*N20 -> 0 | S20: No | T20: 2-Improbable | U20: =+IF(R20="","",IF(R20<50001,1,IF(R20<200001,2,IF(R20<500001,3,IF(R20<1000001,4,5))))) -> 1 | V20: 2 | W20: 4 | Z20: =MAX(U20:Y20) -> 4 | AA20: =IF(Z20=1,VLOOKUP(T20,$AH$3:$AI$7,2,FALSE),IF(Z20=2,VLOOKUP(T20,$AH$8:$AI$12,2, FALSE),IF(Z20=3,VLOOKUP(T20,$AH$13:$AI$17,2,FALSE),IF(Z20=4,VLOOKUP(T20,$AH$18:$AI$22,2,FALSE),IF(Z20=5,VLOOKUP(T20,$AH$23:$AI$27,2,FALSE),""))))) -> Moderado | AB20: =IF(T20="1-Raro",IF(Z20=1,1,IF(Z20=2,3,IF(Z20=3,6,IF(Z20=4,10,15)))),IF(T20="2-Improbable",IF(Z20=1,2,IF(Z20=2,5,IF(Z20=3,9,IF(Z20=4,14,19)))),IF(T20="3-Posible",IF(Z20=1,4,IF(Z20=2,8,IF(Z20=3,13,IF(Z20=4,18,21)))),IF(T20="4-Probable",IF(Z20=1,7,IF(Z20=2,12,IF(Z20=3,17,IF(Z20=4,22,23)))),IF(T20="5-Casi Seguro",IF(Z20=1,11,IF(Z20=2,16,IF(Z20=3,20,IF(Z20=4,24,25))))))))) -> 14 | AC20: =((VLOOKUP(T20,$AH$3:$AJ$7,3,FALSE)*SQRT(U20^2+V20^2+W20^2+X20^2+Y20^2))/(5*SQRT((5)*5^2))) -> 0.16395121 | AH20: 3-Posible | AI20: Moderado
A21: 2100 Chancado Primario & Acopio Mineral Mina | B21: 2110 Estación de chancador primario | C21: Compresor aire de Chancado | D21: 2110CP0003 | E21: Compresor de aire Chancado | F21: Comprimir el aire, alimentar el acumulador 2110AR0001 y posteriormente alimentar el supresor de polvo 2110DT0001 | G21: Falla de compresor | H21: Área contaminada de polvo sin efectos posteriores en salud de personas, No afectación a producción, Costos por cambio de compresor | I21: 1 | J21: 1 | K21: =+IF(I21="","",IF((I21-J21)>0,"Si","No")) -> No | L21: Ninguna | M21: 1 | N21: 0 | O21: 70 | P21: 10 | Q21: =+IF(M21="","",(IF(((M21*24)-P21)<0,0,(M21*24)-P21)*N21)) -> 0 | R21: =+(IF(((M21*24)-P21)<0,0,((M21*24)-P21)*'Estimación de pérdidas'!$F$72))*N21 -> 0 | S21: No | T21: 2-Improbable | U21: =+IF(R21="","",IF(R21<50001,1,IF(R21<200001,2,IF(R21<500001,3,IF(R21<1000001,4,5))))) -> 1 | V21: 1 | Z21: =MAX(U21:Y21) -> 1 | AA21: =IF(Z21=1,VLOOKUP(T21,$AH$3:$AI$7,2,FALSE),IF(Z21=2,VLOOKUP(T21,$AH$8:$AI$12,2, FALSE),IF(Z21=3,VLOOKUP(T21,$AH$13:$AI$17,2,FALSE),IF(Z21=4,VLOOKUP(T21,$AH$18:$AI$22,2,FALSE),IF(Z21=5,VLOOKUP(T21,$AH$23:$AI$27,2,FALSE),""))))) -> Bajo | AB21: =IF(T21="1-Raro",IF(Z21=1,1,IF(Z21=2,3,IF(Z21=3,6,IF(Z21=4,10,15)))),IF(T21="2-Improbable",IF(Z21=1,2,IF(Z21=2,5,IF(Z21=3,9,IF(Z21=4,14,19)))),IF(T21="3-Posible",IF(Z21=1,4,IF(Z21=2,8,IF(Z21=3,13,IF(Z21=4,18,21)))),IF(T21="4-Probable",IF(Z21=1,7,IF(Z21=2,12,IF(Z21=3,17,IF(Z21=4,22,23)))),IF(T21="5-Casi Seguro",IF(Z21=1,11,IF(Z21=2,16,IF(Z21=3,20,IF(Z21=4,24,25))))))))) -> 2 | AC21: =((VLOOKUP(T21,$AH$3:$AJ$7,3,FALSE)*SQRT(U21^2+V21^2+W21^2+X21^2+Y21^2))/(5*SQRT((5)*5^2))) -> 0.050596443 | AH21: 2-Improbable | AI21: Moderado
A22: 2100 Chancado Primario & Acopio Mineral Mina | B22: 2110 Estación de chancador primario | C22: Tecle chancador primario | D22: 2110HT0042 | E22: Tecle chancador primario | F22: Izar y desplazar cargas en el área de chancado primario | G22: Falla de cableado / cadena | H22: No afectación a operaciones, Cambiar el tecle | I22: 1 | J22: 1 | K22: =+IF(I22="","",IF((I22-J22)>0,"Si","No")) -> No | L22: Ninguna | M22: 0.33333333 | N22: 0 | P22: 0 | Q22: =+IF(M22="","",(IF(((M22*24)-P22)<0,0,(M22*24)-P22)*N22)) -> 0 | R22: =+(IF(((M22*24)-P22)<0,0,((M22*24)-P22)*'Estimación de pérdidas'!$F$72))*N22 -> 0 | S22: No | T22: 3-Posible | U22: =+IF(R22="","",IF(R22<50001,1,IF(R22<200001,2,IF(R22<500001,3,IF(R22<1000001,4,5))))) -> 1 | V22: 1 | Z22: =MAX(U22:Y22) -> 1 | AA22: =IF(Z22=1,VLOOKUP(T22,$AH$3:$AI$7,2,FALSE),IF(Z22=2,VLOOKUP(T22,$AH$8:$AI$12,2, FALSE),IF(Z22=3,VLOOKUP(T22,$AH$13:$AI$17,2,FALSE),IF(Z22=4,VLOOKUP(T22,$AH$18:$AI$22,2,FALSE),IF(Z22=5,VLOOKUP(T22,$AH$23:$AI$27,2,FALSE),""))))) -> Bajo | AB22: =IF(T22="1-Raro",IF(Z22=1,1,IF(Z22=2,3,IF(Z22=3,6,IF(Z22=4,10,15)))),IF(T22="2-Improbable",IF(Z22=1,2,IF(Z22=2,5,IF(Z22=3,9,IF(Z22=4,14,19)))),IF(T22="3-Posible",IF(Z22=1,4,IF(Z22=2,8,IF(Z22=3,13,IF(Z22=4,18,21)))),IF(T22="4-Probable",IF(Z22=1,7,IF(Z22=2,12,IF(Z22=3,17,IF(Z22=4,22,23)))),IF(T22="5-Casi Seguro",IF(Z22=1,11,IF(Z22=2,16,IF(Z22=3,20,IF(Z22=4,24,25))))))))) -> 4 | AC22: =((VLOOKUP(T22,$AH$3:$AJ$7,3,FALSE)*SQRT(U22^2+V22^2+W22^2+X22^2+Y22^2))/(5*SQRT((5)*5^2))) -> 0.075894664 | AH22: 1-Raro | AI22: Moderado
A23: 2100 Chancado Primario & Acopio Mineral Mina | B23: 2110 Estación de chancador primario | C23: Bomba agua supresión de polvo | D23: 2110PU0043 | E23: Bomba agua supresión polvo | F23: Transferir agua de estanque 2110TK0007 a supresor de polvo 2110DT0001 | G23: Falla de bomba hidráulica | H23: Área contaminada de polvo sin efectos posteriores en salud de personas, No afectación en producción, Costo asociados a cambio de bomba | I23: 1 | J23: 1 | K23: =+IF(I23="","",IF((I23-J23)>0,"Si","No")) -> No | L23: Ninguna | M23: 0.25 | N23: 0 | O23: 70 | P23: 10 | Q23: =+IF(M23="","",(IF(((M23*24)-P23)<0,0,(M23*24)-P23)*N23)) -> 0 | R23: =+(IF(((M23*24)-P23)<0,0,((M23*24)-P23)*'Estimación de pérdidas'!$F$72))*N23 -> 0 | S23: No | T23: 4-Probable | U23: =+IF(R23="","",IF(R23<50001,1,IF(R23<200001,2,IF(R23<500001,3,IF(R23<1000001,4,5))))) -> 1 | V23: 1 | Z23: =MAX(U23:Y23) -> 1 | AA23: =IF(Z23=1,VLOOKUP(T23,$AH$3:$AI$7,2,FALSE),IF(Z23=2,VLOOKUP(T23,$AH$8:$AI$12,2, FALSE),IF(Z23=3,VLOOKUP(T23,$AH$13:$AI$17,2,FALSE),IF(Z23=4,VLOOKUP(T23,$AH$18:$AI$22,2,FALSE),IF(Z23=5,VLOOKUP(T23,$AH$23:$AI$27,2,FALSE),""))))) -> Bajo | AB23: =IF(T23="1-Raro",IF(Z23=1,1,IF(Z23=2,3,IF(Z23=3,6,IF(Z23=4,10,15)))),IF(T23="2-Improbable",IF(Z23=1,2,IF(Z23=2,5,IF(Z23=3,9,IF(Z23=4,14,19)))),IF(T23="3-Posible",IF(Z23=1,4,IF(Z23=2,8,IF(Z23=3,13,IF(Z23=4,18,21)))),IF(T23="4-Probable",IF(Z23=1,7,IF(Z23=2,12,IF(Z23=3,17,IF(Z23=4,22,23)))),IF(T23="5-Casi Seguro",IF(Z23=1,11,IF(Z23=2,16,IF(Z23=3,20,IF(Z23=4,24,25))))))))) -> 7 | AC23: =((VLOOKUP(T23,$AH$3:$AJ$7,3,FALSE)*SQRT(U23^2+V23^2+W23^2+X23^2+Y23^2))/(5*SQRT((5)*5^2))) -> 0.10119289 | AH23: 5-Casi seguro | AI23: Alto
A24: 2100 Chancado Primario & Acopio Mineral Mina | B24: 2110 Estación de chancador primario | C24: Estanque de agua fresca Chancado | D24: 2110TK0007 | E24: Estanque agua fresca chancador | F24: Almacenar agua fresca proveniente de 4100TK0042 para alimentar a través de 2110PU0043 el supresor de polvo 2110DT0001 | G24: Falla de contención de tanque | H24: No afectación a producción, Reparación de estructura de estanque | I24: 1 | J24: 1 | K24: =+IF(I24="","",IF((I24-J24)>0,"Si","No")) -> No | L24: Ninguna | M24: 1 | N24: 0 | O24: 70 | P24: 10 | Q24: =+IF(M24="","",(IF(((M24*24)-P24)<0,0,(M24*24)-P24)*N24)) -> 0 | R24: =+(IF(((M24*24)-P24)<0,0,((M24*24)-P24)*'Estimación de pérdidas'!$F$72))*N24 -> 0 | S24: No | T24: 2-Improbable | U24: =+IF(R24="","",IF(R24<50001,1,IF(R24<200001,2,IF(R24<500001,3,IF(R24<1000001,4,5))))) -> 1 | V24: 1 | Z24: =MAX(U24:Y24) -> 1 | AA24: =IF(Z24=1,VLOOKUP(T24,$AH$3:$AI$7,2,FALSE),IF(Z24=2,VLOOKUP(T24,$AH$8:$AI$12,2, FALSE),IF(Z24=3,VLOOKUP(T24,$AH$13:$AI$17,2,FALSE),IF(Z24=4,VLOOKUP(T24,$AH$18:$AI$22,2,FALSE),IF(Z24=5,VLOOKUP(T24,$AH$23:$AI$27,2,FALSE),""))))) -> Bajo | AB24: =IF(T24="1-Raro",IF(Z24=1,1,IF(Z24=2,3,IF(Z24=3,6,IF(Z24=4,10,15)))),IF(T24="2-Improbable",IF(Z24=1,2,IF(Z24=2,5,IF(Z24=3,9,IF(Z24=4,14,19)))),IF(T24="3-Posible",IF(Z24=1,4,IF(Z24=2,8,IF(Z24=3,13,IF(Z24=4,18,21)))),IF(T24="4-Probable",IF(Z24=1,7,IF(Z24=2,12,IF(Z24=3,17,IF(Z24=4,22,23)))),IF(T24="5-Casi Seguro",IF(Z24=1,11,IF(Z24=2,16,IF(Z24=3,20,IF(Z24=4,24,25))))))))) -> 2 | AC24: =((VLOOKUP(T24,$AH$3:$AJ$7,3,FALSE)*SQRT(U24^2+V24^2+W24^2+X24^2+Y24^2))/(5*SQRT((5)*5^2))) -> 0.050596443 | AH24: 4-Probable | AI24: Alto
A25: 2100 Chancado Primario & Acopio Mineral Mina | B25: 2120 Alimentación acopio de gruesos | C25: Chute alimentación acopio | D25: 2120CH0006 | E25: Chute alimentación acopio | F25: Alimentar el acopio de mineral con la descarga recibida de correa alimentación acopio 2120-CV-0002. El acopio de mineral permite alimentar a la planta de manera continua, hasta 10 horas después de cualquier parada del sistema de chancado (capacidad viva de 2.900 t). | G25: Rotura de chute | H25: No afectación a producción, Parada de chancador de mandíbula, Costos por reparación de chute | I25: 1 | J25: 1 | K25: =+IF(I25="","",IF((I25-J25)>0,"Si","No")) -> No | L25: Ninguna | M25: 0.41666667 | N25: 1 | O25: 70 | P25: 10 | Q25: =+IF(M25="","",(IF(((M25*24)-P25)<0,0,(M25*24)-P25)*N25)) -> 0 | R25: =+(IF(((M25*24)-P25)<0,0,((M25*24)-P25)*'Estimación de pérdidas'!$F$72))*N25 -> 0 | S25: No | T25: 3-Posible | U25: =+IF(R25="","",IF(R25<50001,1,IF(R25<200001,2,IF(R25<500001,3,IF(R25<1000001,4,5))))) -> 1 | V25: 1 | Z25: =MAX(U25:Y25) -> 1 | AA25: =IF(Z25=1,VLOOKUP(T25,$AH$3:$AI$7,2,FALSE),IF(Z25=2,VLOOKUP(T25,$AH$8:$AI$12,2, FALSE),IF(Z25=3,VLOOKUP(T25,$AH$13:$AI$17,2,FALSE),IF(Z25=4,VLOOKUP(T25,$AH$18:$AI$22,2,FALSE),IF(Z25=5,VLOOKUP(T25,$AH$23:$AI$27,2,FALSE),""))))) -> Bajo | AB25: =IF(T25="1-Raro",IF(Z25=1,1,IF(Z25=2,3,IF(Z25=3,6,IF(Z25=4,10,15)))),IF(T25="2-Improbable",IF(Z25=1,2,IF(Z25=2,5,IF(Z25=3,9,IF(Z25=4,14,19)))),IF(T25="3-Posible",IF(Z25=1,4,IF(Z25=2,8,IF(Z25=3,13,IF(Z25=4,18,21)))),IF(T25="4-Probable",IF(Z25=1,7,IF(Z25=2,12,IF(Z25=3,17,IF(Z25=4,22,23)))),IF(T25="5-Casi Seguro",IF(Z25=1,11,IF(Z25=2,16,IF(Z25=3,20,IF(Z25=4,24,25))))))))) -> 4 | AC25: =((VLOOKUP(T25,$AH$3:$AJ$7,3,FALSE)*SQRT(U25^2+V25^2+W25^2+X25^2+Y25^2))/(5*SQRT((5)*5^2))) -> 0.075894664 | AH25: 3-Posible | AI25: Alto
A26: 2100 Chancado Primario & Acopio Mineral Mina | B26: 2120 Alimentación acopio de gruesos | C26: Sistema bajada polea cabeza (tecle + motor eléctrico) | D26: 2120ME0004 | E26: Sistema bajada polea cabeza | F26: Bajar polea cabeza de correa para mantención | G26: Falla de cableado / cadena | H26: No afectación a operaciones, Cambiar el tecle | I26: 1 | J26: 1 | K26: =+IF(I26="","",IF((I26-J26)>0,"Si","No")) -> No | L26: Ninguna | M26: 0.25 | N26: 0 | P26: 0 | Q26: =+IF(M26="","",(IF(((M26*24)-P26)<0,0,(M26*24)-P26)*N26)) -> 0 | R26: =+(IF(((M26*24)-P26)<0,0,((M26*24)-P26)*'Estimación de pérdidas'!$F$72))*N26 -> 0 | S26: No | T26: 3-Posible | U26: =+IF(R26="","",IF(R26<50001,1,IF(R26<200001,2,IF(R26<500001,3,IF(R26<1000001,4,5))))) -> 1 | V26: 1 | Z26: =MAX(U26:Y26) -> 1 | AA26: =IF(Z26=1,VLOOKUP(T26,$AH$3:$AI$7,2,FALSE),IF(Z26=2,VLOOKUP(T26,$AH$8:$AI$12,2, FALSE),IF(Z26=3,VLOOKUP(T26,$AH$13:$AI$17,2,FALSE),IF(Z26=4,VLOOKUP(T26,$AH$18:$AI$22,2,FALSE),IF(Z26=5,VLOOKUP(T26,$AH$23:$AI$27,2,FALSE),""))))) -> Bajo | AB26: =IF(T26="1-Raro",IF(Z26=1,1,IF(Z26=2,3,IF(Z26=3,6,IF(Z26=4,10,15)))),IF(T26="2-Improbable",IF(Z26=1,2,IF(Z26=2,5,IF(Z26=3,9,IF(Z26=4,14,19)))),IF(T26="3-Posible",IF(Z26=1,4,IF(Z26=2,8,IF(Z26=3,13,IF(Z26=4,18,21)))),IF(T26="4-Probable",IF(Z26=1,7,IF(Z26=2,12,IF(Z26=3,17,IF(Z26=4,22,23)))),IF(T26="5-Casi Seguro",IF(Z26=1,11,IF(Z26=2,16,IF(Z26=3,20,IF(Z26=4,24,25))))))))) -> 4 | AC26: =((VLOOKUP(T26,$AH$3:$AJ$7,3,FALSE)*SQRT(U26^2+V26^2+W26^2+X26^2+Y26^2))/(5*SQRT((5)*5^2))) -> 0.075894664 | AH26: 2-Improbable | AI26: Alto
A27: 2200 Pila acopio de gruesos | B27: 2210 Acopio de gruesos & sistema recuperación | C27: Chute descarga acopio | D27: 2210CH0014 | E27: Chute descarga acopio | F27: Recepcionar material chancado del acopio de mineral y conducir a alimentador placas 2210FE0001 | G27: Rotura de chute | H27: No afectación directa a operación, Parada de feeder 2210FE0001, Costos por reparación de chute | I27: 1 | J27: 1 | K27: =+IF(I27="","",IF((I27-J27)>0,"Si","No")) -> No | L27: Ninguna | M27: 0.41666667 | N27: 0.2 | O27: 91.32 | P27: 1 | Q27: =+IF(M27="","",(IF(((M27*24)-P27)<0,0,(M27*24)-P27)*N27)) -> 1.8 | R27: =+(IF(((M27*24)-P27)<0,0,((M27*24)-P27)*'Estimación de pérdidas'!$F$72))*N27 -> 103820.53 | S27: No | T27: 3-Posible | U27: =+IF(R27="","",IF(R27<50001,1,IF(R27<200001,2,IF(R27<500001,3,IF(R27<1000001,4,5))))) -> 2 | V27: 1 | Z27: =MAX(U27:Y27) -> 2 | AA27: =IF(Z27=1,VLOOKUP(T27,$AH$3:$AI$7,2,FALSE),IF(Z27=2,VLOOKUP(T27,$AH$8:$AI$12,2, FALSE),IF(Z27=3,VLOOKUP(T27,$AH$13:$AI$17,2,FALSE),IF(Z27=4,VLOOKUP(T27,$AH$18:$AI$22,2,FALSE),IF(Z27=5,VLOOKUP(T27,$AH$23:$AI$27,2,FALSE),""))))) -> Moderado | AB27: =IF(T27="1-Raro",IF(Z27=1,1,IF(Z27=2,3,IF(Z27=3,6,IF(Z27=4,10,15)))),IF(T27="2-Improbable",IF(Z27=1,2,IF(Z27=2,5,IF(Z27=3,9,IF(Z27=4,14,19)))),IF(T27="3-Posible",IF(Z27=1,4,IF(Z27=2,8,IF(Z27=3,13,IF(Z27=4,18,21)))),IF(T27="4-Probable",IF(Z27=1,7,IF(Z27=2,12,IF(Z27=3,17,IF(Z27=4,22,23)))),IF(T27="5-Casi Seguro",IF(Z27=1,11,IF(Z27=2,16,IF(Z27=3,20,IF(Z27=4,24,25))))))))) -> 8 | AC27: =((VLOOKUP(T27,$AH$3:$AJ$7,3,FALSE)*SQRT(U27^2+V27^2+W27^2+X27^2+Y27^2))/(5*SQRT((5)*5^2))) -> 0.12 | AH27: 1-Raro | AI27: Moderado
A28: 2200 Pila acopio de gruesos | B28: 2210 Acopio de gruesos & sistema recuperación | C28: Chute descarga acopio | D28: 2210CH0015 | E28: Chute descarga acopio | F28: Recepcionar material chancado del acopio de mineral y conducir a alimentador placas 2210FE0002 | G28: Rotura de chute | H28: No afectación directa a operación, Parada de feeder 2210FE0002, Costos por reparación de chute | I28: 1 | J28: 1 | K28: =+IF(I28="","",IF((I28-J28)>0,"Si","No")) -> No | L28: Ninguna | M28: 0.41666667 | N28: 0.2 | O28: 91.32 | P28: 1 | Q28: =+IF(M28="","",(IF(((M28*24)-P28)<0,0,(M28*24)-P28)*N28)) -> 1.8 | R28: =+(IF(((M28*24)-P28)<0,0,((M28*24)-P28)*'Estimación de pérdidas'!$F$72))*N28 -> 103820.53 | S28: No | T28: 3-Posible | U28: =+IF(R28="","",IF(R28<50001,1,IF(R28<200001,2,IF(R28<500001,3,IF(R28<1000001,4,5))))) -> 2 | V28: 1 | Z28: =MAX(U28:Y28) -> 2 | AA28: =IF(Z28=1,VLOOKUP(T28,$AH$3:$AI$7,2,FALSE),IF(Z28=2,VLOOKUP(T28,$AH$8:$AI$12,2, FALSE),IF(Z28=3,VLOOKUP(T28,$AH$13:$AI$17,2,FALSE),IF(Z28=4,VLOOKUP(T28,$AH$18:$AI$22,2,FALSE),IF(Z28=5,VLOOKUP(T28,$AH$23:$AI$27,2,FALSE),""))))) -> Moderado | AB28: =IF(T28="1-Raro",IF(Z28=1,1,IF(Z28=2,3,IF(Z28=3,6,IF(Z28=4,10,15)))),IF(T28="2-Improbable",IF(Z28=1,2,IF(Z28=2,5,IF(Z28=3,9,IF(Z28=4,14,19)))),IF(T28="3-Posible",IF(Z28=1,4,IF(Z28=2,8,IF(Z28=3,13,IF(Z28=4,18,21)))),IF(T28="4-Probable",IF(Z28=1,7,IF(Z28=2,12,IF(Z28=3,17,IF(Z28=4,22,23)))),IF(T28="5-Casi Seguro",IF(Z28=1,11,IF(Z28=2,16,IF(Z28=3,20,IF(Z28=4,24,25))))))))) -> 8 | AC28: =((VLOOKUP(T28,$AH$3:$AJ$7,3,FALSE)*SQRT(U28^2+V28^2+W28^2+X28^2+Y28^2))/(5*SQRT((5)*5^2))) -> 0.12
A29: 2200 Pila acopio de gruesos | B29: 2210 Acopio de gruesos & sistema recuperación | C29: Sistema de lanzas | D29: 2210ME0001 | E29: Sistema de lanzas | F29: Bloquear o habilitar la descarga de chute 2210CH0069 y alimentar apron feeder 2210FE0001 | G29: Falla en cilindro hidráulico | H29: Afectación no directa a operaciones (20%), Detención de feeder 2210FE0001, Costos por cambio de cilindro hidráulico | I29: 1 | J29: 1 | K29: =+IF(I29="","",IF((I29-J29)>0,"Si","No")) -> No | L29: Ninguna | M29: 0.25 | N29: 0.5 | O29: 91.32 | P29: 1 | Q29: =+IF(M29="","",(IF(((M29*24)-P29)<0,0,(M29*24)-P29)*N29)) -> 2.5 | R29: =+(IF(((M29*24)-P29)<0,0,((M29*24)-P29)*'Estimación de pérdidas'!$F$72))*N29 -> 144195.19 | S29: No | T29: 3-Posible | U29: =+IF(R29="","",IF(R29<50001,1,IF(R29<200001,2,IF(R29<500001,3,IF(R29<1000001,4,5))))) -> 2 | V29: 1 | Z29: =MAX(U29:Y29) -> 2 | AA29: =IF(Z29=1,VLOOKUP(T29,$AH$3:$AI$7,2,FALSE),IF(Z29=2,VLOOKUP(T29,$AH$8:$AI$12,2, FALSE),IF(Z29=3,VLOOKUP(T29,$AH$13:$AI$17,2,FALSE),IF(Z29=4,VLOOKUP(T29,$AH$18:$AI$22,2,FALSE),IF(Z29=5,VLOOKUP(T29,$AH$23:$AI$27,2,FALSE),""))))) -> Moderado | AB29: =IF(T29="1-Raro",IF(Z29=1,1,IF(Z29=2,3,IF(Z29=3,6,IF(Z29=4,10,15)))),IF(T29="2-Improbable",IF(Z29=1,2,IF(Z29=2,5,IF(Z29=3,9,IF(Z29=4,14,19)))),IF(T29="3-Posible",IF(Z29=1,4,IF(Z29=2,8,IF(Z29=3,13,IF(Z29=4,18,21)))),IF(T29="4-Probable",IF(Z29=1,7,IF(Z29=2,12,IF(Z29=3,17,IF(Z29=4,22,23)))),IF(T29="5-Casi Seguro",IF(Z29=1,11,IF(Z29=2,16,IF(Z29=3,20,IF(Z29=4,24,25))))))))) -> 8 | AC29: =((VLOOKUP(T29,$AH$3:$AJ$7,3,FALSE)*SQRT(U29^2+V29^2+W29^2+X29^2+Y29^2))/(5*SQRT((5)*5^2))) -> 0.12
A30: 2200 Pila acopio de gruesos | B30: 2210 Acopio de gruesos & sistema recuperación | C30: Sistema de lanzas | D30: 2210ME0002 | E30: Sistema de lanzas | F30: Bloquear o habilitar la descarga de chute 2210CH0070 y alimentar apron feeder 2210FE0002 | G30: Falla en cilindro hidráulico | H30: Afectación no directa a operaciones (20%), Detención de feeder 2210FE0001, Costos por cambio de cilindro hidráulico | I30: 1 | J30: 1 | K30: =+IF(I30="","",IF((I30-J30)>0,"Si","No")) -> No | L30: Ninguna | M30: 0.25 | N30: 0.5 | O30: 91.32 | P30: 1 | Q30: =+IF(M30="","",(IF(((M30*24)-P30)<0,0,(M30*24)-P30)*N30)) -> 2.5 | R30: =+(IF(((M30*24)-P30)<0,0,((M30*24)-P30)*'Estimación de pérdidas'!$F$72))*N30 -> 144195.19 | S30: No | T30: 3-Posible | U30: =+IF(R30="","",IF(R30<50001,1,IF(R30<200001,2,IF(R30<500001,3,IF(R30<1000001,4,5))))) -> 2 | V30: 1 | Z30: =MAX(U30:Y30) -> 2 | AA30: =IF(Z30=1,VLOOKUP(T30,$AH$3:$AI$7,2,FALSE),IF(Z30=2,VLOOKUP(T30,$AH$8:$AI$12,2, FALSE),IF(Z30=3,VLOOKUP(T30,$AH$13:$AI$17,2,FALSE),IF(Z30=4,VLOOKUP(T30,$AH$18:$AI$22,2,FALSE),IF(Z30=5,VLOOKUP(T30,$AH$23:$AI$27,2,FALSE),""))))) -> Moderado | AB30: =IF(T30="1-Raro",IF(Z30=1,1,IF(Z30=2,3,IF(Z30=3,6,IF(Z30=4,10,15)))),IF(T30="2-Improbable",IF(Z30=1,2,IF(Z30=2,5,IF(Z30=3,9,IF(Z30=4,14,19)))),IF(T30="3-Posible",IF(Z30=1,4,IF(Z30=2,8,IF(Z30=3,13,IF(Z30=4,18,21)))),IF(T30="4-Probable",IF(Z30=1,7,IF(Z30=2,12,IF(Z30=3,17,IF(Z30=4,22,23)))),IF(T30="5-Casi Seguro",IF(Z30=1,11,IF(Z30=2,16,IF(Z30=3,20,IF(Z30=4,24,25))))))))) -> 8 | AC30: =((VLOOKUP(T30,$AH$3:$AJ$7,3,FALSE)*SQRT(U30^2+V30^2+W30^2+X30^2+Y30^2))/(5*SQRT((5)*5^2))) -> 0.12
A31: 2200 Pila acopio de gruesos | B31: 2210 Acopio de gruesos & sistema recuperación | C31: Chute descarga alimentador | D31: 2210CH0018 | E31: Chute descarga alimentador | F31: Recepcionar mineral chancado de alimentador 2210-FE-0001 y descargar a 2210-CV-0003 correa alimentación Molino SAG | G31: Rotura de chute | H31: No afectación directa a operación, Parada de feeder 2210FE0001 que alimenta correa de Molino SAG, Costos por reparación de chute | I31: 1 | J31: 1 | K31: =+IF(I31="","",IF((I31-J31)>0,"Si","No")) -> No | L31: Ninguna | M31: 0.41666667 | N31: 0.2 | O31: 91.32 | P31: 1 | Q31: =+IF(M31="","",(IF(((M31*24)-P31)<0,0,(M31*24)-P31)*N31)) -> 1.8 | R31: =+(IF(((M31*24)-P31)<0,0,((M31*24)-P31)*'Estimación de pérdidas'!$F$72))*N31 -> 103820.53 | S31: No | T31: 3-Posible | U31: =+IF(R31="","",IF(R31<50001,1,IF(R31<200001,2,IF(R31<500001,3,IF(R31<1000001,4,5))))) -> 2 | V31: 1 | Z31: =MAX(U31:Y31) -> 2 | AA31: =IF(Z31=1,VLOOKUP(T31,$AH$3:$AI$7,2,FALSE),IF(Z31=2,VLOOKUP(T31,$AH$8:$AI$12,2, FALSE),IF(Z31=3,VLOOKUP(T31,$AH$13:$AI$17,2,FALSE),IF(Z31=4,VLOOKUP(T31,$AH$18:$AI$22,2,FALSE),IF(Z31=5,VLOOKUP(T31,$AH$23:$AI$27,2,FALSE),""))))) -> Moderado | AB31: =IF(T31="1-Raro",IF(Z31=1,1,IF(Z31=2,3,IF(Z31=3,6,IF(Z31=4,10,15)))),IF(T31="2-Improbable",IF(Z31=1,2,IF(Z31=2,5,IF(Z31=3,9,IF(Z31=4,14,19)))),IF(T31="3-Posible",IF(Z31=1,4,IF(Z31=2,8,IF(Z31=3,13,IF(Z31=4,18,21)))),IF(T31="4-Probable",IF(Z31=1,7,IF(Z31=2,12,IF(Z31=3,17,IF(Z31=4,22,23)))),IF(T31="5-Casi Seguro",IF(Z31=1,11,IF(Z31=2,16,IF(Z31=3,20,IF(Z31=4,24,25))))))))) -> 8 | AC31: =((VLOOKUP(T31,$AH$3:$AJ$7,3,FALSE)*SQRT(U31^2+V31^2+W31^2+X31^2+Y31^2))/(5*SQRT((5)*5^2))) -> 0.12
A32: 2200 Pila acopio de gruesos | B32: 2210 Acopio de gruesos & sistema recuperación | C32: Chute descarga alimentador | D32: 2210CH0019 | E32: Chute descarga alimentador | F32: Recepcionar mineral chancado de alimentador 2210-FE-0002 y descargar a 2210-CV-0003 correa alimentación Molino SAG | G32: Rotura de chute | H32: No afectación directa a operación, Parada de feeder 2210FE0002 que alimenta correa de Molino SAG, Costos por reparación de chute | I32: 1 | J32: 1 | K32: =+IF(I32="","",IF((I32-J32)>0,"Si","No")) -> No | L32: Ninguna | M32: 0.41666667 | N32: 0.2 | O32: 91.32 | P32: 1 | Q32: =+IF(M32="","",(IF(((M32*24)-P32)<0,0,(M32*24)-P32)*N32)) -> 1.8 | R32: =+(IF(((M32*24)-P32)<0,0,((M32*24)-P32)*'Estimación de pérdidas'!$F$72))*N32 -> 103820.53 | S32: No | T32: 3-Posible | U32: =+IF(R32="","",IF(R32<50001,1,IF(R32<200001,2,IF(R32<500001,3,IF(R32<1000001,4,5))))) -> 2 | V32: 1 | Z32: =MAX(U32:Y32) -> 2 | AA32: =IF(Z32=1,VLOOKUP(T32,$AH$3:$AI$7,2,FALSE),IF(Z32=2,VLOOKUP(T32,$AH$8:$AI$12,2, FALSE),IF(Z32=3,VLOOKUP(T32,$AH$13:$AI$17,2,FALSE),IF(Z32=4,VLOOKUP(T32,$AH$18:$AI$22,2,FALSE),IF(Z32=5,VLOOKUP(T32,$AH$23:$AI$27,2,FALSE),""))))) -> Moderado | AB32: =IF(T32="1-Raro",IF(Z32=1,1,IF(Z32=2,3,IF(Z32=3,6,IF(Z32=4,10,15)))),IF(T32="2-Improbable",IF(Z32=1,2,IF(Z32=2,5,IF(Z32=3,9,IF(Z32=4,14,19)))),IF(T32="3-Posible",IF(Z32=1,4,IF(Z32=2,8,IF(Z32=3,13,IF(Z32=4,18,21)))),IF(T32="4-Probable",IF(Z32=1,7,IF(Z32=2,12,IF(Z32=3,17,IF(Z32=4,22,23)))),IF(T32="5-Casi Seguro",IF(Z32=1,11,IF(Z32=2,16,IF(Z32=3,20,IF(Z32=4,24,25))))))))) -> 8 | AC32: =((VLOOKUP(T32,$AH$3:$AJ$7,3,FALSE)*SQRT(U32^2+V32^2+W32^2+X32^2+Y32^2))/(5*SQRT((5)*5^2))) -> 0.12
A33: 2200 Pila acopio de gruesos | B33: 2210 Acopio de gruesos & sistema recuperación | C33: Chute descarga correa | D33: 2210CH0021 | E33: Chute descarga correa | F33: Almacenar la descarga mineral grueso de correa alimentación SAG 2210CV0003 y posteriormente alimentar Molino SAG | G33: Rotura de chute | H33: Afectación a operaciones, Detención de correa alimentación SAG, Costos por reparación de chute | I33: 1 | J33: 1 | K33: =+IF(I33="","",IF((I33-J33)>0,"Si","No")) -> No | L33: Ninguna | M33: 0.41666667 | N33: 1 | O33: 91.32 | P33: 1 | Q33: =+IF(M33="","",(IF(((M33*24)-P33)<0,0,(M33*24)-P33)*N33)) -> 9 | R33: =+(IF(((M33*24)-P33)<0,0,((M33*24)-P33)*'Estimación de pérdidas'!$F$72))*N33 -> 519102.67 | S33: No | T33: 3-Posible | U33: =+IF(R33="","",IF(R33<50001,1,IF(R33<200001,2,IF(R33<500001,3,IF(R33<1000001,4,5))))) -> 4 | V33: 1 | Z33: =MAX(U33:Y33) -> 4 | AA33: =IF(Z33=1,VLOOKUP(T33,$AH$3:$AI$7,2,FALSE),IF(Z33=2,VLOOKUP(T33,$AH$8:$AI$12,2, FALSE),IF(Z33=3,VLOOKUP(T33,$AH$13:$AI$17,2,FALSE),IF(Z33=4,VLOOKUP(T33,$AH$18:$AI$22,2,FALSE),IF(Z33=5,VLOOKUP(T33,$AH$23:$AI$27,2,FALSE),""))))) -> Moderado | AB33: =IF(T33="1-Raro",IF(Z33=1,1,IF(Z33=2,3,IF(Z33=3,6,IF(Z33=4,10,15)))),IF(T33="2-Improbable",IF(Z33=1,2,IF(Z33=2,5,IF(Z33=3,9,IF(Z33=4,14,19)))),IF(T33="3-Posible",IF(Z33=1,4,IF(Z33=2,8,IF(Z33=3,13,IF(Z33=4,18,21)))),IF(T33="4-Probable",IF(Z33=1,7,IF(Z33=2,12,IF(Z33=3,17,IF(Z33=4,22,23)))),IF(T33="5-Casi Seguro",IF(Z33=1,11,IF(Z33=2,16,IF(Z33=3,20,IF(Z33=4,24,25))))))))) -> 18 | AC33: =((VLOOKUP(T33,$AH$3:$AJ$7,3,FALSE)*SQRT(U33^2+V33^2+W33^2+X33^2+Y33^2))/(5*SQRT((5)*5^2))) -> 0.22126907
A34: 2200 Pila acopio de gruesos | B34: 2210 Acopio de gruesos & sistema recuperación | C34: Chute descarga lanzas | D34: 2210CH0069 | E34: Chute descarga lanzas | F34: Almacenar material grueso proveniente de descarga de lanzas 2210ME0001 para alimentar apron feeder 2210FE0001 | G34: Rotura de chute | H34: Afectación no directa a operaciones (20%), Detención de feeder 2210FE0001, Costos por reparación de chute | I34: 1 | J34: 1 | K34: =+IF(I34="","",IF((I34-J34)>0,"Si","No")) -> No | L34: Ninguna | M34: 0.41666667 | N34: 0.2 | O34: 91.32 | P34: 1 | Q34: =+IF(M34="","",(IF(((M34*24)-P34)<0,0,(M34*24)-P34)*N34)) -> 1.8 | R34: =+(IF(((M34*24)-P34)<0,0,((M34*24)-P34)*'Estimación de pérdidas'!$F$72))*N34 -> 103820.53 | S34: No | T34: 3-Posible | U34: =+IF(R34="","",IF(R34<50001,1,IF(R34<200001,2,IF(R34<500001,3,IF(R34<1000001,4,5))))) -> 2 | V34: 1 | Z34: =MAX(U34:Y34) -> 2 | AA34: =IF(Z34=1,VLOOKUP(T34,$AH$3:$AI$7,2,FALSE),IF(Z34=2,VLOOKUP(T34,$AH$8:$AI$12,2, FALSE),IF(Z34=3,VLOOKUP(T34,$AH$13:$AI$17,2,FALSE),IF(Z34=4,VLOOKUP(T34,$AH$18:$AI$22,2,FALSE),IF(Z34=5,VLOOKUP(T34,$AH$23:$AI$27,2,FALSE),""))))) -> Moderado | AB34: =IF(T34="1-Raro",IF(Z34=1,1,IF(Z34=2,3,IF(Z34=3,6,IF(Z34=4,10,15)))),IF(T34="2-Improbable",IF(Z34=1,2,IF(Z34=2,5,IF(Z34=3,9,IF(Z34=4,14,19)))),IF(T34="3-Posible",IF(Z34=1,4,IF(Z34=2,8,IF(Z34=3,13,IF(Z34=4,18,21)))),IF(T34="4-Probable",IF(Z34=1,7,IF(Z34=2,12,IF(Z34=3,17,IF(Z34=4,22,23)))),IF(T34="5-Casi Seguro",IF(Z34=1,11,IF(Z34=2,16,IF(Z34=3,20,IF(Z34=4,24,25))))))))) -> 8 | AC34: =((VLOOKUP(T34,$AH$3:$AJ$7,3,FALSE)*SQRT(U34^2+V34^2+W34^2+X34^2+Y34^2))/(5*SQRT((5)*5^2))) -> 0.12
A35: 2200 Pila acopio de gruesos | B35: 2210 Acopio de gruesos & sistema recuperación | C35: Chute descarga lanzas | D35: 2210CH0070 | E35: Chute descarga lanzas | F35: Almacenar material grueso proveniente de descarga de lanzas 2210ME0002 para alimentar apron feeder 2210FE0002 | G35: Rotura de chute | H35: Afectación no directa a operaciones (20%), Detención de feeder 2210FE0002, Costos por reparación de chute | I35: 1 | J35: 1 | K35: =+IF(I35="","",IF((I35-J35)>0,"Si","No")) -> No | L35: Ninguna | M35: 0.41666667 | N35: 0.2 | O35: 91.32 | P35: 1 | Q35: =+IF(M35="","",(IF(((M35*24)-P35)<0,0,(M35*24)-P35)*N35)) -> 1.8 | R35: =+(IF(((M35*24)-P35)<0,0,((M35*24)-P35)*'Estimación de pérdidas'!$F$72))*N35 -> 103820.53 | S35: No | T35: 3-Posible | U35: =+IF(R35="","",IF(R35<50001,1,IF(R35<200001,2,IF(R35<500001,3,IF(R35<1000001,4,5))))) -> 2 | V35: 1 | Z35: =MAX(U35:Y35) -> 2 | AA35: =IF(Z35=1,VLOOKUP(T35,$AH$3:$AI$7,2,FALSE),IF(Z35=2,VLOOKUP(T35,$AH$8:$AI$12,2, FALSE),IF(Z35=3,VLOOKUP(T35,$AH$13:$AI$17,2,FALSE),IF(Z35=4,VLOOKUP(T35,$AH$18:$AI$22,2,FALSE),IF(Z35=5,VLOOKUP(T35,$AH$23:$AI$27,2,FALSE),""))))) -> Moderado | AB35: =IF(T35="1-Raro",IF(Z35=1,1,IF(Z35=2,3,IF(Z35=3,6,IF(Z35=4,10,15)))),IF(T35="2-Improbable",IF(Z35=1,2,IF(Z35=2,5,IF(Z35=3,9,IF(Z35=4,14,19)))),IF(T35="3-Posible",IF(Z35=1,4,IF(Z35=2,8,IF(Z35=3,13,IF(Z35=4,18,21)))),IF(T35="4-Probable",IF(Z35=1,7,IF(Z35=2,12,IF(Z35=3,17,IF(Z35=4,22,23)))),IF(T35="5-Casi Seguro",IF(Z35=1,11,IF(Z35=2,16,IF(Z35=3,20,IF(Z35=4,24,25))))))))) -> 8 | AC35: =((VLOOKUP(T35,$AH$3:$AJ$7,3,FALSE)*SQRT(U35^2+V35^2+W35^2+X35^2+Y35^2))/(5*SQRT((5)*5^2))) -> 0.12
A36: 2200 Pila acopio de gruesos | B36: 2210 Acopio de gruesos & sistema recuperación | C36: Chute descarga material fino | D36: 2210CH0071 | E36: Chute descarga material fino | F36: Almacenar material fino proveniente de apron feeder 2210FE0001 y transferir a correa alimentación SAG 2210CV0003 | G36: Rotura de chute | H36: Afectación no directa a operaciones (20%), Detención de feeder 2210FE0001, Costos por reparación de chute | I36: 1 | J36: 1 | K36: =+IF(I36="","",IF((I36-J36)>0,"Si","No")) -> No | L36: Ninguna | M36: 0.41666667 | N36: 0.2 | O36: 91.32 | P36: 1 | Q36: =+IF(M36="","",(IF(((M36*24)-P36)<0,0,(M36*24)-P36)*N36)) -> 1.8 | R36: =+(IF(((M36*24)-P36)<0,0,((M36*24)-P36)*'Estimación de pérdidas'!$F$72))*N36 -> 103820.53 | S36: No | T36: 3-Posible | U36: =+IF(R36="","",IF(R36<50001,1,IF(R36<200001,2,IF(R36<500001,3,IF(R36<1000001,4,5))))) -> 2 | V36: 1 | Z36: =MAX(U36:Y36) -> 2 | AA36: =IF(Z36=1,VLOOKUP(T36,$AH$3:$AI$7,2,FALSE),IF(Z36=2,VLOOKUP(T36,$AH$8:$AI$12,2, FALSE),IF(Z36=3,VLOOKUP(T36,$AH$13:$AI$17,2,FALSE),IF(Z36=4,VLOOKUP(T36,$AH$18:$AI$22,2,FALSE),IF(Z36=5,VLOOKUP(T36,$AH$23:$AI$27,2,FALSE),""))))) -> Moderado | AB36: =IF(T36="1-Raro",IF(Z36=1,1,IF(Z36=2,3,IF(Z36=3,6,IF(Z36=4,10,15)))),IF(T36="2-Improbable",IF(Z36=1,2,IF(Z36=2,5,IF(Z36=3,9,IF(Z36=4,14,19)))),IF(T36="3-Posible",IF(Z36=1,4,IF(Z36=2,8,IF(Z36=3,13,IF(Z36=4,18,21)))),IF(T36="4-Probable",IF(Z36=1,7,IF(Z36=2,12,IF(Z36=3,17,IF(Z36=4,22,23)))),IF(T36="5-Casi Seguro",IF(Z36=1,11,IF(Z36=2,16,IF(Z36=3,20,IF(Z36=4,24,25))))))))) -> 8 | AC36: =((VLOOKUP(T36,$AH$3:$AJ$7,3,FALSE)*SQRT(U36^2+V36^2+W36^2+X36^2+Y36^2))/(5*SQRT((5)*5^2))) -> 0.12
A37: 2200 Pila acopio de gruesos | B37: 2210 Acopio de gruesos & sistema recuperación | C37: Chute descarga material fino | D37: 2210CH0072 | E37: Chute descarga material fino | F37: Almacenar material fino proveniente de apron feeder 2210FE0002 y transferir a correa alimentación SAG 2210CV0003 | G37: Rotura de chute | H37: Afectación no directa a operaciones (20%), Detención de feeder 2210FE0002, Costos por reparación de chute | I37: 1 | J37: 1 | K37: =+IF(I37="","",IF((I37-J37)>0,"Si","No")) -> No | L37: Ninguna | M37: 0.41666667 | N37: 0.2 | O37: 91.32 | P37: 1 | Q37: =+IF(M37="","",(IF(((M37*24)-P37)<0,0,(M37*24)-P37)*N37)) -> 1.8 | R37: =+(IF(((M37*24)-P37)<0,0,((M37*24)-P37)*'Estimación de pérdidas'!$F$72))*N37 -> 103820.53 | S37: No | T37: 3-Posible | U37: =+IF(R37="","",IF(R37<50001,1,IF(R37<200001,2,IF(R37<500001,3,IF(R37<1000001,4,5))))) -> 2 | V37: 1 | Z37: =MAX(U37:Y37) -> 2 | AA37: =IF(Z37=1,VLOOKUP(T37,$AH$3:$AI$7,2,FALSE),IF(Z37=2,VLOOKUP(T37,$AH$8:$AI$12,2, FALSE),IF(Z37=3,VLOOKUP(T37,$AH$13:$AI$17,2,FALSE),IF(Z37=4,VLOOKUP(T37,$AH$18:$AI$22,2,FALSE),IF(Z37=5,VLOOKUP(T37,$AH$23:$AI$27,2,FALSE),""))))) -> Moderado | AB37: =IF(T37="1-Raro",IF(Z37=1,1,IF(Z37=2,3,IF(Z37=3,6,IF(Z37=4,10,15)))),IF(T37="2-Improbable",IF(Z37=1,2,IF(Z37=2,5,IF(Z37=3,9,IF(Z37=4,14,19)))),IF(T37="3-Posible",IF(Z37=1,4,IF(Z37=2,8,IF(Z37=3,13,IF(Z37=4,18,21)))),IF(T37="4-Probable",IF(Z37=1,7,IF(Z37=2,12,IF(Z37=3,17,IF(Z37=4,22,23)))),IF(T37="5-Casi Seguro",IF(Z37=1,11,IF(Z37=2,16,IF(Z37=3,20,IF(Z37=4,24,25))))))))) -> 8 | AC37: =((VLOOKUP(T37,$AH$3:$AJ$7,3,FALSE)*SQRT(U37^2+V37^2+W37^2+X37^2+Y37^2))/(5*SQRT((5)*5^2))) -> 0.12
A38: 2200 Pila acopio de gruesos | B38: 2210 Acopio de gruesos & sistema recuperación | C38: Correa alimentación SAG | D38: 2210CV0003 | E38: Correa alimentación SAG | F38: Obtener el material chancado de alimentadores 2210FE0001/2210FE0002 y conducir a 2210CH0018/ 2210CH0019 para alimentar el Molino SAG | G38: Rotura de correa alimentación a Molino SAG (277 m) | H38: Afectación a operaciones, Parada de Molino SAG, Cambio de correa | I38: 1 | J38: 1 | K38: =+IF(I38="","",IF((I38-J38)>0,"Si","No")) -> No | L38: Ninguna | M38: 3 | N38: 1 | O38: 91.32 | P38: 1 | Q38: =+IF(M38="","",(IF(((M38*24)-P38)<0,0,(M38*24)-P38)*N38)) -> 71 | R38: =+(IF(((M38*24)-P38)<0,0,((M38*24)-P38)*'Estimación de pérdidas'!$F$72))*N38 -> 4095143.3 | S38: No | T38: 3-Posible | U38: =+IF(R38="","",IF(R38<50001,1,IF(R38<200001,2,IF(R38<500001,3,IF(R38<1000001,4,5))))) -> 5 | V38: 2 | Z38: =MAX(U38:Y38) -> 5 | AA38: =IF(Z38=1,VLOOKUP(T38,$AH$3:$AI$7,2,FALSE),IF(Z38=2,VLOOKUP(T38,$AH$8:$AI$12,2, FALSE),IF(Z38=3,VLOOKUP(T38,$AH$13:$AI$17,2,FALSE),IF(Z38=4,VLOOKUP(T38,$AH$18:$AI$22,2,FALSE),IF(Z38=5,VLOOKUP(T38,$AH$23:$AI$27,2,FALSE),""))))) -> Alto | AB38: =IF(T38="1-Raro",IF(Z38=1,1,IF(Z38=2,3,IF(Z38=3,6,IF(Z38=4,10,15)))),IF(T38="2-Improbable",IF(Z38=1,2,IF(Z38=2,5,IF(Z38=3,9,IF(Z38=4,14,19)))),IF(T38="3-Posible",IF(Z38=1,4,IF(Z38=2,8,IF(Z38=3,13,IF(Z38=4,18,21)))),IF(T38="4-Probable",IF(Z38=1,7,IF(Z38=2,12,IF(Z38=3,17,IF(Z38=4,22,23)))),IF(T38="5-Casi Seguro",IF(Z38=1,11,IF(Z38=2,16,IF(Z38=3,20,IF(Z38=4,24,25))))))))) -> 21 | AC38: =((VLOOKUP(T38,$AH$3:$AJ$7,3,FALSE)*SQRT(U38^2+V38^2+W38^2+X38^2+Y38^2))/(5*SQRT((5)*5^2))) -> 0.28899827
A39: 2200 Pila acopio de gruesos | B39: 2210 Acopio de gruesos & sistema recuperación | C39: Sistema supresión de polvo | D39: 2210DT0003 | E39: Sistema supresión polvo | F39: Suprimir por medio de neblina seca de agua el polvo generado por la descarga de los alimentadores 2210FE0001/ 2210FE0002 | G39: Rotura cámara de niebla | H39: Área contaminada de polvo sin efectos, posteriores en salud de personas, No afecta a operaciones, Costos por cambio cámara de niebla | I39: 1 | J39: 1 | K39: =+IF(I39="","",IF((I39-J39)>0,"Si","No")) -> No | L39: Ninguna | M39: 0.25 | N39: 0 | O39: 70 | P39: 10 | Q39: =+IF(M39="","",(IF(((M39*24)-P39)<0,0,(M39*24)-P39)*N39)) -> 0 | R39: =+(IF(((M39*24)-P39)<0,0,((M39*24)-P39)*'Estimación de pérdidas'!$F$72))*N39 -> 0 | S39: No | T39: 3-Posible | U39: =+IF(R39="","",IF(R39<50001,1,IF(R39<200001,2,IF(R39<500001,3,IF(R39<1000001,4,5))))) -> 1 | V39: 1 | Z39: =MAX(U39:Y39) -> 1 | AA39: =IF(Z39=1,VLOOKUP(T39,$AH$3:$AI$7,2,FALSE),IF(Z39=2,VLOOKUP(T39,$AH$8:$AI$12,2, FALSE),IF(Z39=3,VLOOKUP(T39,$AH$13:$AI$17,2,FALSE),IF(Z39=4,VLOOKUP(T39,$AH$18:$AI$22,2,FALSE),IF(Z39=5,VLOOKUP(T39,$AH$23:$AI$27,2,FALSE),""))))) -> Bajo | AB39: =IF(T39="1-Raro",IF(Z39=1,1,IF(Z39=2,3,IF(Z39=3,6,IF(Z39=4,10,15)))),IF(T39="2-Improbable",IF(Z39=1,2,IF(Z39=2,5,IF(Z39=3,9,IF(Z39=4,14,19)))),IF(T39="3-Posible",IF(Z39=1,4,IF(Z39=2,8,IF(Z39=3,13,IF(Z39=4,18,21)))),IF(T39="4-Probable",IF(Z39=1,7,IF(Z39=2,12,IF(Z39=3,17,IF(Z39=4,22,23)))),IF(T39="5-Casi Seguro",IF(Z39=1,11,IF(Z39=2,16,IF(Z39=3,20,IF(Z39=4,24,25))))))))) -> 4 | AC39: =((VLOOKUP(T39,$AH$3:$AJ$7,3,FALSE)*SQRT(U39^2+V39^2+W39^2+X39^2+Y39^2))/(5*SQRT((5)*5^2))) -> 0.075894664
A40: 2200 Pila acopio de gruesos | B40: 2210 Acopio de gruesos & sistema recuperación | C40: Ventilador túnel emergencia | D40: 2210FA0008 | E40: Ventilador túnel emergencia | F40: Mantener un nivel adecuado de ventilación en túnel de emergencia para mantención de feeder y correas | G40: Falla en motor eléctrico por cortocircuito | H40: Tratamiento médico no restrictivo, No afectación a operaciones Costos por cambio de conjunto ventilador - motor eléctrico | I40: 1 | J40: 1 | K40: =+IF(I40="","",IF((I40-J40)>0,"Si","No")) -> No | L40: Ninguna | M40: 0.33333333 | N40: 0 | O40: 91.32 | P40: 1 | Q40: =+IF(M40="","",(IF(((M40*24)-P40)<0,0,(M40*24)-P40)*N40)) -> 0 | R40: =+(IF(((M40*24)-P40)<0,0,((M40*24)-P40)*'Estimación de pérdidas'!$F$72))*N40 -> 0 | S40: Si | T40: 3-Posible | U40: =+IF(R40="","",IF(R40<50001,1,IF(R40<200001,2,IF(R40<500001,3,IF(R40<1000001,4,5))))) -> 1 | V40: 1 | W40: 2 | Z40: =MAX(U40:Y40) -> 2 | AA40: =IF(Z40=1,VLOOKUP(T40,$AH$3:$AI$7,2,FALSE),IF(Z40=2,VLOOKUP(T40,$AH$8:$AI$12,2, FALSE),IF(Z40=3,VLOOKUP(T40,$AH$13:$AI$17,2,FALSE),IF(Z40=4,VLOOKUP(T40,$AH$18:$AI$22,2,FALSE),IF(Z40=5,VLOOKUP(T40,$AH$23:$AI$27,2,FALSE),""))))) -> Moderado | AB40: =IF(T40="1-Raro",IF(Z40=1,1,IF(Z40=2,3,IF(Z40=3,6,IF(Z40=4,10,15)))),IF(T40="2-Improbable",IF(Z40=1,2,IF(Z40=2,5,IF(Z40=3,9,IF(Z40=4,14,19)))),IF(T40="3-Posible",IF(Z40=1,4,IF(Z40=2,8,IF(Z40=3,13,IF(Z40=4,18,21)))),IF(T40="4-Probable",IF(Z40=1,7,IF(Z40=2,12,IF(Z40=3,17,IF(Z40=4,22,23)))),IF(T40="5-Casi Seguro",IF(Z40=1,11,IF(Z40=2,16,IF(Z40=3,20,IF(Z40=4,24,25))))))))) -> 8 | AC40: =((VLOOKUP(T40,$AH$3:$AJ$7,3,FALSE)*SQRT(U40^2+V40^2+W40^2+X40^2+Y40^2))/(5*SQRT((5)*5^2))) -> 0.13145341
A41: 2200 Pila acopio de gruesos | B41: 2210 Acopio de gruesos & sistema recuperación | C41: Alimentador placas | D41: 2210FE0001 | E41: Alimentador placas | F41: Conducir mineral chancado de acopio hacia la correa transportadora 2210-CV-0003 | G41: Falla de polea de alimentador | H41: Afectación no directa a operaciones (20%), Detención de feeder 2210FE0001, Costos por cambio de cilindro hidráulico | I41: 1 | J41: 1 | K41: =+IF(I41="","",IF((I41-J41)>0,"Si","No")) -> No | L41: Ninguna | M41: 1.5 | N41: 0.2 | O41: 91.32 | P41: 1 | Q41: =+IF(M41="","",(IF(((M41*24)-P41)<0,0,(M41*24)-P41)*N41)) -> 7 | R41: =+(IF(((M41*24)-P41)<0,0,((M41*24)-P41)*'Estimación de pérdidas'!$F$72))*N41 -> 403746.52 | S41: No | T41: 3-Posible | U41: =+IF(R41="","",IF(R41<50001,1,IF(R41<200001,2,IF(R41<500001,3,IF(R41<1000001,4,5))))) -> 3 | V41: 2 | Z41: =MAX(U41:Y41) -> 3 | AA41: =IF(Z41=1,VLOOKUP(T41,$AH$3:$AI$7,2,FALSE),IF(Z41=2,VLOOKUP(T41,$AH$8:$AI$12,2, FALSE),IF(Z41=3,VLOOKUP(T41,$AH$13:$AI$17,2,FALSE),IF(Z41=4,VLOOKUP(T41,$AH$18:$AI$22,2,FALSE),IF(Z41=5,VLOOKUP(T41,$AH$23:$AI$27,2,FALSE),""))))) -> Moderado | AB41: =IF(T41="1-Raro",IF(Z41=1,1,IF(Z41=2,3,IF(Z41=3,6,IF(Z41=4,10,15)))),IF(T41="2-Improbable",IF(Z41=1,2,IF(Z41=2,5,IF(Z41=3,9,IF(Z41=4,14,19)))),IF(T41="3-Posible",IF(Z41=1,4,IF(Z41=2,8,IF(Z41=3,13,IF(Z41=4,18,21)))),IF(T41="4-Probable",IF(Z41=1,7,IF(Z41=2,12,IF(Z41=3,17,IF(Z41=4,22,23)))),IF(T41="5-Casi Seguro",IF(Z41=1,11,IF(Z41=2,16,IF(Z41=3,20,IF(Z41=4,24,25))))))))) -> 13 | AC41: =((VLOOKUP(T41,$AH$3:$AJ$7,3,FALSE)*SQRT(U41^2+V41^2+W41^2+X41^2+Y41^2))/(5*SQRT((5)*5^2))) -> 0.19349419
A42: 2200 Pila acopio de gruesos | B42: 2210 Acopio de gruesos & sistema recuperación | C42: Alimentador placas | D42: 2210FE0002 | E42: Alimentador placas | F42: Conducir mineral chancado de acopio hacia la correa transportadora 2210-CV-0003 | G42: Falla de polea de alimentador | H42: Afectación no directa a operaciones (20%), Detención de feeder 2210FE0001, Costos por cambio de cilindro hidráulico | I42: 1 | J42: 1 | K42: =+IF(I42="","",IF((I42-J42)>0,"Si","No")) -> No | L42: Ninguna | M42: 1.5 | N42: 0.2 | O42: 91.32 | P42: 1 | Q42: =+IF(M42="","",(IF(((M42*24)-P42)<0,0,(M42*24)-P42)*N42)) -> 7 | R42: =+(IF(((M42*24)-P42)<0,0,((M42*24)-P42)*'Estimación de pérdidas'!$F$72))*N42 -> 403746.52 | S42: No | T42: 3-Posible | U42: =+IF(R42="","",IF(R42<50001,1,IF(R42<200001,2,IF(R42<500001,3,IF(R42<1000001,4,5))))) -> 3 | V42: 2 | Z42: =MAX(U42:Y42) -> 3 | AA42: =IF(Z42=1,VLOOKUP(T42,$AH$3:$AI$7,2,FALSE),IF(Z42=2,VLOOKUP(T42,$AH$8:$AI$12,2, FALSE),IF(Z42=3,VLOOKUP(T42,$AH$13:$AI$17,2,FALSE),IF(Z42=4,VLOOKUP(T42,$AH$18:$AI$22,2,FALSE),IF(Z42=5,VLOOKUP(T42,$AH$23:$AI$27,2,FALSE),""))))) -> Moderado | AB42: =IF(T42="1-Raro",IF(Z42=1,1,IF(Z42=2,3,IF(Z42=3,6,IF(Z42=4,10,15)))),IF(T42="2-Improbable",IF(Z42=1,2,IF(Z42=2,5,IF(Z42=3,9,IF(Z42=4,14,19)))),IF(T42="3-Posible",IF(Z42=1,4,IF(Z42=2,8,IF(Z42=3,13,IF(Z42=4,18,21)))),IF(T42="4-Probable",IF(Z42=1,7,IF(Z42=2,12,IF(Z42=3,17,IF(Z42=4,22,23)))),IF(T42="5-Casi Seguro",IF(Z42=1,11,IF(Z42=2,16,IF(Z42=3,20,IF(Z42=4,24,25))))))))) -> 13 | AC42: =((VLOOKUP(T42,$AH$3:$AJ$7,3,FALSE)*SQRT(U42^2+V42^2+W42^2+X42^2+Y42^2))/(5*SQRT((5)*5^2))) -> 0.19349419
A43: 2200 Pila acopio de gruesos | B43: 2210 Acopio de gruesos & sistema recuperación | C43: Tecle servicio acopio | D43: 2210HT0005 | E43: Tecle servicio acopio | F43: Izar y desplazar cargas en el área de acopio de material | G43: Falla de cableado / cadena | H43: No afectación a operaciones, Cambiar el tecle | I43: 1 | J43: 1 | K43: =+IF(I43="","",IF((I43-J43)>0,"Si","No")) -> No | L43: Ninguna | M43: 0.33333333 | N43: 0 | P43: 0 | Q43: =+IF(M43="","",(IF(((M43*24)-P43)<0,0,(M43*24)-P43)*N43)) -> 0 | R43: =+(IF(((M43*24)-P43)<0,0,((M43*24)-P43)*'Estimación de pérdidas'!$F$72))*N43 -> 0 | S43: No | T43: 3-Posible | U43: =+IF(R43="","",IF(R43<50001,1,IF(R43<200001,2,IF(R43<500001,3,IF(R43<1000001,4,5))))) -> 1 | V43: 1 | Z43: =MAX(U43:Y43) -> 1 | AA43: =IF(Z43=1,VLOOKUP(T43,$AH$3:$AI$7,2,FALSE),IF(Z43=2,VLOOKUP(T43,$AH$8:$AI$12,2, FALSE),IF(Z43=3,VLOOKUP(T43,$AH$13:$AI$17,2,FALSE),IF(Z43=4,VLOOKUP(T43,$AH$18:$AI$22,2,FALSE),IF(Z43=5,VLOOKUP(T43,$AH$23:$AI$27,2,FALSE),""))))) -> Bajo | AB43: =IF(T43="1-Raro",IF(Z43=1,1,IF(Z43=2,3,IF(Z43=3,6,IF(Z43=4,10,15)))),IF(T43="2-Improbable",IF(Z43=1,2,IF(Z43=2,5,IF(Z43=3,9,IF(Z43=4,14,19)))),IF(T43="3-Posible",IF(Z43=1,4,IF(Z43=2,8,IF(Z43=3,13,IF(Z43=4,18,21)))),IF(T43="4-Probable",IF(Z43=1,7,IF(Z43=2,12,IF(Z43=3,17,IF(Z43=4,22,23)))),IF(T43="5-Casi Seguro",IF(Z43=1,11,IF(Z43=2,16,IF(Z43=3,20,IF(Z43=4,24,25))))))))) -> 4 | AC43: =((VLOOKUP(T43,$AH$3:$AJ$7,3,FALSE)*SQRT(U43^2+V43^2+W43^2+X43^2+Y43^2))/(5*SQRT((5)*5^2))) -> 0.075894664
A44: 2200 Pila acopio de gruesos | B44: 2210 Acopio de gruesos & sistema recuperación | C44: Tecle servicio acopio | D44: 2210HT0006 | E44: Tecle servicio acopio | F44: Izar y desplazar cargas en el área de acopio de material | G44: Falla de cableado / cadena | H44: No afectación a operaciones, Cambiar el tecle | I44: 1 | J44: 1 | K44: =+IF(I44="","",IF((I44-J44)>0,"Si","No")) -> No | L44: Ninguna | M44: 0.33333333 | N44: 0 | P44: 0 | Q44: =+IF(M44="","",(IF(((M44*24)-P44)<0,0,(M44*24)-P44)*N44)) -> 0 | R44: =+(IF(((M44*24)-P44)<0,0,((M44*24)-P44)*'Estimación de pérdidas'!$F$72))*N44 -> 0 | S44: No | T44: 3-Posible | U44: =+IF(R44="","",IF(R44<50001,1,IF(R44<200001,2,IF(R44<500001,3,IF(R44<1000001,4,5))))) -> 1 | V44: 1 | Z44: =MAX(U44:Y44) -> 1 | AA44: =IF(Z44=1,VLOOKUP(T44,$AH$3:$AI$7,2,FALSE),IF(Z44=2,VLOOKUP(T44,$AH$8:$AI$12,2, FALSE),IF(Z44=3,VLOOKUP(T44,$AH$13:$AI$17,2,FALSE),IF(Z44=4,VLOOKUP(T44,$AH$18:$AI$22,2,FALSE),IF(Z44=5,VLOOKUP(T44,$AH$23:$AI$27,2,FALSE),""))))) -> Bajo | AB44: =IF(T44="1-Raro",IF(Z44=1,1,IF(Z44=2,3,IF(Z44=3,6,IF(Z44=4,10,15)))),IF(T44="2-Improbable",IF(Z44=1,2,IF(Z44=2,5,IF(Z44=3,9,IF(Z44=4,14,19)))),IF(T44="3-Posible",IF(Z44=1,4,IF(Z44=2,8,IF(Z44=3,13,IF(Z44=4,18,21)))),IF(T44="4-Probable",IF(Z44=1,7,IF(Z44=2,12,IF(Z44=3,17,IF(Z44=4,22,23)))),IF(T44="5-Casi Seguro",IF(Z44=1,11,IF(Z44=2,16,IF(Z44=3,20,IF(Z44=4,24,25))))))))) -> 4 | AC44: =((VLOOKUP(T44,$AH$3:$AJ$7,3,FALSE)*SQRT(U44^2+V44^2+W44^2+X44^2+Y44^2))/(5*SQRT((5)*5^2))) -> 0.075894664
A45: 2200 Pila acopio de gruesos | B45: 2210 Acopio de gruesos & sistema recuperación | C45: Tecle servicio acopio | D45: 2210HT0007 | E45: Tecle servicio acopio | F45: Izar y desplazar cargas en el área de acopio de material | G45: Falla de cableado / cadena | H45: No afectación a operaciones, Cambiar el tecle | I45: 1 | J45: 1 | K45: =+IF(I45="","",IF((I45-J45)>0,"Si","No")) -> No | L45: Ninguna | M45: 0.33333333 | N45: 0 | P45: 0 | Q45: =+IF(M45="","",(IF(((M45*24)-P45)<0,0,(M45*24)-P45)*N45)) -> 0 | R45: =+(IF(((M45*24)-P45)<0,0,((M45*24)-P45)*'Estimación de pérdidas'!$F$72))*N45 -> 0 | S45: No | T45: 3-Posible | U45: =+IF(R45="","",IF(R45<50001,1,IF(R45<200001,2,IF(R45<500001,3,IF(R45<1000001,4,5))))) -> 1 | V45: 1 | Z45: =MAX(U45:Y45) -> 1 | AA45: =IF(Z45=1,VLOOKUP(T45,$AH$3:$AI$7,2,FALSE),IF(Z45=2,VLOOKUP(T45,$AH$8:$AI$12,2, FALSE),IF(Z45=3,VLOOKUP(T45,$AH$13:$AI$17,2,FALSE),IF(Z45=4,VLOOKUP(T45,$AH$18:$AI$22,2,FALSE),IF(Z45=5,VLOOKUP(T45,$AH$23:$AI$27,2,FALSE),""))))) -> Bajo | AB45: =IF(T45="1-Raro",IF(Z45=1,1,IF(Z45=2,3,IF(Z45=3,6,IF(Z45=4,10,15)))),IF(T45="2-Improbable",IF(Z45=1,2,IF(Z45=2,5,IF(Z45=3,9,IF(Z45=4,14,19)))),IF(T45="3-Posible",IF(Z45=1,4,IF(Z45=2,8,IF(Z45=3,13,IF(Z45=4,18,21)))),IF(T45="4-Probable",IF(Z45=1,7,IF(Z45=2,12,IF(Z45=3,17,IF(Z45=4,22,23)))),IF(T45="5-Casi Seguro",IF(Z45=1,11,IF(Z45=2,16,IF(Z45=3,20,IF(Z45=4,24,25))))))))) -> 4 | AC45: =((VLOOKUP(T45,$AH$3:$AJ$7,3,FALSE)*SQRT(U45^2+V45^2+W45^2+X45^2+Y45^2))/(5*SQRT((5)*5^2))) -> 0.075894664
A46: 2200 Pila acopio de gruesos | B46: 2210 Acopio de gruesos & sistema recuperación | C46: Unidad hidráulica sistema lanzas | D46: 2210HY0003 | E46: Unidad hidráulica sistema lanzas | F46: 1 Op + 1: Suministrar potencia hidráulica al sistema de lanzas 2210ME0001/2210ME0002 | G46: Falla de bomba hidráulica | H46: No afectación a producción, Parada de feeder, Parada de correa alimentación SAG, Parada Molino SAG, Cambiar bomba hidráulica | I46: 2 | J46: 1 | K46: =+IF(I46="","",IF((I46-J46)>0,"Si","No")) -> Si | L46: Activa | M46: 0.25 | N46: 0 | O46: 91.32 | P46: 1 | Q46: =+IF(M46="","",(IF(((M46*24)-P46)<0,0,(M46*24)-P46)*N46)) -> 0 | R46: =+(IF(((M46*24)-P46)<0,0,((M46*24)-P46)*'Estimación de pérdidas'!$F$72))*N46 -> 0 | S46: No | T46: 3-Posible | U46: =+IF(R46="","",IF(R46<50001,1,IF(R46<200001,2,IF(R46<500001,3,IF(R46<1000001,4,5))))) -> 1 | V46: 1 | Z46: =MAX(U46:Y46) -> 1 | AA46: =IF(Z46=1,VLOOKUP(T46,$AH$3:$AI$7,2,FALSE),IF(Z46=2,VLOOKUP(T46,$AH$8:$AI$12,2, FALSE),IF(Z46=3,VLOOKUP(T46,$AH$13:$AI$17,2,FALSE),IF(Z46=4,VLOOKUP(T46,$AH$18:$AI$22,2,FALSE),IF(Z46=5,VLOOKUP(T46,$AH$23:$AI$27,2,FALSE),""))))) -> Bajo | AB46: =IF(T46="1-Raro",IF(Z46=1,1,IF(Z46=2,3,IF(Z46=3,6,IF(Z46=4,10,15)))),IF(T46="2-Improbable",IF(Z46=1,2,IF(Z46=2,5,IF(Z46=3,9,IF(Z46=4,14,19)))),IF(T46="3-Posible",IF(Z46=1,4,IF(Z46=2,8,IF(Z46=3,13,IF(Z46=4,18,21)))),IF(T46="4-Probable",IF(Z46=1,7,IF(Z46=2,12,IF(Z46=3,17,IF(Z46=4,22,23)))),IF(T46="5-Casi Seguro",IF(Z46=1,11,IF(Z46=2,16,IF(Z46=3,20,IF(Z46=4,24,25))))))))) -> 4 | AC46: =((VLOOKUP(T46,$AH$3:$AJ$7,3,FALSE)*SQRT(U46^2+V46^2+W46^2+X46^2+Y46^2))/(5*SQRT((5)*5^2))) -> 0.075894664
A47: 2200 Pila acopio de gruesos | B47: 2210 Acopio de gruesos & sistema recuperación | C47: Unidad hidráulica sistema lanzas | D47: 2210HY0007 | E47: Unidad hidráulica sistema lanzas | F47: 1 Op + 1: Suministrar potencia hidráulica al sistema de lanzas 2210ME0001/2210ME0002 | G47: Falla de bomba hidráulica | H47: No afectación a producción, Parada de feeder, Parada de correa alimentación SAG, Parada Molino SAG, Cambiar bomba hidráulica | I47: 2 | J47: 1 | K47: =+IF(I47="","",IF((I47-J47)>0,"Si","No")) -> Si | L47: Activa | M47: 0.25 | N47: 0 | O47: 91.32 | P47: 1 | Q47: =+IF(M47="","",(IF(((M47*24)-P47)<0,0,(M47*24)-P47)*N47)) -> 0 | R47: =+(IF(((M47*24)-P47)<0,0,((M47*24)-P47)*'Estimación de pérdidas'!$F$72))*N47 -> 0 | S47: No | T47: 3-Posible | U47: =+IF(R47="","",IF(R47<50001,1,IF(R47<200001,2,IF(R47<500001,3,IF(R47<1000001,4,5))))) -> 1 | V47: 1 | Z47: =MAX(U47:Y47) -> 1 | AA47: =IF(Z47=1,VLOOKUP(T47,$AH$3:$AI$7,2,FALSE),IF(Z47=2,VLOOKUP(T47,$AH$8:$AI$12,2, FALSE),IF(Z47=3,VLOOKUP(T47,$AH$13:$AI$17,2,FALSE),IF(Z47=4,VLOOKUP(T47,$AH$18:$AI$22,2,FALSE),IF(Z47=5,VLOOKUP(T47,$AH$23:$AI$27,2,FALSE),""))))) -> Bajo | AB47: =IF(T47="1-Raro",IF(Z47=1,1,IF(Z47=2,3,IF(Z47=3,6,IF(Z47=4,10,15)))),IF(T47="2-Improbable",IF(Z47=1,2,IF(Z47=2,5,IF(Z47=3,9,IF(Z47=4,14,19)))),IF(T47="3-Posible",IF(Z47=1,4,IF(Z47=2,8,IF(Z47=3,13,IF(Z47=4,18,21)))),IF(T47="4-Probable",IF(Z47=1,7,IF(Z47=2,12,IF(Z47=3,17,IF(Z47=4,22,23)))),IF(T47="5-Casi Seguro",IF(Z47=1,11,IF(Z47=2,16,IF(Z47=3,20,IF(Z47=4,24,25))))))))) -> 4 | AC47: =((VLOOKUP(T47,$AH$3:$AJ$7,3,FALSE)*SQRT(U47^2+V47^2+W47^2+X47^2+Y47^2))/(5*SQRT((5)*5^2))) -> 0.075894664
A48: 2200 Pila acopio de gruesos | B48: 2210 Acopio de gruesos & sistema recuperación | C48: Plataforma operación spile bar | D48: 2210ME0005 | E48: Plataforma operación lanzas | F48: Desplazar el sistema de lanzas para operar | G48: Falla en estructura de plataforma | H48: No afectación a operaciones, Reparar la plataforma | I48: 2 | J48: 1 | K48: =+IF(I48="","",IF((I48-J48)>0,"Si","No")) -> Si | L48: Ninguna | M48: 0.25 | N48: 0 | P48: 0 | Q48: =+IF(M48="","",(IF(((M48*24)-P48)<0,0,(M48*24)-P48)*N48)) -> 0 | R48: =+(IF(((M48*24)-P48)<0,0,((M48*24)-P48)*'Estimación de pérdidas'!$F$72))*N48 -> 0 | S48: No | T48: 1-Raro | U48: =+IF(R48="","",IF(R48<50001,1,IF(R48<200001,2,IF(R48<500001,3,IF(R48<1000001,4,5))))) -> 1 | V48: 1 | Z48: =MAX(U48:Y48) -> 1 | AA48: =IF(Z48=1,VLOOKUP(T48,$AH$3:$AI$7,2,FALSE),IF(Z48=2,VLOOKUP(T48,$AH$8:$AI$12,2, FALSE),IF(Z48=3,VLOOKUP(T48,$AH$13:$AI$17,2,FALSE),IF(Z48=4,VLOOKUP(T48,$AH$18:$AI$22,2,FALSE),IF(Z48=5,VLOOKUP(T48,$AH$23:$AI$27,2,FALSE),""))))) -> Bajo | AB48: =IF(T48="1-Raro",IF(Z48=1,1,IF(Z48=2,3,IF(Z48=3,6,IF(Z48=4,10,15)))),IF(T48="2-Improbable",IF(Z48=1,2,IF(Z48=2,5,IF(Z48=3,9,IF(Z48=4,14,19)))),IF(T48="3-Posible",IF(Z48=1,4,IF(Z48=2,8,IF(Z48=3,13,IF(Z48=4,18,21)))),IF(T48="4-Probable",IF(Z48=1,7,IF(Z48=2,12,IF(Z48=3,17,IF(Z48=4,22,23)))),IF(T48="5-Casi Seguro",IF(Z48=1,11,IF(Z48=2,16,IF(Z48=3,20,IF(Z48=4,24,25))))))))) -> 1 | AC48: =((VLOOKUP(T48,$AH$3:$AJ$7,3,FALSE)*SQRT(U48^2+V48^2+W48^2+X48^2+Y48^2))/(5*SQRT((5)*5^2))) -> 0.025298221
A49: 2200 Pila acopio de gruesos | B49: 2210 Acopio de gruesos & sistema recuperación | C49: Plataforma operación spile bar | D49: 2210ME0006 | E49: Plataforma operación lanzas | F49: Desplazar el sistema de lanzas para operar | G49: Falla en estructura de plataforma | H49: No afectación a operaciones, Reparar la plataforma | I49: 2 | J49: 1 | K49: =+IF(I49="","",IF((I49-J49)>0,"Si","No")) -> Si | L49: Ninguna | M49: 0.25 | N49: 0 | P49: 0 | Q49: =+IF(M49="","",(IF(((M49*24)-P49)<0,0,(M49*24)-P49)*N49)) -> 0 | R49: =+(IF(((M49*24)-P49)<0,0,((M49*24)-P49)*'Estimación de pérdidas'!$F$72))*N49 -> 0 | S49: No | T49: 1-Raro | U49: =+IF(R49="","",IF(R49<50001,1,IF(R49<200001,2,IF(R49<500001,3,IF(R49<1000001,4,5))))) -> 1 | V49: 1 | Z49: =MAX(U49:Y49) -> 1 | AA49: =IF(Z49=1,VLOOKUP(T49,$AH$3:$AI$7,2,FALSE),IF(Z49=2,VLOOKUP(T49,$AH$8:$AI$12,2, FALSE),IF(Z49=3,VLOOKUP(T49,$AH$13:$AI$17,2,FALSE),IF(Z49=4,VLOOKUP(T49,$AH$18:$AI$22,2,FALSE),IF(Z49=5,VLOOKUP(T49,$AH$23:$AI$27,2,FALSE),""))))) -> Bajo | AB49: =IF(T49="1-Raro",IF(Z49=1,1,IF(Z49=2,3,IF(Z49=3,6,IF(Z49=4,10,15)))),IF(T49="2-Improbable",IF(Z49=1,2,IF(Z49=2,5,IF(Z49=3,9,IF(Z49=4,14,19)))),IF(T49="3-Posible",IF(Z49=1,4,IF(Z49=2,8,IF(Z49=3,13,IF(Z49=4,18,21)))),IF(T49="4-Probable",IF(Z49=1,7,IF(Z49=2,12,IF(Z49=3,17,IF(Z49=4,22,23)))),IF(T49="5-Casi Seguro",IF(Z49=1,11,IF(Z49=2,16,IF(Z49=3,20,IF(Z49=4,24,25))))))))) -> 1 | AC49: =((VLOOKUP(T49,$AH$3:$AJ$7,3,FALSE)*SQRT(U49^2+V49^2+W49^2+X49^2+Y49^2))/(5*SQRT((5)*5^2))) -> 0.025298221
A50: 2200 Pila acopio de gruesos | B50: 2210 Acopio de gruesos & sistema recuperación | C50: Bomba sumidero acopio | D50: 2210PU0051 | E50: Bomba sumidero acopio | F50: Transferir derrames recolectados en Stock pile a contención de derrames Molienda | G50: Falla de bomba hidráulica | H50: No afecta operaciones, Costo por cambio de bomba | I50: 1 | J50: 1 | K50: =+IF(I50="","",IF((I50-J50)>0,"Si","No")) -> No | L50: Ninguna | M50: 0.33 | N50: 0 | P50: 0 | Q50: =+IF(M50="","",(IF(((M50*24)-P50)<0,0,(M50*24)-P50)*N50)) -> 0 | R50: =+(IF(((M50*24)-P50)<0,0,((M50*24)-P50)*'Estimación de pérdidas'!$F$72))*N50 -> 0 | S50: No | T50: 3-Posible | U50: =+IF(R50="","",IF(R50<50001,1,IF(R50<200001,2,IF(R50<500001,3,IF(R50<1000001,4,5))))) -> 1 | V50: 1 | Z50: =MAX(U50:Y50) -> 1 | AA50: =IF(Z50=1,VLOOKUP(T50,$AH$3:$AI$7,2,FALSE),IF(Z50=2,VLOOKUP(T50,$AH$8:$AI$12,2, FALSE),IF(Z50=3,VLOOKUP(T50,$AH$13:$AI$17,2,FALSE),IF(Z50=4,VLOOKUP(T50,$AH$18:$AI$22,2,FALSE),IF(Z50=5,VLOOKUP(T50,$AH$23:$AI$27,2,FALSE),""))))) -> Bajo | AB50: =IF(T50="1-Raro",IF(Z50=1,1,IF(Z50=2,3,IF(Z50=3,6,IF(Z50=4,10,15)))),IF(T50="2-Improbable",IF(Z50=1,2,IF(Z50=2,5,IF(Z50=3,9,IF(Z50=4,14,19)))),IF(T50="3-Posible",IF(Z50=1,4,IF(Z50=2,8,IF(Z50=3,13,IF(Z50=4,18,21)))),IF(T50="4-Probable",IF(Z50=1,7,IF(Z50=2,12,IF(Z50=3,17,IF(Z50=4,22,23)))),IF(T50="5-Casi Seguro",IF(Z50=1,11,IF(Z50=2,16,IF(Z50=3,20,IF(Z50=4,24,25))))))))) -> 4 | AC50: =((VLOOKUP(T50,$AH$3:$AJ$7,3,FALSE)*SQRT(U50^2+V50^2+W50^2+X50^2+Y50^2))/(5*SQRT((5)*5^2))) -> 0.075894664
A51: 3100 Planta de Molienda | B51: 3110 Molienda SAG | C51: Tolva desechos | D51: 3110BN0006 | E51: Tolva desechos | F51: Recepcionar el material trasladado por el electroimán a través del carro 3110HT0012 producto de limpieza en correa transferencia pebbles 3110-CV-0004 | G51: Rotura en paredes de tolva | H51: No afectación a operación de planta, Costos reparación de tolva | I51: 1 | J51: 1 | K51: =+IF(I51="","",IF((I51-J51)>0,"Si","No")) -> No | L51: Ninguna | M51: 0.33333333 | N51: 0 | P51: 0 | Q51: =+IF(M51="","",(IF(((M51*24)-P51)<0,0,(M51*24)-P51)*N51)) -> 0 | R51: =+(IF(((M51*24)-P51)<0,0,((M51*24)-P51)*'Estimación de pérdidas'!$F$72))*N51 -> 0 | S51: No | T51: 2-Improbable | U51: =+IF(R51="","",IF(R51<50001,1,IF(R51<200001,2,IF(R51<500001,3,IF(R51<1000001,4,5))))) -> 1 | V51: 1 | Z51: =MAX(U51:Y51) -> 1 | AA51: =IF(Z51=1,VLOOKUP(T51,$AH$3:$AI$7,2,FALSE),IF(Z51=2,VLOOKUP(T51,$AH$8:$AI$12,2, FALSE),IF(Z51=3,VLOOKUP(T51,$AH$13:$AI$17,2,FALSE),IF(Z51=4,VLOOKUP(T51,$AH$18:$AI$22,2,FALSE),IF(Z51=5,VLOOKUP(T51,$AH$23:$AI$27,2,FALSE),""))))) -> Bajo | AB51: =IF(T51="1-Raro",IF(Z51=1,1,IF(Z51=2,3,IF(Z51=3,6,IF(Z51=4,10,15)))),IF(T51="2-Improbable",IF(Z51=1,2,IF(Z51=2,5,IF(Z51=3,9,IF(Z51=4,14,19)))),IF(T51="3-Posible",IF(Z51=1,4,IF(Z51=2,8,IF(Z51=3,13,IF(Z51=4,18,21)))),IF(T51="4-Probable",IF(Z51=1,7,IF(Z51=2,12,IF(Z51=3,17,IF(Z51=4,22,23)))),IF(T51="5-Casi Seguro",IF(Z51=1,11,IF(Z51=2,16,IF(Z51=3,20,IF(Z51=4,24,25))))))))) -> 2 | AC51: =((VLOOKUP(T51,$AH$3:$AJ$7,3,FALSE)*SQRT(U51^2+V51^2+W51^2+X51^2+Y51^2))/(5*SQRT((5)*5^2))) -> 0.050596443
A52: 3100 Planta de Molienda | B52: 3110 Molienda SAG | C52: Contenedor bolas SAG | D52: 3110BN0011 | E52: Contenedor bolas SAG | F52: Depositar las bolas descargados de camiones para transferir al capacho de bolas de Molino SAG cuando sea requerido | G52: Rotura en paredes de tolva | H52: No afectación a producción, Costos reparación de tolva | I52: 1 | J52: 1 | K52: =+IF(I52="","",IF((I52-J52)>0,"Si","No")) -> No | L52: Ninguna | M52: 0.33333333 | N52: 0 | P52: 0 | Q52: =+IF(M52="","",(IF(((M52*24)-P52)<0,0,(M52*24)-P52)*N52)) -> 0 | R52: =+(IF(((M52*24)-P52)<0,0,((M52*24)-P52)*'Estimación de pérdidas'!$F$72))*N52 -> 0 | S52: No | T52: 2-Improbable | U52: =+IF(R52="","",IF(R52<50001,1,IF(R52<200001,2,IF(R52<500001,3,IF(R52<1000001,4,5))))) -> 1 | V52: 1 | Z52: =MAX(U52:Y52) -> 1 | AA52: =IF(Z52=1,VLOOKUP(T52,$AH$3:$AI$7,2,FALSE),IF(Z52=2,VLOOKUP(T52,$AH$8:$AI$12,2, FALSE),IF(Z52=3,VLOOKUP(T52,$AH$13:$AI$17,2,FALSE),IF(Z52=4,VLOOKUP(T52,$AH$18:$AI$22,2,FALSE),IF(Z52=5,VLOOKUP(T52,$AH$23:$AI$27,2,FALSE),""))))) -> Bajo | AB52: =IF(T52="1-Raro",IF(Z52=1,1,IF(Z52=2,3,IF(Z52=3,6,IF(Z52=4,10,15)))),IF(T52="2-Improbable",IF(Z52=1,2,IF(Z52=2,5,IF(Z52=3,9,IF(Z52=4,14,19)))),IF(T52="3-Posible",IF(Z52=1,4,IF(Z52=2,8,IF(Z52=3,13,IF(Z52=4,18,21)))),IF(T52="4-Probable",IF(Z52=1,7,IF(Z52=2,12,IF(Z52=3,17,IF(Z52=4,22,23)))),IF(T52="5-Casi Seguro",IF(Z52=1,11,IF(Z52=2,16,IF(Z52=3,20,IF(Z52=4,24,25))))))))) -> 2 | AC52: =((VLOOKUP(T52,$AH$3:$AJ$7,3,FALSE)*SQRT(U52^2+V52^2+W52^2+X52^2+Y52^2))/(5*SQRT((5)*5^2))) -> 0.050596443
A53: 3100 Planta de Molienda | B53: 3110 Molienda SAG | C53: Cajón alimentador hidrociclón | D53: 3110BX0026 | E53: Cajón alimentador hidrociclón | F53: Recepcionar la pulpa que descarga el Molino SAG, el Molino de Bolas y el agua a molienda para alimentar con pulpa a la batería de hidrociclones | G53: Rotura de paredes de cajón | H53: Afectación a operaciones, Parada Molinos SAG y Bolas, Costos por reparación de cajón | I53: 1 | J53: 1 | K53: =+IF(I53="","",IF((I53-J53)>0,"Si","No")) -> No | L53: Ninguna | M53: 0.33333333 | N53: 1 | O53: 91.32 | P53: 1 | Q53: =+IF(M53="","",(IF(((M53*24)-P53)<0,0,(M53*24)-P53)*N53)) -> 7 | R53: =+(IF(((M53*24)-P53)<0,0,((M53*24)-P53)*'Estimación de pérdidas'!$F$72))*N53 -> 403746.52 | S53: No | T53: 3-Posible | U53: =+IF(R53="","",IF(R53<50001,1,IF(R53<200001,2,IF(R53<500001,3,IF(R53<1000001,4,5))))) -> 3 | V53: 1 | Z53: =MAX(U53:Y53) -> 3 | AA53: =IF(Z53=1,VLOOKUP(T53,$AH$3:$AI$7,2,FALSE),IF(Z53=2,VLOOKUP(T53,$AH$8:$AI$12,2, FALSE),IF(Z53=3,VLOOKUP(T53,$AH$13:$AI$17,2,FALSE),IF(Z53=4,VLOOKUP(T53,$AH$18:$AI$22,2,FALSE),IF(Z53=5,VLOOKUP(T53,$AH$23:$AI$27,2,FALSE),""))))) -> Moderado | AB53: =IF(T53="1-Raro",IF(Z53=1,1,IF(Z53=2,3,IF(Z53=3,6,IF(Z53=4,10,15)))),IF(T53="2-Improbable",IF(Z53=1,2,IF(Z53=2,5,IF(Z53=3,9,IF(Z53=4,14,19)))),IF(T53="3-Posible",IF(Z53=1,4,IF(Z53=2,8,IF(Z53=3,13,IF(Z53=4,18,21)))),IF(T53="4-Probable",IF(Z53=1,7,IF(Z53=2,12,IF(Z53=3,17,IF(Z53=4,22,23)))),IF(T53="5-Casi Seguro",IF(Z53=1,11,IF(Z53=2,16,IF(Z53=3,20,IF(Z53=4,24,25))))))))) -> 13 | AC53: =((VLOOKUP(T53,$AH$3:$AJ$7,3,FALSE)*SQRT(U53^2+V53^2+W53^2+X53^2+Y53^2))/(5*SQRT((5)*5^2))) -> 0.16970563
A54: 3100 Planta de Molienda | B54: 3110 Molienda SAG | C54: Chute intermedio alimentación | D54: 3110CH0026 | E54: Chute intermedio alimentación | F54: Recepción de bolas, agua, mineral y lechada de cal para alimentación del Molino SAG | G54: Rotura de chute | H54: Afectación a operaciones, Parada Molino SAG, Costos por reparación de chute | I54: 1 | J54: 1 | K54: =+IF(I54="","",IF((I54-J54)>0,"Si","No")) -> No | L54: Ninguna | M54: 0.33 | N54: 1 | O54: 91.32 | P54: 1 | Q54: =+IF(M54="","",(IF(((M54*24)-P54)<0,0,(M54*24)-P54)*N54)) -> 6.92 | R54: =+(IF(((M54*24)-P54)<0,0,((M54*24)-P54)*'Estimación de pérdidas'!$F$72))*N54 -> 399132.28 | S54: No | T54: 3-Posible | U54: =+IF(R54="","",IF(R54<50001,1,IF(R54<200001,2,IF(R54<500001,3,IF(R54<1000001,4,5))))) -> 3 | V54: 1 | Z54: =MAX(U54:Y54) -> 3 | AA54: =IF(Z54=1,VLOOKUP(T54,$AH$3:$AI$7,2,FALSE),IF(Z54=2,VLOOKUP(T54,$AH$8:$AI$12,2, FALSE),IF(Z54=3,VLOOKUP(T54,$AH$13:$AI$17,2,FALSE),IF(Z54=4,VLOOKUP(T54,$AH$18:$AI$22,2,FALSE),IF(Z54=5,VLOOKUP(T54,$AH$23:$AI$27,2,FALSE),""))))) -> Moderado | AB54: =IF(T54="1-Raro",IF(Z54=1,1,IF(Z54=2,3,IF(Z54=3,6,IF(Z54=4,10,15)))),IF(T54="2-Improbable",IF(Z54=1,2,IF(Z54=2,5,IF(Z54=3,9,IF(Z54=4,14,19)))),IF(T54="3-Posible",IF(Z54=1,4,IF(Z54=2,8,IF(Z54=3,13,IF(Z54=4,18,21)))),IF(T54="4-Probable",IF(Z54=1,7,IF(Z54=2,12,IF(Z54=3,17,IF(Z54=4,22,23)))),IF(T54="5-Casi Seguro",IF(Z54=1,11,IF(Z54=2,16,IF(Z54=3,20,IF(Z54=4,24,25))))))))) -> 13 | AC54: =((VLOOKUP(T54,$AH$3:$AJ$7,3,FALSE)*SQRT(U54^2+V54^2+W54^2+X54^2+Y54^2))/(5*SQRT((5)*5^2))) -> 0.16970563
A55: 3100 Planta de Molienda | B55: 3110 Molienda SAG | C55: Chute Trommel SAG | D55: 3110CH0028 | E55: Chute Trommel SAG | F55: Recepcionar la pulpa bajo tamaño proveniente de Trommel SAG hacia 3110BX0026 Cajón alimentación hidrociclones | G55: Rotura de chute | H55: Afectación a operaciones, Parada Molino SAG, Costos por reparación de chute | I55: 1 | J55: 1 | K55: =+IF(I55="","",IF((I55-J55)>0,"Si","No")) -> No | L55: Ninguna | M55: 0.33333333 | N55: 1 | O55: 91.32 | P55: 1 | Q55: =+IF(M55="","",(IF(((M55*24)-P55)<0,0,(M55*24)-P55)*N55)) -> 7 | R55: =+(IF(((M55*24)-P55)<0,0,((M55*24)-P55)*'Estimación de pérdidas'!$F$72))*N55 -> 403746.52 | S55: No | T55: 3-Posible | U55: =+IF(R55="","",IF(R55<50001,1,IF(R55<200001,2,IF(R55<500001,3,IF(R55<1000001,4,5))))) -> 3 | V55: 1 | Z55: =MAX(U55:Y55) -> 3 | AA55: =IF(Z55=1,VLOOKUP(T55,$AH$3:$AI$7,2,FALSE),IF(Z55=2,VLOOKUP(T55,$AH$8:$AI$12,2, FALSE),IF(Z55=3,VLOOKUP(T55,$AH$13:$AI$17,2,FALSE),IF(Z55=4,VLOOKUP(T55,$AH$18:$AI$22,2,FALSE),IF(Z55=5,VLOOKUP(T55,$AH$23:$AI$27,2,FALSE),""))))) -> Moderado | AB55: =IF(T55="1-Raro",IF(Z55=1,1,IF(Z55=2,3,IF(Z55=3,6,IF(Z55=4,10,15)))),IF(T55="2-Improbable",IF(Z55=1,2,IF(Z55=2,5,IF(Z55=3,9,IF(Z55=4,14,19)))),IF(T55="3-Posible",IF(Z55=1,4,IF(Z55=2,8,IF(Z55=3,13,IF(Z55=4,18,21)))),IF(T55="4-Probable",IF(Z55=1,7,IF(Z55=2,12,IF(Z55=3,17,IF(Z55=4,22,23)))),IF(T55="5-Casi Seguro",IF(Z55=1,11,IF(Z55=2,16,IF(Z55=3,20,IF(Z55=4,24,25))))))))) -> 13 | AC55: =((VLOOKUP(T55,$AH$3:$AJ$7,3,FALSE)*SQRT(U55^2+V55^2+W55^2+X55^2+Y55^2))/(5*SQRT((5)*5^2))) -> 0.16970563
A56: 3100 Planta de Molienda | B56: 3110 Molienda SAG | C56: Chute sobre tamaño Trommel | D56: 3110CH0029 | E56: Chute sobre tamaño Trommel | F56: Alimentar la correa transferencia de pebbles 3110-CV-0004 con mineral proveniente de Molino SAG | G56: Rotura de chute | H56: Afectación a operaciones, Parada Molino SAG, Costos por reparación de chute | I56: 1 | J56: 1 | K56: =+IF(I56="","",IF((I56-J56)>0,"Si","No")) -> No | L56: Ninguna | M56: 0.41666667 | N56: 1 | O56: 91.32 | P56: 1 | Q56: =+IF(M56="","",(IF(((M56*24)-P56)<0,0,(M56*24)-P56)*N56)) -> 9 | R56: =+(IF(((M56*24)-P56)<0,0,((M56*24)-P56)*'Estimación de pérdidas'!$F$72))*N56 -> 519102.67 | S56: No | T56: 3-Posible | U56: =+IF(R56="","",IF(R56<50001,1,IF(R56<200001,2,IF(R56<500001,3,IF(R56<1000001,4,5))))) -> 4 | V56: 1 | Z56: =MAX(U56:Y56) -> 4 | AA56: =IF(Z56=1,VLOOKUP(T56,$AH$3:$AI$7,2,FALSE),IF(Z56=2,VLOOKUP(T56,$AH$8:$AI$12,2, FALSE),IF(Z56=3,VLOOKUP(T56,$AH$13:$AI$17,2,FALSE),IF(Z56=4,VLOOKUP(T56,$AH$18:$AI$22,2,FALSE),IF(Z56=5,VLOOKUP(T56,$AH$23:$AI$27,2,FALSE),""))))) -> Moderado | AB56: =IF(T56="1-Raro",IF(Z56=1,1,IF(Z56=2,3,IF(Z56=3,6,IF(Z56=4,10,15)))),IF(T56="2-Improbable",IF(Z56=1,2,IF(Z56=2,5,IF(Z56=3,9,IF(Z56=4,14,19)))),IF(T56="3-Posible",IF(Z56=1,4,IF(Z56=2,8,IF(Z56=3,13,IF(Z56=4,18,21)))),IF(T56="4-Probable",IF(Z56=1,7,IF(Z56=2,12,IF(Z56=3,17,IF(Z56=4,22,23)))),IF(T56="5-Casi Seguro",IF(Z56=1,11,IF(Z56=2,16,IF(Z56=3,20,IF(Z56=4,24,25))))))))) -> 18 | AC56: =((VLOOKUP(T56,$AH$3:$AJ$7,3,FALSE)*SQRT(U56^2+V56^2+W56^2+X56^2+Y56^2))/(5*SQRT((5)*5^2))) -> 0.22126907
A57: 3100 Planta de Molienda | B57: 3110 Molienda SAG | C57: Chute descarga pebbles | D57: 3110CH0030 | E57: Chute descarga pebbles | F57: Recepcionar la descarga de la correa transferencia de pebbles3110-CV-0004 para posteriormente alimentar la correa retorno de pebbles 3110-CV-0005 | G57: Rotura de chute | H57: Afectación a operaciones, Parada Molino SAG, Costos por reparación de chute | I57: 1 | J57: 1 | K57: =+IF(I57="","",IF((I57-J57)>0,"Si","No")) -> No | L57: Ninguna | M57: 0.33 | N57: 1 | O57: 91.32 | P57: 1 | Q57: =+IF(M57="","",(IF(((M57*24)-P57)<0,0,(M57*24)-P57)*N57)) -> 6.92 | R57: =+(IF(((M57*24)-P57)<0,0,((M57*24)-P57)*'Estimación de pérdidas'!$F$72))*N57 -> 399132.28 | S57: No | T57: 3-Posible | U57: =+IF(R57="","",IF(R57<50001,1,IF(R57<200001,2,IF(R57<500001,3,IF(R57<1000001,4,5))))) -> 3 | V57: 1 | Z57: =MAX(U57:Y57) -> 3 | AA57: =IF(Z57=1,VLOOKUP(T57,$AH$3:$AI$7,2,FALSE),IF(Z57=2,VLOOKUP(T57,$AH$8:$AI$12,2, FALSE),IF(Z57=3,VLOOKUP(T57,$AH$13:$AI$17,2,FALSE),IF(Z57=4,VLOOKUP(T57,$AH$18:$AI$22,2,FALSE),IF(Z57=5,VLOOKUP(T57,$AH$23:$AI$27,2,FALSE),""))))) -> Moderado | AB57: =IF(T57="1-Raro",IF(Z57=1,1,IF(Z57=2,3,IF(Z57=3,6,IF(Z57=4,10,15)))),IF(T57="2-Improbable",IF(Z57=1,2,IF(Z57=2,5,IF(Z57=3,9,IF(Z57=4,14,19)))),IF(T57="3-Posible",IF(Z57=1,4,IF(Z57=2,8,IF(Z57=3,13,IF(Z57=4,18,21)))),IF(T57="4-Probable",IF(Z57=1,7,IF(Z57=2,12,IF(Z57=3,17,IF(Z57=4,22,23)))),IF(T57="5-Casi Seguro",IF(Z57=1,11,IF(Z57=2,16,IF(Z57=3,20,IF(Z57=4,24,25))))))))) -> 13 | AC57: =((VLOOKUP(T57,$AH$3:$AJ$7,3,FALSE)*SQRT(U57^2+V57^2+W57^2+X57^2+Y57^2))/(5*SQRT((5)*5^2))) -> 0.16970563
A58: 3100 Planta de Molienda | B58: 3110 Molienda SAG | C58: Chute retorno pebbles | D58: 3110CH0031 | E58: Chute retorno pebbles | F58: Almacenar los pebbles provenientes de correa retorno de pebbles 3110-CV-0005 y retornar a correa alimentación SAG 2110CV0003 | G58: Rotura de chute | H58: Afectación a operaciones, Parada Molino SAG, Costos por reparación de chute | I58: 1 | J58: 1 | K58: =+IF(I58="","",IF((I58-J58)>0,"Si","No")) -> No | L58: Ninguna | M58: 0.33 | N58: 1 | O58: 91.32 | P58: 1 | Q58: =+IF(M58="","",(IF(((M58*24)-P58)<0,0,(M58*24)-P58)*N58)) -> 6.92 | R58: =+(IF(((M58*24)-P58)<0,0,((M58*24)-P58)*'Estimación de pérdidas'!$F$72))*N58 -> 399132.28 | S58: No | T58: 3-Posible | U58: =+IF(R58="","",IF(R58<50001,1,IF(R58<200001,2,IF(R58<500001,3,IF(R58<1000001,4,5))))) -> 3 | V58: 1 | Z58: =MAX(U58:Y58) -> 3 | AA58: =IF(Z58=1,VLOOKUP(T58,$AH$3:$AI$7,2,FALSE),IF(Z58=2,VLOOKUP(T58,$AH$8:$AI$12,2, FALSE),IF(Z58=3,VLOOKUP(T58,$AH$13:$AI$17,2,FALSE),IF(Z58=4,VLOOKUP(T58,$AH$18:$AI$22,2,FALSE),IF(Z58=5,VLOOKUP(T58,$AH$23:$AI$27,2,FALSE),""))))) -> Moderado | AB58: =IF(T58="1-Raro",IF(Z58=1,1,IF(Z58=2,3,IF(Z58=3,6,IF(Z58=4,10,15)))),IF(T58="2-Improbable",IF(Z58=1,2,IF(Z58=2,5,IF(Z58=3,9,IF(Z58=4,14,19)))),IF(T58="3-Posible",IF(Z58=1,4,IF(Z58=2,8,IF(Z58=3,13,IF(Z58=4,18,21)))),IF(T58="4-Probable",IF(Z58=1,7,IF(Z58=2,12,IF(Z58=3,17,IF(Z58=4,22,23)))),IF(T58="5-Casi Seguro",IF(Z58=1,11,IF(Z58=2,16,IF(Z58=3,20,IF(Z58=4,24,25))))))))) -> 13 | AC58: =((VLOOKUP(T58,$AH$3:$AJ$7,3,FALSE)*SQRT(U58^2+V58^2+W58^2+X58^2+Y58^2))/(5*SQRT((5)*5^2))) -> 0.16970563
A59: 3100 Planta de Molienda | B59: 3120 Molienda Bolas | C59: Circuito cerrado de televisión CCTV | D59: 3120CT0001 | E59: CCTV molienda bolas | F59: Sistema de videovigilancia diseñada para supervisar el proceso. | G59: Falla de gabinete | H59: No afectación a producción, Cambio de gabinete | I59: 1 | J59: 1 | K59: =+IF(I59="","",IF((I59-J59)>0,"Si","No")) -> No | L59: Ninguna | M59: 0.33333333 | N59: 0 | O59: 91.32 | P59: 1 | Q59: =+IF(M59="","",(IF(((M59*24)-P59)<0,0,(M59*24)-P59)*N59)) -> 0 | R59: =+(IF(((M59*24)-P59)<0,0,((M59*24)-P59)*'Estimación de pérdidas'!$F$72))*N59 -> 0 | S59: No | T59: 2-Improbable | U59: =+IF(R59="","",IF(R59<50001,1,IF(R59<200001,2,IF(R59<500001,3,IF(R59<1000001,4,5))))) -> 1 | V59: 2 | Z59: =MAX(U59:Y59) -> 2 | AA59: =IF(Z59=1,VLOOKUP(T59,$AH$3:$AI$7,2,FALSE),IF(Z59=2,VLOOKUP(T59,$AH$8:$AI$12,2, FALSE),IF(Z59=3,VLOOKUP(T59,$AH$13:$AI$17,2,FALSE),IF(Z59=4,VLOOKUP(T59,$AH$18:$AI$22,2,FALSE),IF(Z59=5,VLOOKUP(T59,$AH$23:$AI$27,2,FALSE),""))))) -> Bajo | AB59: =IF(T59="1-Raro",IF(Z59=1,1,IF(Z59=2,3,IF(Z59=3,6,IF(Z59=4,10,15)))),IF(T59="2-Improbable",IF(Z59=1,2,IF(Z59=2,5,IF(Z59=3,9,IF(Z59=4,14,19)))),IF(T59="3-Posible",IF(Z59=1,4,IF(Z59=2,8,IF(Z59=3,13,IF(Z59=4,18,21)))),IF(T59="4-Probable",IF(Z59=1,7,IF(Z59=2,12,IF(Z59=3,17,IF(Z59=4,22,23)))),IF(T59="5-Casi Seguro",IF(Z59=1,11,IF(Z59=2,16,IF(Z59=3,20,IF(Z59=4,24,25))))))))) -> 5 | AC59: =((VLOOKUP(T59,$AH$3:$AJ$7,3,FALSE)*SQRT(U59^2+V59^2+W59^2+X59^2+Y59^2))/(5*SQRT((5)*5^2))) -> 0.08
A60: 3100 Planta de Molienda | B60: 3110 Molienda SAG | C60: Chute rebose pebbles | D60: 3110CH0073 | E60: Chute rebose pebbles | F60: Almacenar el rebose de pebbles de chute descarga 3110CH0030 para transferir a 3110CV0005 correa retorno de pebbles | G60: Rotura de chute | H60: Afectación a operaciones, Parada Molino SAG, Costos por reparación de chute | I60: 1 | J60: 1 | K60: =+IF(I60="","",IF((I60-J60)>0,"Si","No")) -> No | L60: Ninguna | M60: 0.33 | N60: 1 | O60: 91.32 | P60: 1 | Q60: =+IF(M60="","",(IF(((M60*24)-P60)<0,0,(M60*24)-P60)*N60)) -> 6.92 | R60: =+(IF(((M60*24)-P60)<0,0,((M60*24)-P60)*'Estimación de pérdidas'!$F$72))*N60 -> 399132.28 | S60: No | T60: 3-Posible | U60: =+IF(R60="","",IF(R60<50001,1,IF(R60<200001,2,IF(R60<500001,3,IF(R60<1000001,4,5))))) -> 3 | V60: 1 | Z60: =MAX(U60:Y60) -> 3 | AA60: =IF(Z60=1,VLOOKUP(T60,$AH$3:$AI$7,2,FALSE),IF(Z60=2,VLOOKUP(T60,$AH$8:$AI$12,2, FALSE),IF(Z60=3,VLOOKUP(T60,$AH$13:$AI$17,2,FALSE),IF(Z60=4,VLOOKUP(T60,$AH$18:$AI$22,2,FALSE),IF(Z60=5,VLOOKUP(T60,$AH$23:$AI$27,2,FALSE),""))))) -> Moderado | AB60: =IF(T60="1-Raro",IF(Z60=1,1,IF(Z60=2,3,IF(Z60=3,6,IF(Z60=4,10,15)))),IF(T60="2-Improbable",IF(Z60=1,2,IF(Z60=2,5,IF(Z60=3,9,IF(Z60=4,14,19)))),IF(T60="3-Posible",IF(Z60=1,4,IF(Z60=2,8,IF(Z60=3,13,IF(Z60=4,18,21)))),IF(T60="4-Probable",IF(Z60=1,7,IF(Z60=2,12,IF(Z60=3,17,IF(Z60=4,22,23)))),IF(T60="5-Casi Seguro",IF(Z60=1,11,IF(Z60=2,16,IF(Z60=3,20,IF(Z60=4,24,25))))))))) -> 13 | AC60: =((VLOOKUP(T60,$AH$3:$AJ$7,3,FALSE)*SQRT(U60^2+V60^2+W60^2+X60^2+Y60^2))/(5*SQRT((5)*5^2))) -> 0.16970563
A61: 3100 Planta de Molienda | B61: 3110 Molienda SAG | C61: Correa transferencia pebbles | D61: 3110CV0004 | E61: Correa transferencia pebbles | F61: Recepcionar de chute 3110CH0029 los pebbles sin chancar clasificado en el trommel 3120-SN-010 y alimentar chute 3110CH0030 que alimenta correa retorno de pebbles | G61: Rotura de correa (143 m) | H61: Afectación a operaciones, Parada Molino SAG, Cambio de correa | I61: 1 | J61: 1 | K61: =+IF(I61="","",IF((I61-J61)>0,"Si","No")) -> No | L61: Ninguna | M61: 1.5 | N61: 1 | O61: 91.32 | P61: 1 | Q61: =+IF(M61="","",(IF(((M61*24)-P61)<0,0,(M61*24)-P61)*N61)) -> 35 | R61: =+(IF(((M61*24)-P61)<0,0,((M61*24)-P61)*'Estimación de pérdidas'!$F$72))*N61 -> 2018732.6 | S61: No | T61: 3-Posible | U61: =+IF(R61="","",IF(R61<50001,1,IF(R61<200001,2,IF(R61<500001,3,IF(R61<1000001,4,5))))) -> 5 | V61: 2 | Z61: =MAX(U61:Y61) -> 5 | AA61: =IF(Z61=1,VLOOKUP(T61,$AH$3:$AI$7,2,FALSE),IF(Z61=2,VLOOKUP(T61,$AH$8:$AI$12,2, FALSE),IF(Z61=3,VLOOKUP(T61,$AH$13:$AI$17,2,FALSE),IF(Z61=4,VLOOKUP(T61,$AH$18:$AI$22,2,FALSE),IF(Z61=5,VLOOKUP(T61,$AH$23:$AI$27,2,FALSE),""))))) -> Alto | AB61: =IF(T61="1-Raro",IF(Z61=1,1,IF(Z61=2,3,IF(Z61=3,6,IF(Z61=4,10,15)))),IF(T61="2-Improbable",IF(Z61=1,2,IF(Z61=2,5,IF(Z61=3,9,IF(Z61=4,14,19)))),IF(T61="3-Posible",IF(Z61=1,4,IF(Z61=2,8,IF(Z61=3,13,IF(Z61=4,18,21)))),IF(T61="4-Probable",IF(Z61=1,7,IF(Z61=2,12,IF(Z61=3,17,IF(Z61=4,22,23)))),IF(T61="5-Casi Seguro",IF(Z61=1,11,IF(Z61=2,16,IF(Z61=3,20,IF(Z61=4,24,25))))))))) -> 21 | AC61: =((VLOOKUP(T61,$AH$3:$AJ$7,3,FALSE)*SQRT(U61^2+V61^2+W61^2+X61^2+Y61^2))/(5*SQRT((5)*5^2))) -> 0.28899827
A62: 3100 Planta de Molienda | B62: 3110 Molienda SAG | C62: Correa retorno pebbles | D62: 3110CV0005 | E62: Correa retorno pebbles | F62: Recepcionar de chute 3110CH0030 los pebbles descargados de 3110CV0004 correa transferencia de pebbles para retornar a la alimentación de Molino SAG | G62: Rotura de correa (38 m) | H62: Afectación a operaciones, Parada Molino SAG, Cambio de correa | I62: 1 | J62: 1 | K62: =+IF(I62="","",IF((I62-J62)>0,"Si","No")) -> No | L62: Ninguna | M62: 0.75 | N62: 1 | O62: 91.32 | P62: 1 | Q62: =+IF(M62="","",(IF(((M62*24)-P62)<0,0,(M62*24)-P62)*N62)) -> 17 | R62: =+(IF(((M62*24)-P62)<0,0,((M62*24)-P62)*'Estimación de pérdidas'!$F$72))*N62 -> 980527.27 | S62: No | T62: 3-Posible | U62: =+IF(R62="","",IF(R62<50001,1,IF(R62<200001,2,IF(R62<500001,3,IF(R62<1000001,4,5))))) -> 4 | V62: 1 | Z62: =MAX(U62:Y62) -> 4 | AA62: =IF(Z62=1,VLOOKUP(T62,$AH$3:$AI$7,2,FALSE),IF(Z62=2,VLOOKUP(T62,$AH$8:$AI$12,2, FALSE),IF(Z62=3,VLOOKUP(T62,$AH$13:$AI$17,2,FALSE),IF(Z62=4,VLOOKUP(T62,$AH$18:$AI$22,2,FALSE),IF(Z62=5,VLOOKUP(T62,$AH$23:$AI$27,2,FALSE),""))))) -> Moderado | AB62: =IF(T62="1-Raro",IF(Z62=1,1,IF(Z62=2,3,IF(Z62=3,6,IF(Z62=4,10,15)))),IF(T62="2-Improbable",IF(Z62=1,2,IF(Z62=2,5,IF(Z62=3,9,IF(Z62=4,14,19)))),IF(T62="3-Posible",IF(Z62=1,4,IF(Z62=2,8,IF(Z62=3,13,IF(Z62=4,18,21)))),IF(T62="4-Probable",IF(Z62=1,7,IF(Z62=2,12,IF(Z62=3,17,IF(Z62=4,22,23)))),IF(T62="5-Casi Seguro",IF(Z62=1,11,IF(Z62=2,16,IF(Z62=3,20,IF(Z62=4,24,25))))))))) -> 18 | AC62: =((VLOOKUP(T62,$AH$3:$AJ$7,3,FALSE)*SQRT(U62^2+V62^2+W62^2+X62^2+Y62^2))/(5*SQRT((5)*5^2))) -> 0.22126907
A63: 3100 Planta de Molienda | B63: 3110 Molienda SAG | C63: Tolva bolas SAG | D63: 3110HO0001 | E63: Tolva bolas SAG | F63: Recepcionar las bolas de la tolva de alimentación de bolas del SAG 3110HO0001 y descarga al chute intermedio alimentación 3110-CH-0026 | G63: Rotura en paredes de tolva | H63: No afectación a producción, Costos por reparación de tolva | I63: 1 | J63: 1 | K63: =+IF(I63="","",IF((I63-J63)>0,"Si","No")) -> No | L63: Ninguna | M63: 0.33333333 | N63: 0 | P63: 0 | Q63: =+IF(M63="","",(IF(((M63*24)-P63)<0,0,(M63*24)-P63)*N63)) -> 0 | R63: =+(IF(((M63*24)-P63)<0,0,((M63*24)-P63)*'Estimación de pérdidas'!$F$72))*N63 -> 0 | S63: No | T63: 2-Improbable | U63: =+IF(R63="","",IF(R63<50001,1,IF(R63<200001,2,IF(R63<500001,3,IF(R63<1000001,4,5))))) -> 1 | V63: 1 | Z63: =MAX(U63:Y63) -> 1 | AA63: =IF(Z63=1,VLOOKUP(T63,$AH$3:$AI$7,2,FALSE),IF(Z63=2,VLOOKUP(T63,$AH$8:$AI$12,2, FALSE),IF(Z63=3,VLOOKUP(T63,$AH$13:$AI$17,2,FALSE),IF(Z63=4,VLOOKUP(T63,$AH$18:$AI$22,2,FALSE),IF(Z63=5,VLOOKUP(T63,$AH$23:$AI$27,2,FALSE),""))))) -> Bajo | AB63: =IF(T63="1-Raro",IF(Z63=1,1,IF(Z63=2,3,IF(Z63=3,6,IF(Z63=4,10,15)))),IF(T63="2-Improbable",IF(Z63=1,2,IF(Z63=2,5,IF(Z63=3,9,IF(Z63=4,14,19)))),IF(T63="3-Posible",IF(Z63=1,4,IF(Z63=2,8,IF(Z63=3,13,IF(Z63=4,18,21)))),IF(T63="4-Probable",IF(Z63=1,7,IF(Z63=2,12,IF(Z63=3,17,IF(Z63=4,22,23)))),IF(T63="5-Casi Seguro",IF(Z63=1,11,IF(Z63=2,16,IF(Z63=3,20,IF(Z63=4,24,25))))))))) -> 2 | AC63: =((VLOOKUP(T63,$AH$3:$AJ$7,3,FALSE)*SQRT(U63^2+V63^2+W63^2+X63^2+Y63^2))/(5*SQRT((5)*5^2))) -> 0.050596443
A64: 3100 Planta de Molienda | B64: 3110 Molienda SAG | C64: Tecle removedor pernos | D64: 3110HT0011 | E64: Tecle removedor pernos | F64: Sujetar martillo bota pernos de Molino SAG | G64: Falla de cableado / cadena | H64: No afectación a operaciones, Cambiar el tecle | I64: 1 | J64: 1 | K64: =+IF(I64="","",IF((I64-J64)>0,"Si","No")) -> No | L64: Ninguna | M64: 0.33333333 | N64: 0 | P64: 0 | Q64: =+IF(M64="","",(IF(((M64*24)-P64)<0,0,(M64*24)-P64)*N64)) -> 0 | R64: =+(IF(((M64*24)-P64)<0,0,((M64*24)-P64)*'Estimación de pérdidas'!$F$72))*N64 -> 0 | S64: No | T64: 3-Posible | U64: =+IF(R64="","",IF(R64<50001,1,IF(R64<200001,2,IF(R64<500001,3,IF(R64<1000001,4,5))))) -> 1 | V64: 1 | Z64: =MAX(U64:Y64) -> 1 | AA64: =IF(Z64=1,VLOOKUP(T64,$AH$3:$AI$7,2,FALSE),IF(Z64=2,VLOOKUP(T64,$AH$8:$AI$12,2, FALSE),IF(Z64=3,VLOOKUP(T64,$AH$13:$AI$17,2,FALSE),IF(Z64=4,VLOOKUP(T64,$AH$18:$AI$22,2,FALSE),IF(Z64=5,VLOOKUP(T64,$AH$23:$AI$27,2,FALSE),""))))) -> Bajo | AB64: =IF(T64="1-Raro",IF(Z64=1,1,IF(Z64=2,3,IF(Z64=3,6,IF(Z64=4,10,15)))),IF(T64="2-Improbable",IF(Z64=1,2,IF(Z64=2,5,IF(Z64=3,9,IF(Z64=4,14,19)))),IF(T64="3-Posible",IF(Z64=1,4,IF(Z64=2,8,IF(Z64=3,13,IF(Z64=4,18,21)))),IF(T64="4-Probable",IF(Z64=1,7,IF(Z64=2,12,IF(Z64=3,17,IF(Z64=4,22,23)))),IF(T64="5-Casi Seguro",IF(Z64=1,11,IF(Z64=2,16,IF(Z64=3,20,IF(Z64=4,24,25))))))))) -> 4 | AC64: =((VLOOKUP(T64,$AH$3:$AJ$7,3,FALSE)*SQRT(U64^2+V64^2+W64^2+X64^2+Y64^2))/(5*SQRT((5)*5^2))) -> 0.075894664
A65: 3100 Planta de Molienda | B65: 3110 Molienda SAG | C65: Tecle correa | D65: 3110HT0012 | E65: Tecle electroimán de correa | F65: Izar y trasladar carga en 3110CV0004 correa transferencia de pebbles | G65: Falla de cableado / cadena | H65: No afectación a operaciones, Cambiar el tecle | I65: 1 | J65: 1 | K65: =+IF(I65="","",IF((I65-J65)>0,"Si","No")) -> No | L65: Ninguna | M65: 0.33333333 | N65: 0 | P65: 0 | Q65: =+IF(M65="","",(IF(((M65*24)-P65)<0,0,(M65*24)-P65)*N65)) -> 0 | R65: =+(IF(((M65*24)-P65)<0,0,((M65*24)-P65)*'Estimación de pérdidas'!$F$72))*N65 -> 0 | S65: No | T65: 3-Posible | U65: =+IF(R65="","",IF(R65<50001,1,IF(R65<200001,2,IF(R65<500001,3,IF(R65<1000001,4,5))))) -> 1 | V65: 1 | Z65: =MAX(U65:Y65) -> 1 | AA65: =IF(Z65=1,VLOOKUP(T65,$AH$3:$AI$7,2,FALSE),IF(Z65=2,VLOOKUP(T65,$AH$8:$AI$12,2, FALSE),IF(Z65=3,VLOOKUP(T65,$AH$13:$AI$17,2,FALSE),IF(Z65=4,VLOOKUP(T65,$AH$18:$AI$22,2,FALSE),IF(Z65=5,VLOOKUP(T65,$AH$23:$AI$27,2,FALSE),""))))) -> Bajo | AB65: =IF(T65="1-Raro",IF(Z65=1,1,IF(Z65=2,3,IF(Z65=3,6,IF(Z65=4,10,15)))),IF(T65="2-Improbable",IF(Z65=1,2,IF(Z65=2,5,IF(Z65=3,9,IF(Z65=4,14,19)))),IF(T65="3-Posible",IF(Z65=1,4,IF(Z65=2,8,IF(Z65=3,13,IF(Z65=4,18,21)))),IF(T65="4-Probable",IF(Z65=1,7,IF(Z65=2,12,IF(Z65=3,17,IF(Z65=4,22,23)))),IF(T65="5-Casi Seguro",IF(Z65=1,11,IF(Z65=2,16,IF(Z65=3,20,IF(Z65=4,24,25))))))))) -> 4 | AC65: =((VLOOKUP(T65,$AH$3:$AJ$7,3,FALSE)*SQRT(U65^2+V65^2+W65^2+X65^2+Y65^2))/(5*SQRT((5)*5^2))) -> 0.075894664
A66: 3100 Planta de Molienda | B66: 3110 Molienda SAG | C66: Tecle correa | D66: 3110HT0019 | E66: Tecle electroimán de correa | F66: Izar y trasladar en correa | G66: Falla de cableado / cadena | H66: No afectación a operaciones, Cambiar el tecle | I66: 1 | J66: 1 | K66: =+IF(I66="","",IF((I66-J66)>0,"Si","No")) -> No | L66: Ninguna | M66: 0.33333333 | N66: 0 | P66: 0 | Q66: =+IF(M66="","",(IF(((M66*24)-P66)<0,0,(M66*24)-P66)*N66)) -> 0 | R66: =+(IF(((M66*24)-P66)<0,0,((M66*24)-P66)*'Estimación de pérdidas'!$F$72))*N66 -> 0 | S66: No | T66: 3-Posible | U66: =+IF(R66="","",IF(R66<50001,1,IF(R66<200001,2,IF(R66<500001,3,IF(R66<1000001,4,5))))) -> 1 | V66: 1 | Z66: =MAX(U66:Y66) -> 1 | AA66: =IF(Z66=1,VLOOKUP(T66,$AH$3:$AI$7,2,FALSE),IF(Z66=2,VLOOKUP(T66,$AH$8:$AI$12,2, FALSE),IF(Z66=3,VLOOKUP(T66,$AH$13:$AI$17,2,FALSE),IF(Z66=4,VLOOKUP(T66,$AH$18:$AI$22,2,FALSE),IF(Z66=5,VLOOKUP(T66,$AH$23:$AI$27,2,FALSE),""))))) -> Bajo | AB66: =IF(T66="1-Raro",IF(Z66=1,1,IF(Z66=2,3,IF(Z66=3,6,IF(Z66=4,10,15)))),IF(T66="2-Improbable",IF(Z66=1,2,IF(Z66=2,5,IF(Z66=3,9,IF(Z66=4,14,19)))),IF(T66="3-Posible",IF(Z66=1,4,IF(Z66=2,8,IF(Z66=3,13,IF(Z66=4,18,21)))),IF(T66="4-Probable",IF(Z66=1,7,IF(Z66=2,12,IF(Z66=3,17,IF(Z66=4,22,23)))),IF(T66="5-Casi Seguro",IF(Z66=1,11,IF(Z66=2,16,IF(Z66=3,20,IF(Z66=4,24,25))))))))) -> 4 | AC66: =((VLOOKUP(T66,$AH$3:$AJ$7,3,FALSE)*SQRT(U66^2+V66^2+W66^2+X66^2+Y66^2))/(5*SQRT((5)*5^2))) -> 0.075894664
A67: 3100 Planta de Molienda | B67: 3110 Molienda SAG | C67: Tecle tubería alimentación ciclón | D67: 3110HT0043 | E67: Tecle tubería alimentación ciclón | F67: Izar y trasladar tubería alimentación ciclón | G67: Falla de cableado / cadena | H67: No afectación a operaciones, Cambiar el tecle | I67: 1 | J67: 1 | K67: =+IF(I67="","",IF((I67-J67)>0,"Si","No")) -> No | L67: Ninguna | M67: 0.33333333 | N67: 0 | P67: 0 | Q67: =+IF(M67="","",(IF(((M67*24)-P67)<0,0,(M67*24)-P67)*N67)) -> 0 | R67: =+(IF(((M67*24)-P67)<0,0,((M67*24)-P67)*'Estimación de pérdidas'!$F$72))*N67 -> 0 | S67: No | T67: 3-Posible | U67: =+IF(R67="","",IF(R67<50001,1,IF(R67<200001,2,IF(R67<500001,3,IF(R67<1000001,4,5))))) -> 1 | V67: 1 | Z67: =MAX(U67:Y67) -> 1 | AA67: =IF(Z67=1,VLOOKUP(T67,$AH$3:$AI$7,2,FALSE),IF(Z67=2,VLOOKUP(T67,$AH$8:$AI$12,2, FALSE),IF(Z67=3,VLOOKUP(T67,$AH$13:$AI$17,2,FALSE),IF(Z67=4,VLOOKUP(T67,$AH$18:$AI$22,2,FALSE),IF(Z67=5,VLOOKUP(T67,$AH$23:$AI$27,2,FALSE),""))))) -> Bajo | AB67: =IF(T67="1-Raro",IF(Z67=1,1,IF(Z67=2,3,IF(Z67=3,6,IF(Z67=4,10,15)))),IF(T67="2-Improbable",IF(Z67=1,2,IF(Z67=2,5,IF(Z67=3,9,IF(Z67=4,14,19)))),IF(T67="3-Posible",IF(Z67=1,4,IF(Z67=2,8,IF(Z67=3,13,IF(Z67=4,18,21)))),IF(T67="4-Probable",IF(Z67=1,7,IF(Z67=2,12,IF(Z67=3,17,IF(Z67=4,22,23)))),IF(T67="5-Casi Seguro",IF(Z67=1,11,IF(Z67=2,16,IF(Z67=3,20,IF(Z67=4,24,25))))))))) -> 4 | AC67: =((VLOOKUP(T67,$AH$3:$AJ$7,3,FALSE)*SQRT(U67^2+V67^2+W67^2+X67^2+Y67^2))/(5*SQRT((5)*5^2))) -> 0.075894664
A68: 3100 Planta de Molienda | B68: 3110 Molienda SAG | C68: Capacho bolas SAG | D68: 3110KB0001 | E68: Capacho bolas SAG | F68: Recepcionar las bolas transferidas de tolva de almacenamiento (3110-BN-0011) y posterior transporte mediante puente grúa hasta la tolva de alimentación de bolas del SAG (3110HO0001) | G68: Falla eje de capacho | H68: No afectación a operación de planta, Costos por cambio de eje de capacho | I68: 2 | J68: 1 | K68: =+IF(I68="","",IF((I68-J68)>0,"Si","No")) -> Si | L68: Activa | M68: 0.25 | N68: 0 | P68: 0 | Q68: =+IF(M68="","",(IF(((M68*24)-P68)<0,0,(M68*24)-P68)*N68)) -> 0 | R68: =+(IF(((M68*24)-P68)<0,0,((M68*24)-P68)*'Estimación de pérdidas'!$F$72))*N68 -> 0 | S68: No | T68: 3-Posible | U68: =+IF(R68="","",IF(R68<50001,1,IF(R68<200001,2,IF(R68<500001,3,IF(R68<1000001,4,5))))) -> 1 | V68: 1 | Z68: =MAX(U68:Y68) -> 1 | AA68: =IF(Z68=1,VLOOKUP(T68,$AH$3:$AI$7,2,FALSE),IF(Z68=2,VLOOKUP(T68,$AH$8:$AI$12,2, FALSE),IF(Z68=3,VLOOKUP(T68,$AH$13:$AI$17,2,FALSE),IF(Z68=4,VLOOKUP(T68,$AH$18:$AI$22,2,FALSE),IF(Z68=5,VLOOKUP(T68,$AH$23:$AI$27,2,FALSE),""))))) -> Bajo | AB68: =IF(T68="1-Raro",IF(Z68=1,1,IF(Z68=2,3,IF(Z68=3,6,IF(Z68=4,10,15)))),IF(T68="2-Improbable",IF(Z68=1,2,IF(Z68=2,5,IF(Z68=3,9,IF(Z68=4,14,19)))),IF(T68="3-Posible",IF(Z68=1,4,IF(Z68=2,8,IF(Z68=3,13,IF(Z68=4,18,21)))),IF(T68="4-Probable",IF(Z68=1,7,IF(Z68=2,12,IF(Z68=3,17,IF(Z68=4,22,23)))),IF(T68="5-Casi Seguro",IF(Z68=1,11,IF(Z68=2,16,IF(Z68=3,20,IF(Z68=4,24,25))))))))) -> 4 | AC68: =((VLOOKUP(T68,$AH$3:$AJ$7,3,FALSE)*SQRT(U68^2+V68^2+W68^2+X68^2+Y68^2))/(5*SQRT((5)*5^2))) -> 0.075894664
A69: 3100 Planta de Molienda | B69: 3110 Molienda SAG | C69: Manipuladora revestimientos SAG | D69: 3110LH0001 | E69: Manipuladora revestimientos SAG | F69: Posicionar los revestimientos en interior de Molino SAG en mantención | G69: Falla cilindro hidráulico de manipuladora | H69: Afectación a producción, Alarga parada de mantención de Molino SAG , Cambio de cilindro | I69: 1 | J69: 1 | K69: =+IF(I69="","",IF((I69-J69)>0,"Si","No")) -> No | L69: Ninguna | M69: 0.33333333 | N69: 1 | P69: 0 | Q69: =+IF(M69="","",(IF(((M69*24)-P69)<0,0,(M69*24)-P69)*N69)) -> 8 | R69: =+(IF(((M69*24)-P69)<0,0,((M69*24)-P69)*'Estimación de pérdidas'!$F$72))*N69 -> 461424.6 | S69: No | T69: 3-Posible | U69: =+IF(R69="","",IF(R69<50001,1,IF(R69<200001,2,IF(R69<500001,3,IF(R69<1000001,4,5))))) -> 3 | V69: 2 | Z69: =MAX(U69:Y69) -> 3 | AA69: =IF(Z69=1,VLOOKUP(T69,$AH$3:$AI$7,2,FALSE),IF(Z69=2,VLOOKUP(T69,$AH$8:$AI$12,2, FALSE),IF(Z69=3,VLOOKUP(T69,$AH$13:$AI$17,2,FALSE),IF(Z69=4,VLOOKUP(T69,$AH$18:$AI$22,2,FALSE),IF(Z69=5,VLOOKUP(T69,$AH$23:$AI$27,2,FALSE),""))))) -> Moderado | AB69: =IF(T69="1-Raro",IF(Z69=1,1,IF(Z69=2,3,IF(Z69=3,6,IF(Z69=4,10,15)))),IF(T69="2-Improbable",IF(Z69=1,2,IF(Z69=2,5,IF(Z69=3,9,IF(Z69=4,14,19)))),IF(T69="3-Posible",IF(Z69=1,4,IF(Z69=2,8,IF(Z69=3,13,IF(Z69=4,18,21)))),IF(T69="4-Probable",IF(Z69=1,7,IF(Z69=2,12,IF(Z69=3,17,IF(Z69=4,22,23)))),IF(T69="5-Casi Seguro",IF(Z69=1,11,IF(Z69=2,16,IF(Z69=3,20,IF(Z69=4,24,25))))))))) -> 13 | AC69: =((VLOOKUP(T69,$AH$3:$AJ$7,3,FALSE)*SQRT(U69^2+V69^2+W69^2+X69^2+Y69^2))/(5*SQRT((5)*5^2))) -> 0.19349419
A70: 3100 Planta de Molienda | B70: 3110 Molienda SAG | C70: Inching Drive Molino SAG | D70: 3110ME0011 | E70: Inching drive molino SAG | F70: Mover el Molino SAG de forma lenta en mantención | G70: Rotura componentes internos inching drive | H70: Afectación a producción, Alarga parada de mantención de Molino SAG Cambio de inching drive | I70: 1 | J70: 1 | K70: =+IF(I70="","",IF((I70-J70)>0,"Si","No")) -> No | L70: Ninguna | M70: 0.5 | N70: 1 | P70: 0 | Q70: =+IF(M70="","",(IF(((M70*24)-P70)<0,0,(M70*24)-P70)*N70)) -> 12 | R70: =+(IF(((M70*24)-P70)<0,0,((M70*24)-P70)*'Estimación de pérdidas'!$F$72))*N70 -> 692136.9 | S70: No | T70: 2-Improbable | U70: =+IF(R70="","",IF(R70<50001,1,IF(R70<200001,2,IF(R70<500001,3,IF(R70<1000001,4,5))))) -> 4 | V70: 2 | Z70: =MAX(U70:Y70) -> 4 | AA70: =IF(Z70=1,VLOOKUP(T70,$AH$3:$AI$7,2,FALSE),IF(Z70=2,VLOOKUP(T70,$AH$8:$AI$12,2, FALSE),IF(Z70=3,VLOOKUP(T70,$AH$13:$AI$17,2,FALSE),IF(Z70=4,VLOOKUP(T70,$AH$18:$AI$22,2,FALSE),IF(Z70=5,VLOOKUP(T70,$AH$23:$AI$27,2,FALSE),""))))) -> Moderado | AB70: =IF(T70="1-Raro",IF(Z70=1,1,IF(Z70=2,3,IF(Z70=3,6,IF(Z70=4,10,15)))),IF(T70="2-Improbable",IF(Z70=1,2,IF(Z70=2,5,IF(Z70=3,9,IF(Z70=4,14,19)))),IF(T70="3-Posible",IF(Z70=1,4,IF(Z70=2,8,IF(Z70=3,13,IF(Z70=4,18,21)))),IF(T70="4-Probable",IF(Z70=1,7,IF(Z70=2,12,IF(Z70=3,17,IF(Z70=4,22,23)))),IF(T70="5-Casi Seguro",IF(Z70=1,11,IF(Z70=2,16,IF(Z70=3,20,IF(Z70=4,24,25))))))))) -> 14 | AC70: =((VLOOKUP(T70,$AH$3:$AJ$7,3,FALSE)*SQRT(U70^2+V70^2+W70^2+X70^2+Y70^2))/(5*SQRT((5)*5^2))) -> 0.16
A71: 3100 Planta de Molienda | B71: 3110 Molienda SAG | C71: Removedor pernos SAG | D71: 3110ME0012 | E71: Removedor pernos SAG | F71: Remover pernos de Molino SAG | G71: Falla en unidad hidráulica | H71: Afectación a producción, Cambio de unidad hidráulica | I71: 1 | J71: 1 | K71: =+IF(I71="","",IF((I71-J71)>0,"Si","No")) -> No | L71: Ninguna | M71: 0.25 | N71: 0.25 | P71: 0 | Q71: =+IF(M71="","",(IF(((M71*24)-P71)<0,0,(M71*24)-P71)*N71)) -> 1.5 | R71: =+(IF(((M71*24)-P71)<0,0,((M71*24)-P71)*'Estimación de pérdidas'!$F$72))*N71 -> 86517.112 | S71: No | T71: 3-Posible | U71: =+IF(R71="","",IF(R71<50001,1,IF(R71<200001,2,IF(R71<500001,3,IF(R71<1000001,4,5))))) -> 2 | V71: 2 | Z71: =MAX(U71:Y71) -> 2 | AA71: =IF(Z71=1,VLOOKUP(T71,$AH$3:$AI$7,2,FALSE),IF(Z71=2,VLOOKUP(T71,$AH$8:$AI$12,2, FALSE),IF(Z71=3,VLOOKUP(T71,$AH$13:$AI$17,2,FALSE),IF(Z71=4,VLOOKUP(T71,$AH$18:$AI$22,2,FALSE),IF(Z71=5,VLOOKUP(T71,$AH$23:$AI$27,2,FALSE),""))))) -> Moderado | AB71: =IF(T71="1-Raro",IF(Z71=1,1,IF(Z71=2,3,IF(Z71=3,6,IF(Z71=4,10,15)))),IF(T71="2-Improbable",IF(Z71=1,2,IF(Z71=2,5,IF(Z71=3,9,IF(Z71=4,14,19)))),IF(T71="3-Posible",IF(Z71=1,4,IF(Z71=2,8,IF(Z71=3,13,IF(Z71=4,18,21)))),IF(T71="4-Probable",IF(Z71=1,7,IF(Z71=2,12,IF(Z71=3,17,IF(Z71=4,22,23)))),IF(T71="5-Casi Seguro",IF(Z71=1,11,IF(Z71=2,16,IF(Z71=3,20,IF(Z71=4,24,25))))))))) -> 8 | AC71: =((VLOOKUP(T71,$AH$3:$AJ$7,3,FALSE)*SQRT(U71^2+V71^2+W71^2+X71^2+Y71^2))/(5*SQRT((5)*5^2))) -> 0.15178933
A72: 3100 Planta de Molienda | B72: 3110 Molienda SAG | C72: Molino SAG | D72: 3110MI0001 | E72: Molino SAG | F72: Reducir el tamaño que permita entregar a la siguiente etapa de molienda un tamaño de transferencia T80 entre 1 y 2 mm. La descarga del SAG es clasificada en el trommel (3120-SN-010), el material fino es descargado al cajón de alimentación hidrociclones y el material grueso (pebbles) es recirculado a la alimentación del SAG. | G72: Falla motor eléctrico por cortocircuito | H72: Afectación a operaciones, Parada de Molino SAG, Costos por cambio de motor eléctrico | I72: 1 | J72: 1 | K72: =+IF(I72="","",IF((I72-J72)>0,"Si","No")) -> No | L72: Ninguna | M72: 2 | N72: 1 | O72: 91.32 | P72: 1 | Q72: =+IF(M72="","",(IF(((M72*24)-P72)<0,0,(M72*24)-P72)*N72)) -> 47 | R72: =+(IF(((M72*24)-P72)<0,0,((M72*24)-P72)*'Estimación de pérdidas'!$F$72))*N72 -> 2710869.5 | S72: No | T72: 2-Improbable | U72: =+IF(R72="","",IF(R72<50001,1,IF(R72<200001,2,IF(R72<500001,3,IF(R72<1000001,4,5))))) -> 5 | V72: 5 | Z72: =MAX(U72:Y72) -> 5 | AA72: =IF(Z72=1,VLOOKUP(T72,$AH$3:$AI$7,2,FALSE),IF(Z72=2,VLOOKUP(T72,$AH$8:$AI$12,2, FALSE),IF(Z72=3,VLOOKUP(T72,$AH$13:$AI$17,2,FALSE),IF(Z72=4,VLOOKUP(T72,$AH$18:$AI$22,2,FALSE),IF(Z72=5,VLOOKUP(T72,$AH$23:$AI$27,2,FALSE),""))))) -> Alto | AB72: =IF(T72="1-Raro",IF(Z72=1,1,IF(Z72=2,3,IF(Z72=3,6,IF(Z72=4,10,15)))),IF(T72="2-Improbable",IF(Z72=1,2,IF(Z72=2,5,IF(Z72=3,9,IF(Z72=4,14,19)))),IF(T72="3-Posible",IF(Z72=1,4,IF(Z72=2,8,IF(Z72=3,13,IF(Z72=4,18,21)))),IF(T72="4-Probable",IF(Z72=1,7,IF(Z72=2,12,IF(Z72=3,17,IF(Z72=4,22,23)))),IF(T72="5-Casi Seguro",IF(Z72=1,11,IF(Z72=2,16,IF(Z72=3,20,IF(Z72=4,24,25))))))))) -> 19 | AC72: =((VLOOKUP(T72,$AH$3:$AJ$7,3,FALSE)*SQRT(U72^2+V72^2+W72^2+X72^2+Y72^2))/(5*SQRT((5)*5^2))) -> 0.25298221
A73: 3100 Planta de Molienda | B73: 3110 Molienda SAG | C73: Bomba alimentación hidrociclón | D73: 3110PU0061 | E73: Bomba alimentación hidrociclón | F73: 1 Op + 1 Stby: Proporcionar el flujo de alimentación a la batería de hidrociclones (3110CY0001) | G73: Falla de bomba hidráulica | H73: No afectación a operaciones, Costos de reparación de bomba | I73: 2 | J73: 1 | K73: =+IF(I73="","",IF((I73-J73)>0,"Si","No")) -> Si | L73: Activa | M73: 0.83333333 | N73: 0 | O73: 91.32 | P73: 1 | Q73: =+IF(M73="","",(IF(((M73*24)-P73)<0,0,(M73*24)-P73)*N73)) -> 0 | R73: =+(IF(((M73*24)-P73)<0,0,((M73*24)-P73)*'Estimación de pérdidas'!$F$72))*N73 -> 0 | S73: No | T73: 4-Probable | U73: =+IF(R73="","",IF(R73<50001,1,IF(R73<200001,2,IF(R73<500001,3,IF(R73<1000001,4,5))))) -> 1 | V73: 3 | Z73: =MAX(U73:Y73) -> 3 | AA73: =IF(Z73=1,VLOOKUP(T73,$AH$3:$AI$7,2,FALSE),IF(Z73=2,VLOOKUP(T73,$AH$8:$AI$12,2, FALSE),IF(Z73=3,VLOOKUP(T73,$AH$13:$AI$17,2,FALSE),IF(Z73=4,VLOOKUP(T73,$AH$18:$AI$22,2,FALSE),IF(Z73=5,VLOOKUP(T73,$AH$23:$AI$27,2,FALSE),""))))) -> Moderado | AB73: =IF(T73="1-Raro",IF(Z73=1,1,IF(Z73=2,3,IF(Z73=3,6,IF(Z73=4,10,15)))),IF(T73="2-Improbable",IF(Z73=1,2,IF(Z73=2,5,IF(Z73=3,9,IF(Z73=4,14,19)))),IF(T73="3-Posible",IF(Z73=1,4,IF(Z73=2,8,IF(Z73=3,13,IF(Z73=4,18,21)))),IF(T73="4-Probable",IF(Z73=1,7,IF(Z73=2,12,IF(Z73=3,17,IF(Z73=4,22,23)))),IF(T73="5-Casi Seguro",IF(Z73=1,11,IF(Z73=2,16,IF(Z73=3,20,IF(Z73=4,24,25))))))))) -> 17 | AC73: =((VLOOKUP(T73,$AH$3:$AJ$7,3,FALSE)*SQRT(U73^2+V73^2+W73^2+X73^2+Y73^2))/(5*SQRT((5)*5^2))) -> 0.22627417
A74: 3100 Planta de Molienda | B74: 3110 Molienda SAG | C74: Bomba alimentación hidrociclón | D74: 3110PU0062 | E74: Bomba alimentación hidrociclón | F74: 1 Op + 1 Stby: Proporcionar el flujo de alimentación a la batería de hidrociclones (3110CY0001) | G74: Falla de bomba hidráulica | H74: No afectación a operaciones, Costos de reparación de bomba | I74: 2 | J74: 1 | K74: =+IF(I74="","",IF((I74-J74)>0,"Si","No")) -> Si | L74: Activa | M74: 0.83333333 | N74: 0 | O74: 91.32 | P74: 1 | Q74: =+IF(M74="","",(IF(((M74*24)-P74)<0,0,(M74*24)-P74)*N74)) -> 0 | R74: =+(IF(((M74*24)-P74)<0,0,((M74*24)-P74)*'Estimación de pérdidas'!$F$72))*N74 -> 0 | S74: No | T74: 4-Probable | U74: =+IF(R74="","",IF(R74<50001,1,IF(R74<200001,2,IF(R74<500001,3,IF(R74<1000001,4,5))))) -> 1 | V74: 3 | Z74: =MAX(U74:Y74) -> 3 | AA74: =IF(Z74=1,VLOOKUP(T74,$AH$3:$AI$7,2,FALSE),IF(Z74=2,VLOOKUP(T74,$AH$8:$AI$12,2, FALSE),IF(Z74=3,VLOOKUP(T74,$AH$13:$AI$17,2,FALSE),IF(Z74=4,VLOOKUP(T74,$AH$18:$AI$22,2,FALSE),IF(Z74=5,VLOOKUP(T74,$AH$23:$AI$27,2,FALSE),""))))) -> Moderado | AB74: =IF(T74="1-Raro",IF(Z74=1,1,IF(Z74=2,3,IF(Z74=3,6,IF(Z74=4,10,15)))),IF(T74="2-Improbable",IF(Z74=1,2,IF(Z74=2,5,IF(Z74=3,9,IF(Z74=4,14,19)))),IF(T74="3-Posible",IF(Z74=1,4,IF(Z74=2,8,IF(Z74=3,13,IF(Z74=4,18,21)))),IF(T74="4-Probable",IF(Z74=1,7,IF(Z74=2,12,IF(Z74=3,17,IF(Z74=4,22,23)))),IF(T74="5-Casi Seguro",IF(Z74=1,11,IF(Z74=2,16,IF(Z74=3,20,IF(Z74=4,24,25))))))))) -> 17 | AC74: =((VLOOKUP(T74,$AH$3:$AJ$7,3,FALSE)*SQRT(U74^2+V74^2+W74^2+X74^2+Y74^2))/(5*SQRT((5)*5^2))) -> 0.22627417
A75: 3100 Planta de Molienda | B75: 3110 Molienda SAG | C75: Bomba sumidero Molienda | D75: 3110PU0063 | E75: Bomba sumidero molienda | F75: 1 Op + 1 Stby: Transferir los derrames desde sumidero Molienda a área Lixiviación | G75: Falla de bomba hidráulica | H75: No afectación a producción, Costos por reparación de bomba | I75: 2 | J75: 1 | K75: =+IF(I75="","",IF((I75-J75)>0,"Si","No")) -> Si | L75: Activa | M75: 0.33 | N75: 0 | O75: 91.32 | P75: 1 | Q75: =+IF(M75="","",(IF(((M75*24)-P75)<0,0,(M75*24)-P75)*N75)) -> 0 | R75: =+(IF(((M75*24)-P75)<0,0,((M75*24)-P75)*'Estimación de pérdidas'!$F$72))*N75 -> 0 | S75: No | T75: 3-Posible | U75: =+IF(R75="","",IF(R75<50001,1,IF(R75<200001,2,IF(R75<500001,3,IF(R75<1000001,4,5))))) -> 1 | V75: 1 | Z75: =MAX(U75:Y75) -> 1 | AA75: =IF(Z75=1,VLOOKUP(T75,$AH$3:$AI$7,2,FALSE),IF(Z75=2,VLOOKUP(T75,$AH$8:$AI$12,2, FALSE),IF(Z75=3,VLOOKUP(T75,$AH$13:$AI$17,2,FALSE),IF(Z75=4,VLOOKUP(T75,$AH$18:$AI$22,2,FALSE),IF(Z75=5,VLOOKUP(T75,$AH$23:$AI$27,2,FALSE),""))))) -> Bajo | AB75: =IF(T75="1-Raro",IF(Z75=1,1,IF(Z75=2,3,IF(Z75=3,6,IF(Z75=4,10,15)))),IF(T75="2-Improbable",IF(Z75=1,2,IF(Z75=2,5,IF(Z75=3,9,IF(Z75=4,14,19)))),IF(T75="3-Posible",IF(Z75=1,4,IF(Z75=2,8,IF(Z75=3,13,IF(Z75=4,18,21)))),IF(T75="4-Probable",IF(Z75=1,7,IF(Z75=2,12,IF(Z75=3,17,IF(Z75=4,22,23)))),IF(T75="5-Casi Seguro",IF(Z75=1,11,IF(Z75=2,16,IF(Z75=3,20,IF(Z75=4,24,25))))))))) -> 4 | AC75: =((VLOOKUP(T75,$AH$3:$AJ$7,3,FALSE)*SQRT(U75^2+V75^2+W75^2+X75^2+Y75^2))/(5*SQRT((5)*5^2))) -> 0.075894664
A76: 3100 Planta de Molienda | B76: 3110 Molienda SAG | C76: Bomba sumidero Molienda | D76: 3110PU0064 | E76: Bomba sumidero molienda | F76: 1 Op + 1 Stby: Transferir los derrames desde sumidero Molienda a área Lixiviación | G76: Falla de bomba hidráulica | H76: No afectación a producción, Costos por reparación de bomba | I76: 2 | J76: 1 | K76: =+IF(I76="","",IF((I76-J76)>0,"Si","No")) -> Si | L76: Activa | M76: 0.33 | N76: 0 | O76: 91.32 | P76: 1 | Q76: =+IF(M76="","",(IF(((M76*24)-P76)<0,0,(M76*24)-P76)*N76)) -> 0 | R76: =+(IF(((M76*24)-P76)<0,0,((M76*24)-P76)*'Estimación de pérdidas'!$F$72))*N76 -> 0 | S76: No | T76: 3-Posible | U76: =+IF(R76="","",IF(R76<50001,1,IF(R76<200001,2,IF(R76<500001,3,IF(R76<1000001,4,5))))) -> 1 | V76: 1 | Z76: =MAX(U76:Y76) -> 1 | AA76: =IF(Z76=1,VLOOKUP(T76,$AH$3:$AI$7,2,FALSE),IF(Z76=2,VLOOKUP(T76,$AH$8:$AI$12,2, FALSE),IF(Z76=3,VLOOKUP(T76,$AH$13:$AI$17,2,FALSE),IF(Z76=4,VLOOKUP(T76,$AH$18:$AI$22,2,FALSE),IF(Z76=5,VLOOKUP(T76,$AH$23:$AI$27,2,FALSE),""))))) -> Bajo | AB76: =IF(T76="1-Raro",IF(Z76=1,1,IF(Z76=2,3,IF(Z76=3,6,IF(Z76=4,10,15)))),IF(T76="2-Improbable",IF(Z76=1,2,IF(Z76=2,5,IF(Z76=3,9,IF(Z76=4,14,19)))),IF(T76="3-Posible",IF(Z76=1,4,IF(Z76=2,8,IF(Z76=3,13,IF(Z76=4,18,21)))),IF(T76="4-Probable",IF(Z76=1,7,IF(Z76=2,12,IF(Z76=3,17,IF(Z76=4,22,23)))),IF(T76="5-Casi Seguro",IF(Z76=1,11,IF(Z76=2,16,IF(Z76=3,20,IF(Z76=4,24,25))))))))) -> 4 | AC76: =((VLOOKUP(T76,$AH$3:$AJ$7,3,FALSE)*SQRT(U76^2+V76^2+W76^2+X76^2+Y76^2))/(5*SQRT((5)*5^2))) -> 0.075894664
A77: Activos para control de emergencias | B77: 3110 Molienda SAG | C77: Lavaojos | D77: 3110SY0005 | E77: Ducha y lava ojos emergencia | F77: Lavado de ojos de forma rápida y eficaz cuando una persona se ve afectada ante sustancias peligrosas | G77: Rotura línea alimentación agua potable / neutra | H77: No afectación a producción, Pérdida de visión de la persona | I77: 1 | J77: 1 | K77: =+IF(I77="","",IF((I77-J77)>0,"Si","No")) -> No | L77: Ninguna | M77: 0.33 | N77: 0 | P77: 0 | Q77: =+IF(M77="","",(IF(((M77*24)-P77)<0,0,(M77*24)-P77)*N77)) -> 0 | R77: =+(IF(((M77*24)-P77)<0,0,((M77*24)-P77)*'Estimación de pérdidas'!$F$72))*N77 -> 0 | S77: Si | T77: 4-Probable | U77: =+IF(R77="","",IF(R77<50001,1,IF(R77<200001,2,IF(R77<500001,3,IF(R77<1000001,4,5))))) -> 1 | V77: 1 | W77: 4 | Z77: =MAX(U77:Y77) -> 4 | AA77: =IF(Z77=1,VLOOKUP(T77,$AH$3:$AI$7,2,FALSE),IF(Z77=2,VLOOKUP(T77,$AH$8:$AI$12,2, FALSE),IF(Z77=3,VLOOKUP(T77,$AH$13:$AI$17,2,FALSE),IF(Z77=4,VLOOKUP(T77,$AH$18:$AI$22,2,FALSE),IF(Z77=5,VLOOKUP(T77,$AH$23:$AI$27,2,FALSE),""))))) -> Alto | AB77: =IF(T77="1-Raro",IF(Z77=1,1,IF(Z77=2,3,IF(Z77=3,6,IF(Z77=4,10,15)))),IF(T77="2-Improbable",IF(Z77=1,2,IF(Z77=2,5,IF(Z77=3,9,IF(Z77=4,14,19)))),IF(T77="3-Posible",IF(Z77=1,4,IF(Z77=2,8,IF(Z77=3,13,IF(Z77=4,18,21)))),IF(T77="4-Probable",IF(Z77=1,7,IF(Z77=2,12,IF(Z77=3,17,IF(Z77=4,22,23)))),IF(T77="5-Casi Seguro",IF(Z77=1,11,IF(Z77=2,16,IF(Z77=3,20,IF(Z77=4,24,25))))))))) -> 22 | AC77: =((VLOOKUP(T77,$AH$3:$AJ$7,3,FALSE)*SQRT(U77^2+V77^2+W77^2+X77^2+Y77^2))/(5*SQRT((5)*5^2))) -> 0.30357866
A78: 3100 Planta de Molienda | B78: 3120 Molienda Bolas | C78: Sistema analizador tamaño partícula | D78: 3120AY0001 | E78: Analizador tamaño partícula | F78: Analizar el tamaño de partícula de la muestra obtenida de muestreador 3120SA0004 | G78: Falla analizador | H78: No afecta a operaciones, Costos por cambio analizador | I78: 1 | J78: 1 | K78: =+IF(I78="","",IF((I78-J78)>0,"Si","No")) -> No | L78: Ninguna | M78: 0.25 | N78: 0 | P78: 0 | Q78: =+IF(M78="","",(IF(((M78*24)-P78)<0,0,(M78*24)-P78)*N78)) -> 0 | R78: =+(IF(((M78*24)-P78)<0,0,((M78*24)-P78)*'Estimación de pérdidas'!$F$72))*N78 -> 0 | S78: No | T78: 3-Posible | U78: =+IF(R78="","",IF(R78<50001,1,IF(R78<200001,2,IF(R78<500001,3,IF(R78<1000001,4,5))))) -> 1 | V78: 2 | Z78: =MAX(U78:Y78) -> 2 | AA78: =IF(Z78=1,VLOOKUP(T78,$AH$3:$AI$7,2,FALSE),IF(Z78=2,VLOOKUP(T78,$AH$8:$AI$12,2, FALSE),IF(Z78=3,VLOOKUP(T78,$AH$13:$AI$17,2,FALSE),IF(Z78=4,VLOOKUP(T78,$AH$18:$AI$22,2,FALSE),IF(Z78=5,VLOOKUP(T78,$AH$23:$AI$27,2,FALSE),""))))) -> Moderado | AB78: =IF(T78="1-Raro",IF(Z78=1,1,IF(Z78=2,3,IF(Z78=3,6,IF(Z78=4,10,15)))),IF(T78="2-Improbable",IF(Z78=1,2,IF(Z78=2,5,IF(Z78=3,9,IF(Z78=4,14,19)))),IF(T78="3-Posible",IF(Z78=1,4,IF(Z78=2,8,IF(Z78=3,13,IF(Z78=4,18,21)))),IF(T78="4-Probable",IF(Z78=1,7,IF(Z78=2,12,IF(Z78=3,17,IF(Z78=4,22,23)))),IF(T78="5-Casi Seguro",IF(Z78=1,11,IF(Z78=2,16,IF(Z78=3,20,IF(Z78=4,24,25))))))))) -> 8 | AC78: =((VLOOKUP(T78,$AH$3:$AJ$7,3,FALSE)*SQRT(U78^2+V78^2+W78^2+X78^2+Y78^2))/(5*SQRT((5)*5^2))) -> 0.12
A79: 3100 Planta de Molienda | B79: 3120 Molienda Bolas | C79: Tolva bolas Molino | D79: 3120BN0012 | E79: Tolva bolas Molino | F79: Contener las bolas requeridas proveniente de camiones para transferir a capacho 3120-KB-0002 | G79: Rotura en paredes de tolva | H79: No afectación a operaciones, Costos por reparación de tolva | I79: 1 | J79: 1 | K79: =+IF(I79="","",IF((I79-J79)>0,"Si","No")) -> No | L79: Ninguna | M79: 0.33333333 | N79: 0 | P79: 0 | Q79: =+IF(M79="","",(IF(((M79*24)-P79)<0,0,(M79*24)-P79)*N79)) -> 0 | R79: =+(IF(((M79*24)-P79)<0,0,((M79*24)-P79)*'Estimación de pérdidas'!$F$72))*N79 -> 0 | S79: No | T79: 2-Improbable | U79: =+IF(R79="","",IF(R79<50001,1,IF(R79<200001,2,IF(R79<500001,3,IF(R79<1000001,4,5))))) -> 1 | V79: 1 | Z79: =MAX(U79:Y79) -> 1 | AA79: =IF(Z79=1,VLOOKUP(T79,$AH$3:$AI$7,2,FALSE),IF(Z79=2,VLOOKUP(T79,$AH$8:$AI$12,2, FALSE),IF(Z79=3,VLOOKUP(T79,$AH$13:$AI$17,2,FALSE),IF(Z79=4,VLOOKUP(T79,$AH$18:$AI$22,2,FALSE),IF(Z79=5,VLOOKUP(T79,$AH$23:$AI$27,2,FALSE),""))))) -> Bajo | AB79: =IF(T79="1-Raro",IF(Z79=1,1,IF(Z79=2,3,IF(Z79=3,6,IF(Z79=4,10,15)))),IF(T79="2-Improbable",IF(Z79=1,2,IF(Z79=2,5,IF(Z79=3,9,IF(Z79=4,14,19)))),IF(T79="3-Posible",IF(Z79=1,4,IF(Z79=2,8,IF(Z79=3,13,IF(Z79=4,18,21)))),IF(T79="4-Probable",IF(Z79=1,7,IF(Z79=2,12,IF(Z79=3,17,IF(Z79=4,22,23)))),IF(T79="5-Casi Seguro",IF(Z79=1,11,IF(Z79=2,16,IF(Z79=3,20,IF(Z79=4,24,25))))))))) -> 2 | AC79: =((VLOOKUP(T79,$AH$3:$AJ$7,3,FALSE)*SQRT(U79^2+V79^2+W79^2+X79^2+Y79^2))/(5*SQRT((5)*5^2))) -> 0.050596443
A80: 3100 Planta de Molienda | B80: 3120 Molienda Bolas | C80: Chute intermedio alimentación | D80: 3120CH0032 | E80: Chute intermedio alimentación | F80: Recibir la descarga de bolas desde tolva 3120-HO-0002, agua y mineral proveniente de hidro ciclones para alimentar el Molino de Bolas. | G80: Rotura de chute | H80: Afectación a operaciones, Parada Molino Bolas Costos por reparación de chute | I80: 1 | J80: 1 | K80: =+IF(I80="","",IF((I80-J80)>0,"Si","No")) -> No | L80: Ninguna | M80: 0.33 | N80: 1 | O80: 91.32 | P80: 1 | Q80: =+IF(M80="","",(IF(((M80*24)-P80)<0,0,(M80*24)-P80)*N80)) -> 6.92 | R80: =+(IF(((M80*24)-P80)<0,0,((M80*24)-P80)*'Estimación de pérdidas'!$F$72))*N80 -> 399132.28 | S80: No | T80: 3-Posible | U80: =+IF(R80="","",IF(R80<50001,1,IF(R80<200001,2,IF(R80<500001,3,IF(R80<1000001,4,5))))) -> 3 | V80: 1 | Z80: =MAX(U80:Y80) -> 3 | AA80: =IF(Z80=1,VLOOKUP(T80,$AH$3:$AI$7,2,FALSE),IF(Z80=2,VLOOKUP(T80,$AH$8:$AI$12,2, FALSE),IF(Z80=3,VLOOKUP(T80,$AH$13:$AI$17,2,FALSE),IF(Z80=4,VLOOKUP(T80,$AH$18:$AI$22,2,FALSE),IF(Z80=5,VLOOKUP(T80,$AH$23:$AI$27,2,FALSE),""))))) -> Moderado | AB80: =IF(T80="1-Raro",IF(Z80=1,1,IF(Z80=2,3,IF(Z80=3,6,IF(Z80=4,10,15)))),IF(T80="2-Improbable",IF(Z80=1,2,IF(Z80=2,5,IF(Z80=3,9,IF(Z80=4,14,19)))),IF(T80="3-Posible",IF(Z80=1,4,IF(Z80=2,8,IF(Z80=3,13,IF(Z80=4,18,21)))),IF(T80="4-Probable",IF(Z80=1,7,IF(Z80=2,12,IF(Z80=3,17,IF(Z80=4,22,23)))),IF(T80="5-Casi Seguro",IF(Z80=1,11,IF(Z80=2,16,IF(Z80=3,20,IF(Z80=4,24,25))))))))) -> 13 | AC80: =((VLOOKUP(T80,$AH$3:$AJ$7,3,FALSE)*SQRT(U80^2+V80^2+W80^2+X80^2+Y80^2))/(5*SQRT((5)*5^2))) -> 0.16970563
A81: 3100 Planta de Molienda | B81: 3120 Molienda Bolas | C81: Chute desechos | D81: 3120CH0034 | E81: Chute desechos | F81: Recepcionar la descarga de desechos proveniente de Molino Bolas | G81: Rotura de chute | H81: No afectación a operaciones, Costos por reparación de chute | I81: 1 | J81: 1 | K81: =+IF(I81="","",IF((I81-J81)>0,"Si","No")) -> No | L81: Ninguna | M81: 0.33 | N81: 0 | P81: 0 | Q81: =+IF(M81="","",(IF(((M81*24)-P81)<0,0,(M81*24)-P81)*N81)) -> 0 | R81: =+(IF(((M81*24)-P81)<0,0,((M81*24)-P81)*'Estimación de pérdidas'!$F$72))*N81 -> 0 | S81: No | T81: 3-Posible | U81: =+IF(R81="","",IF(R81<50001,1,IF(R81<200001,2,IF(R81<500001,3,IF(R81<1000001,4,5))))) -> 1 | V81: 1 | Z81: =MAX(U81:Y81) -> 1 | AA81: =IF(Z81=1,VLOOKUP(T81,$AH$3:$AI$7,2,FALSE),IF(Z81=2,VLOOKUP(T81,$AH$8:$AI$12,2, FALSE),IF(Z81=3,VLOOKUP(T81,$AH$13:$AI$17,2,FALSE),IF(Z81=4,VLOOKUP(T81,$AH$18:$AI$22,2,FALSE),IF(Z81=5,VLOOKUP(T81,$AH$23:$AI$27,2,FALSE),""))))) -> Bajo | AB81: =IF(T81="1-Raro",IF(Z81=1,1,IF(Z81=2,3,IF(Z81=3,6,IF(Z81=4,10,15)))),IF(T81="2-Improbable",IF(Z81=1,2,IF(Z81=2,5,IF(Z81=3,9,IF(Z81=4,14,19)))),IF(T81="3-Posible",IF(Z81=1,4,IF(Z81=2,8,IF(Z81=3,13,IF(Z81=4,18,21)))),IF(T81="4-Probable",IF(Z81=1,7,IF(Z81=2,12,IF(Z81=3,17,IF(Z81=4,22,23)))),IF(T81="5-Casi Seguro",IF(Z81=1,11,IF(Z81=2,16,IF(Z81=3,20,IF(Z81=4,24,25))))))))) -> 4 | AC81: =((VLOOKUP(T81,$AH$3:$AJ$7,3,FALSE)*SQRT(U81^2+V81^2+W81^2+X81^2+Y81^2))/(5*SQRT((5)*5^2))) -> 0.075894664
A82: 3100 Planta de Molienda | B82: 3120 Molienda Bolas | C82: Chute Trommel Molino Bolas | D82: 3120CH0058 | E82: Chute Trommel Molino Bolas | F82: Recepcionar la pulpa bajo tamaño proveniente de Trommel de Molino Bolas | G82: Rotura de chute | H82: Afectación a operaciones, Costos por reparación de chute | I82: 1 | J82: 1 | K82: =+IF(I82="","",IF((I82-J82)>0,"Si","No")) -> No | L82: Ninguna | M82: 0.33333333 | N82: 1 | O82: 91.32 | P82: 1 | Q82: =+IF(M82="","",(IF(((M82*24)-P82)<0,0,(M82*24)-P82)*N82)) -> 7 | R82: =+(IF(((M82*24)-P82)<0,0,((M82*24)-P82)*'Estimación de pérdidas'!$F$72))*N82 -> 403746.52 | S82: No | T82: 3-Posible | U82: =+IF(R82="","",IF(R82<50001,1,IF(R82<200001,2,IF(R82<500001,3,IF(R82<1000001,4,5))))) -> 3 | V82: 1 | Z82: =MAX(U82:Y82) -> 3 | AA82: =IF(Z82=1,VLOOKUP(T82,$AH$3:$AI$7,2,FALSE),IF(Z82=2,VLOOKUP(T82,$AH$8:$AI$12,2, FALSE),IF(Z82=3,VLOOKUP(T82,$AH$13:$AI$17,2,FALSE),IF(Z82=4,VLOOKUP(T82,$AH$18:$AI$22,2,FALSE),IF(Z82=5,VLOOKUP(T82,$AH$23:$AI$27,2,FALSE),""))))) -> Moderado | AB82: =IF(T82="1-Raro",IF(Z82=1,1,IF(Z82=2,3,IF(Z82=3,6,IF(Z82=4,10,15)))),IF(T82="2-Improbable",IF(Z82=1,2,IF(Z82=2,5,IF(Z82=3,9,IF(Z82=4,14,19)))),IF(T82="3-Posible",IF(Z82=1,4,IF(Z82=2,8,IF(Z82=3,13,IF(Z82=4,18,21)))),IF(T82="4-Probable",IF(Z82=1,7,IF(Z82=2,12,IF(Z82=3,17,IF(Z82=4,22,23)))),IF(T82="5-Casi Seguro",IF(Z82=1,11,IF(Z82=2,16,IF(Z82=3,20,IF(Z82=4,24,25))))))))) -> 13 | AC82: =((VLOOKUP(T82,$AH$3:$AJ$7,3,FALSE)*SQRT(U82^2+V82^2+W82^2+X82^2+Y82^2))/(5*SQRT((5)*5^2))) -> 0.16970563
A83: 3100 Planta de Molienda | B83: 3110 Molienda SAG | C83: Circuito cerrado de televisión CCTV | D83: 3110CT0001 | E83: CCTV molienda SAG | F83: Sistema de videovigilancia diseñada para supervisar el proceso. | G83: Falla de gabinete | H83: No afectación a producción, Cambio de gabinete | I83: 1 | J83: 1 | K83: =+IF(I83="","",IF((I83-J83)>0,"Si","No")) -> No | L83: Ninguna | M83: 0.33333333 | N83: 0 | O83: 91.32 | P83: 1 | Q83: =+IF(M83="","",(IF(((M83*24)-P83)<0,0,(M83*24)-P83)*N83)) -> 0 | R83: =+(IF(((M83*24)-P83)<0,0,((M83*24)-P83)*'Estimación de pérdidas'!$F$72))*N83 -> 0 | S83: No | T83: 2-Improbable | U83: =+IF(R83="","",IF(R83<50001,1,IF(R83<200001,2,IF(R83<500001,3,IF(R83<1000001,4,5))))) -> 1 | V83: 2 | Z83: =MAX(U83:Y83) -> 2 | AA83: =IF(Z83=1,VLOOKUP(T83,$AH$3:$AI$7,2,FALSE),IF(Z83=2,VLOOKUP(T83,$AH$8:$AI$12,2, FALSE),IF(Z83=3,VLOOKUP(T83,$AH$13:$AI$17,2,FALSE),IF(Z83=4,VLOOKUP(T83,$AH$18:$AI$22,2,FALSE),IF(Z83=5,VLOOKUP(T83,$AH$23:$AI$27,2,FALSE),""))))) -> Bajo | AB83: =IF(T83="1-Raro",IF(Z83=1,1,IF(Z83=2,3,IF(Z83=3,6,IF(Z83=4,10,15)))),IF(T83="2-Improbable",IF(Z83=1,2,IF(Z83=2,5,IF(Z83=3,9,IF(Z83=4,14,19)))),IF(T83="3-Posible",IF(Z83=1,4,IF(Z83=2,8,IF(Z83=3,13,IF(Z83=4,18,21)))),IF(T83="4-Probable",IF(Z83=1,7,IF(Z83=2,12,IF(Z83=3,17,IF(Z83=4,22,23)))),IF(T83="5-Casi Seguro",IF(Z83=1,11,IF(Z83=2,16,IF(Z83=3,20,IF(Z83=4,24,25))))))))) -> 5 | AC83: =((VLOOKUP(T83,$AH$3:$AJ$7,3,FALSE)*SQRT(U83^2+V83^2+W83^2+X83^2+Y83^2))/(5*SQRT((5)*5^2))) -> 0.08
A84: 3100 Planta de Molienda | B84: 3120 Molienda Bolas | C84: Puente grúa hidrociclones | D84: 3120CN0006 | E84: Puente grúa hidrociclones | F84: Izar y desplazar cargas en hidrociclones 3120-CY-0001 | G84: Falla de cable | H84: Fatalidad o incapacidad permanente a una persona, Afectación a producción, Cambio de cable | I84: 1 | J84: 1 | K84: =+IF(I84="","",IF((I84-J84)>0,"Si","No")) -> No | L84: Ninguna | M84: 1 | N84: 0.25 | P84: 12 | Q84: =+IF(M84="","",(IF(((M84*24)-P84)<0,0,(M84*24)-P84)*N84)) -> 3 | R84: =+(IF(((M84*24)-P84)<0,0,((M84*24)-P84)*'Estimación de pérdidas'!$F$72))*N84 -> 173034.22 | S84: No | T84: 2-Improbable | U84: =+IF(R84="","",IF(R84<50001,1,IF(R84<200001,2,IF(R84<500001,3,IF(R84<1000001,4,5))))) -> 2 | V84: 2 | W84: 4 | Z84: =MAX(U84:Y84) -> 4 | AA84: =IF(Z84=1,VLOOKUP(T84,$AH$3:$AI$7,2,FALSE),IF(Z84=2,VLOOKUP(T84,$AH$8:$AI$12,2, FALSE),IF(Z84=3,VLOOKUP(T84,$AH$13:$AI$17,2,FALSE),IF(Z84=4,VLOOKUP(T84,$AH$18:$AI$22,2,FALSE),IF(Z84=5,VLOOKUP(T84,$AH$23:$AI$27,2,FALSE),""))))) -> Moderado | AB84: =IF(T84="1-Raro",IF(Z84=1,1,IF(Z84=2,3,IF(Z84=3,6,IF(Z84=4,10,15)))),IF(T84="2-Improbable",IF(Z84=1,2,IF(Z84=2,5,IF(Z84=3,9,IF(Z84=4,14,19)))),IF(T84="3-Posible",IF(Z84=1,4,IF(Z84=2,8,IF(Z84=3,13,IF(Z84=4,18,21)))),IF(T84="4-Probable",IF(Z84=1,7,IF(Z84=2,12,IF(Z84=3,17,IF(Z84=4,22,23)))),IF(T84="5-Casi Seguro",IF(Z84=1,11,IF(Z84=2,16,IF(Z84=3,20,IF(Z84=4,24,25))))))))) -> 14 | AC84: =((VLOOKUP(T84,$AH$3:$AJ$7,3,FALSE)*SQRT(U84^2+V84^2+W84^2+X84^2+Y84^2))/(5*SQRT((5)*5^2))) -> 0.17527122
A85: 3100 Planta de Molienda | B85: 3120 Molienda Bolas | C85: Batería de hidrociclones Molienda | D85: 3120CY0001 | E85: Hidrociclón molienda | F85: 10 Operando + 4 Standby: Clasificar el mineral al tamaño producto requerido para Lixiviación, mediante la separación del mineral en dos fracciones, el rebose que contiene los sólidos finos y la descarga que contiene los sólidos más gruesos. | G85: Rotura de estructura de hidrociclón | H85: No afectación a producción, Costo de cambio de hidrociclón | I85: 14 | J85: 10 | K85: =+IF(I85="","",IF((I85-J85)>0,"Si","No")) -> Si | L85: Activa | M85: 0.5 | N85: 0 | O85: 91.32 | P85: 1 | Q85: =+IF(M85="","",(IF(((M85*24)-P85)<0,0,(M85*24)-P85)*N85)) -> 0 | R85: =+(IF(((M85*24)-P85)<0,0,((M85*24)-P85)*'Estimación de pérdidas'!$F$72))*N85 -> 0 | S85: No | T85: 5-Casi seguro | U85: =+IF(R85="","",IF(R85<50001,1,IF(R85<200001,2,IF(R85<500001,3,IF(R85<1000001,4,5))))) -> 1 | V85: 2 | Z85: =MAX(U85:Y85) -> 2 | AA85: =IF(Z85=1,VLOOKUP(T85,$AH$3:$AI$7,2,FALSE),IF(Z85=2,VLOOKUP(T85,$AH$8:$AI$12,2, FALSE),IF(Z85=3,VLOOKUP(T85,$AH$13:$AI$17,2,FALSE),IF(Z85=4,VLOOKUP(T85,$AH$18:$AI$22,2,FALSE),IF(Z85=5,VLOOKUP(T85,$AH$23:$AI$27,2,FALSE),""))))) -> Moderado | AB85: =IF(T85="1-Raro",IF(Z85=1,1,IF(Z85=2,3,IF(Z85=3,6,IF(Z85=4,10,15)))),IF(T85="2-Improbable",IF(Z85=1,2,IF(Z85=2,5,IF(Z85=3,9,IF(Z85=4,14,19)))),IF(T85="3-Posible",IF(Z85=1,4,IF(Z85=2,8,IF(Z85=3,13,IF(Z85=4,18,21)))),IF(T85="4-Probable",IF(Z85=1,7,IF(Z85=2,12,IF(Z85=3,17,IF(Z85=4,22,23)))),IF(T85="5-Casi Seguro",IF(Z85=1,11,IF(Z85=2,16,IF(Z85=3,20,IF(Z85=4,24,25))))))))) -> 16 | AC85: =((VLOOKUP(T85,$AH$3:$AJ$7,3,FALSE)*SQRT(U85^2+V85^2+W85^2+X85^2+Y85^2))/(5*SQRT((5)*5^2))) -> 0.2
A86: 3100 Planta de Molienda | B86: 3120 Molienda Bolas | C86: Tolva Bolas | D86: 3120HO0002 | E86: Tolva Bolas | F86: Recibir la descarga de bolas del capacho 3120-KB-0002 mediante puente grúa y posterior alimentación a 3120CH0032 chute intermedio alimentación a Molino Bolas | G86: Rotura en paredes de tolva | H86: No afectación a producción, Costos por reparación de tolva | I86: 1 | J86: 1 | K86: =+IF(I86="","",IF((I86-J86)>0,"Si","No")) -> No | L86: Ninguna | M86: 0.33333333 | N86: 0 | P86: 0 | Q86: =+IF(M86="","",(IF(((M86*24)-P86)<0,0,(M86*24)-P86)*N86)) -> 0 | R86: =+(IF(((M86*24)-P86)<0,0,((M86*24)-P86)*'Estimación de pérdidas'!$F$72))*N86 -> 0 | S86: No | T86: 2-Improbable | U86: =+IF(R86="","",IF(R86<50001,1,IF(R86<200001,2,IF(R86<500001,3,IF(R86<1000001,4,5))))) -> 1 | V86: 1 | Z86: =MAX(U86:Y86) -> 1 | AA86: =IF(Z86=1,VLOOKUP(T86,$AH$3:$AI$7,2,FALSE),IF(Z86=2,VLOOKUP(T86,$AH$8:$AI$12,2, FALSE),IF(Z86=3,VLOOKUP(T86,$AH$13:$AI$17,2,FALSE),IF(Z86=4,VLOOKUP(T86,$AH$18:$AI$22,2,FALSE),IF(Z86=5,VLOOKUP(T86,$AH$23:$AI$27,2,FALSE),""))))) -> Bajo | AB86: =IF(T86="1-Raro",IF(Z86=1,1,IF(Z86=2,3,IF(Z86=3,6,IF(Z86=4,10,15)))),IF(T86="2-Improbable",IF(Z86=1,2,IF(Z86=2,5,IF(Z86=3,9,IF(Z86=4,14,19)))),IF(T86="3-Posible",IF(Z86=1,4,IF(Z86=2,8,IF(Z86=3,13,IF(Z86=4,18,21)))),IF(T86="4-Probable",IF(Z86=1,7,IF(Z86=2,12,IF(Z86=3,17,IF(Z86=4,22,23)))),IF(T86="5-Casi Seguro",IF(Z86=1,11,IF(Z86=2,16,IF(Z86=3,20,IF(Z86=4,24,25))))))))) -> 2 | AC86: =((VLOOKUP(T86,$AH$3:$AJ$7,3,FALSE)*SQRT(U86^2+V86^2+W86^2+X86^2+Y86^2))/(5*SQRT((5)*5^2))) -> 0.050596443
A87: 3100 Planta de Molienda | B87: 3120 Molienda Bolas | C87: Tecle removedor pernos | D87: 3120HT0014 | E87: Tecle removedor pernos | F87: Izar y trasladar tubería alimentación ciclón 3120-CY-0001 | G87: Falla de cableado / cadena | H87: No afectación a operaciones, Cambiar el tecle | I87: 1 | J87: 1 | K87: =+IF(I87="","",IF((I87-J87)>0,"Si","No")) -> No | L87: Ninguna | M87: 0.33333333 | N87: 0 | P87: 0 | Q87: =+IF(M87="","",(IF(((M87*24)-P87)<0,0,(M87*24)-P87)*N87)) -> 0 | R87: =+(IF(((M87*24)-P87)<0,0,((M87*24)-P87)*'Estimación de pérdidas'!$F$72))*N87 -> 0 | S87: No | T87: 3-Posible | U87: =+IF(R87="","",IF(R87<50001,1,IF(R87<200001,2,IF(R87<500001,3,IF(R87<1000001,4,5))))) -> 1 | V87: 1 | Z87: =MAX(U87:Y87) -> 1 | AA87: =IF(Z87=1,VLOOKUP(T87,$AH$3:$AI$7,2,FALSE),IF(Z87=2,VLOOKUP(T87,$AH$8:$AI$12,2, FALSE),IF(Z87=3,VLOOKUP(T87,$AH$13:$AI$17,2,FALSE),IF(Z87=4,VLOOKUP(T87,$AH$18:$AI$22,2,FALSE),IF(Z87=5,VLOOKUP(T87,$AH$23:$AI$27,2,FALSE),""))))) -> Bajo | AB87: =IF(T87="1-Raro",IF(Z87=1,1,IF(Z87=2,3,IF(Z87=3,6,IF(Z87=4,10,15)))),IF(T87="2-Improbable",IF(Z87=1,2,IF(Z87=2,5,IF(Z87=3,9,IF(Z87=4,14,19)))),IF(T87="3-Posible",IF(Z87=1,4,IF(Z87=2,8,IF(Z87=3,13,IF(Z87=4,18,21)))),IF(T87="4-Probable",IF(Z87=1,7,IF(Z87=2,12,IF(Z87=3,17,IF(Z87=4,22,23)))),IF(T87="5-Casi Seguro",IF(Z87=1,11,IF(Z87=2,16,IF(Z87=3,20,IF(Z87=4,24,25))))))))) -> 4 | AC87: =((VLOOKUP(T87,$AH$3:$AJ$7,3,FALSE)*SQRT(U87^2+V87^2+W87^2+X87^2+Y87^2))/(5*SQRT((5)*5^2))) -> 0.075894664
A88: 3100 Planta de Molienda | B88: 3120 Molienda Bolas | C88: Contenedor bolas | D88: 3120KB0002 | E88: Contenedor bolas | F88: Depositar las bolas que serán transferidas desde 3120-BN-0012 tolva desechos hacia 3120-HO-0002 tolva de bolas cuando sea requerido. | G88: Falla eje de capacho | H88: No afectación a operación de planta, Costos por cambio de eje de capacho | I88: 1 | J88: 1 | K88: =+IF(I88="","",IF((I88-J88)>0,"Si","No")) -> No | L88: Ninguna | M88: 0.25 | N88: 0 | P88: 0 | Q88: =+IF(M88="","",(IF(((M88*24)-P88)<0,0,(M88*24)-P88)*N88)) -> 0 | R88: =+(IF(((M88*24)-P88)<0,0,((M88*24)-P88)*'Estimación de pérdidas'!$F$72))*N88 -> 0 | S88: No | T88: 3-Posible | U88: =+IF(R88="","",IF(R88<50001,1,IF(R88<200001,2,IF(R88<500001,3,IF(R88<1000001,4,5))))) -> 1 | V88: 1 | Z88: =MAX(U88:Y88) -> 1 | AA88: =IF(Z88=1,VLOOKUP(T88,$AH$3:$AI$7,2,FALSE),IF(Z88=2,VLOOKUP(T88,$AH$8:$AI$12,2, FALSE),IF(Z88=3,VLOOKUP(T88,$AH$13:$AI$17,2,FALSE),IF(Z88=4,VLOOKUP(T88,$AH$18:$AI$22,2,FALSE),IF(Z88=5,VLOOKUP(T88,$AH$23:$AI$27,2,FALSE),""))))) -> Bajo | AB88: =IF(T88="1-Raro",IF(Z88=1,1,IF(Z88=2,3,IF(Z88=3,6,IF(Z88=4,10,15)))),IF(T88="2-Improbable",IF(Z88=1,2,IF(Z88=2,5,IF(Z88=3,9,IF(Z88=4,14,19)))),IF(T88="3-Posible",IF(Z88=1,4,IF(Z88=2,8,IF(Z88=3,13,IF(Z88=4,18,21)))),IF(T88="4-Probable",IF(Z88=1,7,IF(Z88=2,12,IF(Z88=3,17,IF(Z88=4,22,23)))),IF(T88="5-Casi Seguro",IF(Z88=1,11,IF(Z88=2,16,IF(Z88=3,20,IF(Z88=4,24,25))))))))) -> 4 | AC88: =((VLOOKUP(T88,$AH$3:$AJ$7,3,FALSE)*SQRT(U88^2+V88^2+W88^2+X88^2+Y88^2))/(5*SQRT((5)*5^2))) -> 0.075894664
A89: 3100 Planta de Molienda | B89: 3120 Molienda Bolas | C89: Removedor pernos | D89: 3120ME0013 | E89: Removedor pernos | F89: Remover pernos de Molino Bolas | G89: Falla en unidad hidráulica | H89: No afecta operación de Molienda, Cambio de unidad hidráulica | I89: 1 | J89: 1 | K89: =+IF(I89="","",IF((I89-J89)>0,"Si","No")) -> No | L89: Ninguna | M89: 0.25 | N89: 0.25 | P89: 0 | Q89: =+IF(M89="","",(IF(((M89*24)-P89)<0,0,(M89*24)-P89)*N89)) -> 1.5 | R89: =+(IF(((M89*24)-P89)<0,0,((M89*24)-P89)*'Estimación de pérdidas'!$F$72))*N89 -> 86517.112 | S89: No | T89: 3-Posible | U89: =+IF(R89="","",IF(R89<50001,1,IF(R89<200001,2,IF(R89<500001,3,IF(R89<1000001,4,5))))) -> 2 | V89: 2 | Z89: =MAX(U89:Y89) -> 2 | AA89: =IF(Z89=1,VLOOKUP(T89,$AH$3:$AI$7,2,FALSE),IF(Z89=2,VLOOKUP(T89,$AH$8:$AI$12,2, FALSE),IF(Z89=3,VLOOKUP(T89,$AH$13:$AI$17,2,FALSE),IF(Z89=4,VLOOKUP(T89,$AH$18:$AI$22,2,FALSE),IF(Z89=5,VLOOKUP(T89,$AH$23:$AI$27,2,FALSE),""))))) -> Moderado | AB89: =IF(T89="1-Raro",IF(Z89=1,1,IF(Z89=2,3,IF(Z89=3,6,IF(Z89=4,10,15)))),IF(T89="2-Improbable",IF(Z89=1,2,IF(Z89=2,5,IF(Z89=3,9,IF(Z89=4,14,19)))),IF(T89="3-Posible",IF(Z89=1,4,IF(Z89=2,8,IF(Z89=3,13,IF(Z89=4,18,21)))),IF(T89="4-Probable",IF(Z89=1,7,IF(Z89=2,12,IF(Z89=3,17,IF(Z89=4,22,23)))),IF(T89="5-Casi Seguro",IF(Z89=1,11,IF(Z89=2,16,IF(Z89=3,20,IF(Z89=4,24,25))))))))) -> 8 | AC89: =((VLOOKUP(T89,$AH$3:$AJ$7,3,FALSE)*SQRT(U89^2+V89^2+W89^2+X89^2+Y89^2))/(5*SQRT((5)*5^2))) -> 0.15178933
A90: 3100 Planta de Molienda | B90: 3120 Molienda Bolas | C90: Inching Drive Molino Bolas | D90: 3120ME0014 | E90: Inching drive molino Bolas | F90: Mover el Molino de forma lenta en mantención | G90: Rotura componentes internos inching drive | H90: Afectación a producción, Alarga parada de mantención de Molino Bolas Cambio de inching drive | I90: 1 | J90: 1 | K90: =+IF(I90="","",IF((I90-J90)>0,"Si","No")) -> No | L90: Ninguna | M90: 0.5 | N90: 1 | P90: 0 | Q90: =+IF(M90="","",(IF(((M90*24)-P90)<0,0,(M90*24)-P90)*N90)) -> 12 | R90: =+(IF(((M90*24)-P90)<0,0,((M90*24)-P90)*'Estimación de pérdidas'!$F$72))*N90 -> 692136.9 | S90: No | T90: 2-Improbable | U90: =+IF(R90="","",IF(R90<50001,1,IF(R90<200001,2,IF(R90<500001,3,IF(R90<1000001,4,5))))) -> 4 | V90: 2 | Z90: =MAX(U90:Y90) -> 4 | AA90: =IF(Z90=1,VLOOKUP(T90,$AH$3:$AI$7,2,FALSE),IF(Z90=2,VLOOKUP(T90,$AH$8:$AI$12,2, FALSE),IF(Z90=3,VLOOKUP(T90,$AH$13:$AI$17,2,FALSE),IF(Z90=4,VLOOKUP(T90,$AH$18:$AI$22,2,FALSE),IF(Z90=5,VLOOKUP(T90,$AH$23:$AI$27,2,FALSE),""))))) -> Moderado | AB90: =IF(T90="1-Raro",IF(Z90=1,1,IF(Z90=2,3,IF(Z90=3,6,IF(Z90=4,10,15)))),IF(T90="2-Improbable",IF(Z90=1,2,IF(Z90=2,5,IF(Z90=3,9,IF(Z90=4,14,19)))),IF(T90="3-Posible",IF(Z90=1,4,IF(Z90=2,8,IF(Z90=3,13,IF(Z90=4,18,21)))),IF(T90="4-Probable",IF(Z90=1,7,IF(Z90=2,12,IF(Z90=3,17,IF(Z90=4,22,23)))),IF(T90="5-Casi Seguro",IF(Z90=1,11,IF(Z90=2,16,IF(Z90=3,20,IF(Z90=4,24,25))))))))) -> 14 | AC90: =((VLOOKUP(T90,$AH$3:$AJ$7,3,FALSE)*SQRT(U90^2+V90^2+W90^2+X90^2+Y90^2))/(5*SQRT((5)*5^2))) -> 0.16
A91: 3100 Planta de Molienda | B91: 3120 Molienda Bolas | C91: Molino Bolas | D91: 3120MI0002 | E91: Molino bolas | F91: Reducir de tamaño el material grueso que descarga de 3120-CY-0001 batería de hidrociclones con el fin de contribuir a obtener la distribución granulométrica con tamaño producto P80 =75 μm para el circuito global de molienda (SAG-Molienda bolas). | G91: Falla motor eléctrico por cortocircuito | H91: Afectación a operaciones, Parada de Molino Bolas, Costos por cambio de motor eléctrico | I91: 1 | J91: 1 | K91: =+IF(I91="","",IF((I91-J91)>0,"Si","No")) -> No | L91: Ninguna | M91: 2 | N91: 1 | O91: 91.32 | P91: 1 | Q91: =+IF(M91="","",(IF(((M91*24)-P91)<0,0,(M91*24)-P91)*N91)) -> 47 | R91: =+(IF(((M91*24)-P91)<0,0,((M91*24)-P91)*'Estimación de pérdidas'!$F$72))*N91 -> 2710869.5 | S91: No | T91: 2-Improbable | U91: =+IF(R91="","",IF(R91<50001,1,IF(R91<200001,2,IF(R91<500001,3,IF(R91<1000001,4,5))))) -> 5 | V91: 5 | Z91: =MAX(U91:Y91) -> 5 | AA91: =IF(Z91=1,VLOOKUP(T91,$AH$3:$AI$7,2,FALSE),IF(Z91=2,VLOOKUP(T91,$AH$8:$AI$12,2, FALSE),IF(Z91=3,VLOOKUP(T91,$AH$13:$AI$17,2,FALSE),IF(Z91=4,VLOOKUP(T91,$AH$18:$AI$22,2,FALSE),IF(Z91=5,VLOOKUP(T91,$AH$23:$AI$27,2,FALSE),""))))) -> Alto | AB91: =IF(T91="1-Raro",IF(Z91=1,1,IF(Z91=2,3,IF(Z91=3,6,IF(Z91=4,10,15)))),IF(T91="2-Improbable",IF(Z91=1,2,IF(Z91=2,5,IF(Z91=3,9,IF(Z91=4,14,19)))),IF(T91="3-Posible",IF(Z91=1,4,IF(Z91=2,8,IF(Z91=3,13,IF(Z91=4,18,21)))),IF(T91="4-Probable",IF(Z91=1,7,IF(Z91=2,12,IF(Z91=3,17,IF(Z91=4,22,23)))),IF(T91="5-Casi Seguro",IF(Z91=1,11,IF(Z91=2,16,IF(Z91=3,20,IF(Z91=4,24,25))))))))) -> 19 | AC91: =((VLOOKUP(T91,$AH$3:$AJ$7,3,FALSE)*SQRT(U91^2+V91^2+W91^2+X91^2+Y91^2))/(5*SQRT((5)*5^2))) -> 0.25298221
A92: 3100 Planta de Molienda | B92: 3120 Molienda Bolas | C92: Bomba rechazo muestreo | D92: 3120PU0085 | E92: Bomba rechazo muestreo | F92: Retornar la muestra obtenida a través de 3120SA0004 muestreador hacia 3120BX0003/4 cajones descarga de harneros | G92: Falla de bomba hidráulica | H92: No afecta operación de Molienda, cambio de bomba | I92: 1 | J92: 1 | K92: =+IF(I92="","",IF((I92-J92)>0,"Si","No")) -> No | L92: Ninguna | M92: 0.25 | N92: 0 | P92: 0 | Q92: =+IF(M92="","",(IF(((M92*24)-P92)<0,0,(M92*24)-P92)*N92)) -> 0 | R92: =+(IF(((M92*24)-P92)<0,0,((M92*24)-P92)*'Estimación de pérdidas'!$F$72))*N92 -> 0 | S92: No | T92: 4-Probable | U92: =+IF(R92="","",IF(R92<50001,1,IF(R92<200001,2,IF(R92<500001,3,IF(R92<1000001,4,5))))) -> 1 | V92: 1 | Z92: =MAX(U92:Y92) -> 1 | AA92: =IF(Z92=1,VLOOKUP(T92,$AH$3:$AI$7,2,FALSE),IF(Z92=2,VLOOKUP(T92,$AH$8:$AI$12,2, FALSE),IF(Z92=3,VLOOKUP(T92,$AH$13:$AI$17,2,FALSE),IF(Z92=4,VLOOKUP(T92,$AH$18:$AI$22,2,FALSE),IF(Z92=5,VLOOKUP(T92,$AH$23:$AI$27,2,FALSE),""))))) -> Bajo | AB92: =IF(T92="1-Raro",IF(Z92=1,1,IF(Z92=2,3,IF(Z92=3,6,IF(Z92=4,10,15)))),IF(T92="2-Improbable",IF(Z92=1,2,IF(Z92=2,5,IF(Z92=3,9,IF(Z92=4,14,19)))),IF(T92="3-Posible",IF(Z92=1,4,IF(Z92=2,8,IF(Z92=3,13,IF(Z92=4,18,21)))),IF(T92="4-Probable",IF(Z92=1,7,IF(Z92=2,12,IF(Z92=3,17,IF(Z92=4,22,23)))),IF(T92="5-Casi Seguro",IF(Z92=1,11,IF(Z92=2,16,IF(Z92=3,20,IF(Z92=4,24,25))))))))) -> 7 | AC92: =((VLOOKUP(T92,$AH$3:$AJ$7,3,FALSE)*SQRT(U92^2+V92^2+W92^2+X92^2+Y92^2))/(5*SQRT((5)*5^2))) -> 0.10119289
A93: 3100 Planta de Molienda | B93: 3120 Molienda Bolas | C93: Muestreador rebose hidrociclones | D93: 3120SA0004 | E93: Muestreador rebose hidrociclones | F93: Obtener una muestra del rebose de hidrociclones 3120-CY-0001 | G93: Falla de motor eléctrico por cortocircuito | H93: No afecta operación de Molienda, Cambiar motorreductor | I93: 1 | J93: 1 | K93: =+IF(I93="","",IF((I93-J93)>0,"Si","No")) -> No | L93: Ninguna | M93: 0.25 | N93: 0 | P93: 0 | Q93: =+IF(M93="","",(IF(((M93*24)-P93)<0,0,(M93*24)-P93)*N93)) -> 0 | R93: =+(IF(((M93*24)-P93)<0,0,((M93*24)-P93)*'Estimación de pérdidas'!$F$72))*N93 -> 0 | S93: No | T93: 3-Posible | U93: =+IF(R93="","",IF(R93<50001,1,IF(R93<200001,2,IF(R93<500001,3,IF(R93<1000001,4,5))))) -> 1 | V93: 1 | Z93: =MAX(U93:Y93) -> 1 | AA93: =IF(Z93=1,VLOOKUP(T93,$AH$3:$AI$7,2,FALSE),IF(Z93=2,VLOOKUP(T93,$AH$8:$AI$12,2, FALSE),IF(Z93=3,VLOOKUP(T93,$AH$13:$AI$17,2,FALSE),IF(Z93=4,VLOOKUP(T93,$AH$18:$AI$22,2,FALSE),IF(Z93=5,VLOOKUP(T93,$AH$23:$AI$27,2,FALSE),""))))) -> Bajo | AB93: =IF(T93="1-Raro",IF(Z93=1,1,IF(Z93=2,3,IF(Z93=3,6,IF(Z93=4,10,15)))),IF(T93="2-Improbable",IF(Z93=1,2,IF(Z93=2,5,IF(Z93=3,9,IF(Z93=4,14,19)))),IF(T93="3-Posible",IF(Z93=1,4,IF(Z93=2,8,IF(Z93=3,13,IF(Z93=4,18,21)))),IF(T93="4-Probable",IF(Z93=1,7,IF(Z93=2,12,IF(Z93=3,17,IF(Z93=4,22,23)))),IF(T93="5-Casi Seguro",IF(Z93=1,11,IF(Z93=2,16,IF(Z93=3,20,IF(Z93=4,24,25))))))))) -> 4 | AC93: =((VLOOKUP(T93,$AH$3:$AJ$7,3,FALSE)*SQRT(U93^2+V93^2+W93^2+X93^2+Y93^2))/(5*SQRT((5)*5^2))) -> 0.075894664
A94: 3100 Planta de Molienda | B94: 3120 Molienda Bolas | C94: Harnero rechazo | D94: 3120SN0008 | E94: Harnero rechazo | F94: 1 Op + 1 Stby: Clasificar material fino proveniente de hidrociclones 3120-CY-0001 hacia 3120SA0004 muestreador | G94: Falla de frame, viga y laterales de harnero por fisura | H94: No afecta operación de Molienda, Cambiar frame, viga y laterales de harnero | I94: 2 | J94: 1 | K94: =+IF(I94="","",IF((I94-J94)>0,"Si","No")) -> Si | L94: Activa | M94: 0.41666667 | N94: 0 | O94: 91.32 | P94: 1 | Q94: =+IF(M94="","",(IF(((M94*24)-P94)<0,0,(M94*24)-P94)*N94)) -> 0 | R94: =+(IF(((M94*24)-P94)<0,0,((M94*24)-P94)*'Estimación de pérdidas'!$F$72))*N94 -> 0 | S94: No | T94: 3-Posible | U94: =+IF(R94="","",IF(R94<50001,1,IF(R94<200001,2,IF(R94<500001,3,IF(R94<1000001,4,5))))) -> 1 | V94: 3 | Z94: =MAX(U94:Y94) -> 3 | AA94: =IF(Z94=1,VLOOKUP(T94,$AH$3:$AI$7,2,FALSE),IF(Z94=2,VLOOKUP(T94,$AH$8:$AI$12,2, FALSE),IF(Z94=3,VLOOKUP(T94,$AH$13:$AI$17,2,FALSE),IF(Z94=4,VLOOKUP(T94,$AH$18:$AI$22,2,FALSE),IF(Z94=5,VLOOKUP(T94,$AH$23:$AI$27,2,FALSE),""))))) -> Moderado | AB94: =IF(T94="1-Raro",IF(Z94=1,1,IF(Z94=2,3,IF(Z94=3,6,IF(Z94=4,10,15)))),IF(T94="2-Improbable",IF(Z94=1,2,IF(Z94=2,5,IF(Z94=3,9,IF(Z94=4,14,19)))),IF(T94="3-Posible",IF(Z94=1,4,IF(Z94=2,8,IF(Z94=3,13,IF(Z94=4,18,21)))),IF(T94="4-Probable",IF(Z94=1,7,IF(Z94=2,12,IF(Z94=3,17,IF(Z94=4,22,23)))),IF(T94="5-Casi Seguro",IF(Z94=1,11,IF(Z94=2,16,IF(Z94=3,20,IF(Z94=4,24,25))))))))) -> 13 | AC94: =((VLOOKUP(T94,$AH$3:$AJ$7,3,FALSE)*SQRT(U94^2+V94^2+W94^2+X94^2+Y94^2))/(5*SQRT((5)*5^2))) -> 0.16970563
A95: 3100 Planta de Molienda | B95: 3120 Molienda Bolas | C95: Harnero rechazo | D95: 3120SN0009 | E95: Harnero rechazo | F95: 1 Op + 1 Stby: Clasificar material fino proveniente de hidrociclones 3120-CY-0001 hacia 3120SA0004 muestreador | G95: Falla de frame, viga y laterales de harnero por fisura | H95: No afecta operación de Molienda, Cambiar frame, viga y laterales de harnero | I95: 2 | J95: 1 | K95: =+IF(I95="","",IF((I95-J95)>0,"Si","No")) -> Si | L95: Activa | M95: 0.41666667 | N95: 0 | O95: 91.32 | P95: 1 | Q95: =+IF(M95="","",(IF(((M95*24)-P95)<0,0,(M95*24)-P95)*N95)) -> 0 | R95: =+(IF(((M95*24)-P95)<0,0,((M95*24)-P95)*'Estimación de pérdidas'!$F$72))*N95 -> 0 | S95: No | T95: 3-Posible | U95: =+IF(R95="","",IF(R95<50001,1,IF(R95<200001,2,IF(R95<500001,3,IF(R95<1000001,4,5))))) -> 1 | V95: 3 | Z95: =MAX(U95:Y95) -> 3 | AA95: =IF(Z95=1,VLOOKUP(T95,$AH$3:$AI$7,2,FALSE),IF(Z95=2,VLOOKUP(T95,$AH$8:$AI$12,2, FALSE),IF(Z95=3,VLOOKUP(T95,$AH$13:$AI$17,2,FALSE),IF(Z95=4,VLOOKUP(T95,$AH$18:$AI$22,2,FALSE),IF(Z95=5,VLOOKUP(T95,$AH$23:$AI$27,2,FALSE),""))))) -> Moderado | AB95: =IF(T95="1-Raro",IF(Z95=1,1,IF(Z95=2,3,IF(Z95=3,6,IF(Z95=4,10,15)))),IF(T95="2-Improbable",IF(Z95=1,2,IF(Z95=2,5,IF(Z95=3,9,IF(Z95=4,14,19)))),IF(T95="3-Posible",IF(Z95=1,4,IF(Z95=2,8,IF(Z95=3,13,IF(Z95=4,18,21)))),IF(T95="4-Probable",IF(Z95=1,7,IF(Z95=2,12,IF(Z95=3,17,IF(Z95=4,22,23)))),IF(T95="5-Casi Seguro",IF(Z95=1,11,IF(Z95=2,16,IF(Z95=3,20,IF(Z95=4,24,25))))))))) -> 13 | AC95: =((VLOOKUP(T95,$AH$3:$AJ$7,3,FALSE)*SQRT(U95^2+V95^2+W95^2+X95^2+Y95^2))/(5*SQRT((5)*5^2))) -> 0.16970563
A96: 3200 Lixiviación | B96: 3210 Espesamiento de Lixiviación | C96: Bomba descarga espesador | D96: 3210PU0081 | E96: Bomba descarga espesador lixiviación | F96: 1 Op + 1 Stby: Descargar el sólido de espesador lixiviación 3210-TH-0001 a muestreo primario | G96: Falla de bomba hidráulica | H96: No afectación a producción, Cambio de componentes internos de bombas | I96: 2 | J96: 1 | K96: =+IF(I96="","",IF((I96-J96)>0,"Si","No")) -> Si | L96: Activa | M96: 1 | N96: 0 | O96: 91.32 | P96: 1 | Q96: =+IF(M96="","",(IF(((M96*24)-P96)<0,0,(M96*24)-P96)*N96)) -> 0 | R96: =+(IF(((M96*24)-P96)<0,0,((M96*24)-P96)*'Estimación de pérdidas'!$F$72))*N96 -> 0 | S96: No | T96: 4-Probable | U96: =+IF(R96="","",IF(R96<50001,1,IF(R96<200001,2,IF(R96<500001,3,IF(R96<1000001,4,5))))) -> 1 | V96: 2 | Z96: =MAX(U96:Y96) -> 2 | AA96: =IF(Z96=1,VLOOKUP(T96,$AH$3:$AI$7,2,FALSE),IF(Z96=2,VLOOKUP(T96,$AH$8:$AI$12,2, FALSE),IF(Z96=3,VLOOKUP(T96,$AH$13:$AI$17,2,FALSE),IF(Z96=4,VLOOKUP(T96,$AH$18:$AI$22,2,FALSE),IF(Z96=5,VLOOKUP(T96,$AH$23:$AI$27,2,FALSE),""))))) -> Moderado | AB96: =IF(T96="1-Raro",IF(Z96=1,1,IF(Z96=2,3,IF(Z96=3,6,IF(Z96=4,10,15)))),IF(T96="2-Improbable",IF(Z96=1,2,IF(Z96=2,5,IF(Z96=3,9,IF(Z96=4,14,19)))),IF(T96="3-Posible",IF(Z96=1,4,IF(Z96=2,8,IF(Z96=3,13,IF(Z96=4,18,21)))),IF(T96="4-Probable",IF(Z96=1,7,IF(Z96=2,12,IF(Z96=3,17,IF(Z96=4,22,23)))),IF(T96="5-Casi Seguro",IF(Z96=1,11,IF(Z96=2,16,IF(Z96=3,20,IF(Z96=4,24,25))))))))) -> 12 | AC96: =((VLOOKUP(T96,$AH$3:$AJ$7,3,FALSE)*SQRT(U96^2+V96^2+W96^2+X96^2+Y96^2))/(5*SQRT((5)*5^2))) -> 0.16
A97: 3200 Lixiviación | B97: 3210 Espesamiento de Lixiviación | C97: Bomba descarga espesador | D97: 3210PU0082 | E97: Bomba descarga espesador lixiviación | F97: 1 Op + 1 Stby: Descargar el sólido de espesador lixiviación 3210-TH-0001 a muestreo primario | G97: Falla de bomba hidráulica | H97: No afectación a producción, Cambio de componentes internos de bombas | I97: 2 | J97: 1 | K97: =+IF(I97="","",IF((I97-J97)>0,"Si","No")) -> Si | L97: Activa | M97: 1 | N97: 0 | O97: 91.32 | P97: 1 | Q97: =+IF(M97="","",(IF(((M97*24)-P97)<0,0,(M97*24)-P97)*N97)) -> 0 | R97: =+(IF(((M97*24)-P97)<0,0,((M97*24)-P97)*'Estimación de pérdidas'!$F$72))*N97 -> 0 | S97: No | T97: 4-Probable | U97: =+IF(R97="","",IF(R97<50001,1,IF(R97<200001,2,IF(R97<500001,3,IF(R97<1000001,4,5))))) -> 1 | V97: 2 | Z97: =MAX(U97:Y97) -> 2 | AA97: =IF(Z97=1,VLOOKUP(T97,$AH$3:$AI$7,2,FALSE),IF(Z97=2,VLOOKUP(T97,$AH$8:$AI$12,2, FALSE),IF(Z97=3,VLOOKUP(T97,$AH$13:$AI$17,2,FALSE),IF(Z97=4,VLOOKUP(T97,$AH$18:$AI$22,2,FALSE),IF(Z97=5,VLOOKUP(T97,$AH$23:$AI$27,2,FALSE),""))))) -> Moderado | AB97: =IF(T97="1-Raro",IF(Z97=1,1,IF(Z97=2,3,IF(Z97=3,6,IF(Z97=4,10,15)))),IF(T97="2-Improbable",IF(Z97=1,2,IF(Z97=2,5,IF(Z97=3,9,IF(Z97=4,14,19)))),IF(T97="3-Posible",IF(Z97=1,4,IF(Z97=2,8,IF(Z97=3,13,IF(Z97=4,18,21)))),IF(T97="4-Probable",IF(Z97=1,7,IF(Z97=2,12,IF(Z97=3,17,IF(Z97=4,22,23)))),IF(T97="5-Casi Seguro",IF(Z97=1,11,IF(Z97=2,16,IF(Z97=3,20,IF(Z97=4,24,25))))))))) -> 12 | AC97: =((VLOOKUP(T97,$AH$3:$AJ$7,3,FALSE)*SQRT(U97^2+V97^2+W97^2+X97^2+Y97^2))/(5*SQRT((5)*5^2))) -> 0.16
A98: 3200 Lixiviación | B98: 3210 Espesamiento de Lixiviación | C98: Bomba sumidero espesador lixiviación | D98: 3210PU0084 | E98: Bomba sumidero espesador lixiviación | F98: Descargar derrames desde sumidero hacia 3210-TH-0001 Espesador de Lixiviación | G98: Falla de bomba hidráulica | H98: No afectación a producción, Cambio de componentes internos de bomba | I98: 1 | J98: 1 | K98: =+IF(I98="","",IF((I98-J98)>0,"Si","No")) -> No | L98: Ninguna | M98: 0.33 | N98: 0 | P98: 0 | Q98: =+IF(M98="","",(IF(((M98*24)-P98)<0,0,(M98*24)-P98)*N98)) -> 0 | R98: =+(IF(((M98*24)-P98)<0,0,((M98*24)-P98)*'Estimación de pérdidas'!$F$72))*N98 -> 0 | S98: No | T98: 3-Posible | U98: =+IF(R98="","",IF(R98<50001,1,IF(R98<200001,2,IF(R98<500001,3,IF(R98<1000001,4,5))))) -> 1 | V98: 1 | Z98: =MAX(U98:Y98) -> 1 | AA98: =IF(Z98=1,VLOOKUP(T98,$AH$3:$AI$7,2,FALSE),IF(Z98=2,VLOOKUP(T98,$AH$8:$AI$12,2, FALSE),IF(Z98=3,VLOOKUP(T98,$AH$13:$AI$17,2,FALSE),IF(Z98=4,VLOOKUP(T98,$AH$18:$AI$22,2,FALSE),IF(Z98=5,VLOOKUP(T98,$AH$23:$AI$27,2,FALSE),""))))) -> Bajo | AB98: =IF(T98="1-Raro",IF(Z98=1,1,IF(Z98=2,3,IF(Z98=3,6,IF(Z98=4,10,15)))),IF(T98="2-Improbable",IF(Z98=1,2,IF(Z98=2,5,IF(Z98=3,9,IF(Z98=4,14,19)))),IF(T98="3-Posible",IF(Z98=1,4,IF(Z98=2,8,IF(Z98=3,13,IF(Z98=4,18,21)))),IF(T98="4-Probable",IF(Z98=1,7,IF(Z98=2,12,IF(Z98=3,17,IF(Z98=4,22,23)))),IF(T98="5-Casi Seguro",IF(Z98=1,11,IF(Z98=2,16,IF(Z98=3,20,IF(Z98=4,24,25))))))))) -> 4 | AC98: =((VLOOKUP(T98,$AH$3:$AJ$7,3,FALSE)*SQRT(U98^2+V98^2+W98^2+X98^2+Y98^2))/(5*SQRT((5)*5^2))) -> 0.075894664
A99: 3200 Lixiviación | B99: 3210 Espesamiento de Lixiviación | C99: Muestreador primario alimentación lixiviación | D99: 3210SA0001 | E99: Muestreador primario lixiviación | F99: Cortar una fracción de flujo principal proveniente de 3210-PU-0081/0082 bomba descarga espesador o solución detox proveniente de 3700-PU-0271/0272 para muestreo | G99: Falla de motor eléctrico por cortocircuito | H99: No afectación a producción, Cambiar motorreductor | I99: 1 | J99: 1 | K99: =+IF(I99="","",IF((I99-J99)>0,"Si","No")) -> No | L99: Ninguna | M99: 0.25 | N99: 0 | P99: 0 | Q99: =+IF(M99="","",(IF(((M99*24)-P99)<0,0,(M99*24)-P99)*N99)) -> 0 | R99: =+(IF(((M99*24)-P99)<0,0,((M99*24)-P99)*'Estimación de pérdidas'!$F$72))*N99 -> 0 | S99: No | T99: 3-Posible | U99: =+IF(R99="","",IF(R99<50001,1,IF(R99<200001,2,IF(R99<500001,3,IF(R99<1000001,4,5))))) -> 1 | V99: 1 | Z99: =MAX(U99:Y99) -> 1 | AA99: =IF(Z99=1,VLOOKUP(T99,$AH$3:$AI$7,2,FALSE),IF(Z99=2,VLOOKUP(T99,$AH$8:$AI$12,2, FALSE),IF(Z99=3,VLOOKUP(T99,$AH$13:$AI$17,2,FALSE),IF(Z99=4,VLOOKUP(T99,$AH$18:$AI$22,2,FALSE),IF(Z99=5,VLOOKUP(T99,$AH$23:$AI$27,2,FALSE),""))))) -> Bajo | AB99: =IF(T99="1-Raro",IF(Z99=1,1,IF(Z99=2,3,IF(Z99=3,6,IF(Z99=4,10,15)))),IF(T99="2-Improbable",IF(Z99=1,2,IF(Z99=2,5,IF(Z99=3,9,IF(Z99=4,14,19)))),IF(T99="3-Posible",IF(Z99=1,4,IF(Z99=2,8,IF(Z99=3,13,IF(Z99=4,18,21)))),IF(T99="4-Probable",IF(Z99=1,7,IF(Z99=2,12,IF(Z99=3,17,IF(Z99=4,22,23)))),IF(T99="5-Casi Seguro",IF(Z99=1,11,IF(Z99=2,16,IF(Z99=3,20,IF(Z99=4,24,25))))))))) -> 4 | AC99: =((VLOOKUP(T99,$AH$3:$AJ$7,3,FALSE)*SQRT(U99^2+V99^2+W99^2+X99^2+Y99^2))/(5*SQRT((5)*5^2))) -> 0.075894664
A100: 3200 Lixiviación | B100: 3210 Espesamiento de Lixiviación | C100: Muestreador secundario alimentación lixiviación | D100: 3210SA0002 | E100: Muestreador secundario lixiviación | F100: Cortar una fracción de muestra proveniente del muestreador primario para muestreo o rechazo de muestra | G100: Falla de motor eléctrico por cortocircuito | H100: No afectación a producción, Cambiar motorreductor | I100: 1 | J100: 1 | K100: =+IF(I100="","",IF((I100-J100)>0,"Si","No")) -> No | L100: Ninguna | M100: 0.33333333 | N100: 0 | P100: 0 | Q100: =+IF(M100="","",(IF(((M100*24)-P100)<0,0,(M100*24)-P100)*N100)) -> 0 | R100: =+(IF(((M100*24)-P100)<0,0,((M100*24)-P100)*'Estimación de pérdidas'!$F$72))*N100 -> 0 | S100: No | T100: 3-Posible | U100: =+IF(R100="","",IF(R100<50001,1,IF(R100<200001,2,IF(R100<500001,3,IF(R100<1000001,4,5))))) -> 1 | V100: 1 | Z100: =MAX(U100:Y100) -> 1 | AA100: =IF(Z100=1,VLOOKUP(T100,$AH$3:$AI$7,2,FALSE),IF(Z100=2,VLOOKUP(T100,$AH$8:$AI$12,2, FALSE),IF(Z100=3,VLOOKUP(T100,$AH$13:$AI$17,2,FALSE),IF(Z100=4,VLOOKUP(T100,$AH$18:$AI$22,2,FALSE),IF(Z100=5,VLOOKUP(T100,$AH$23:$AI$27,2,FALSE),""))))) -> Bajo | AB100: =IF(T100="1-Raro",IF(Z100=1,1,IF(Z100=2,3,IF(Z100=3,6,IF(Z100=4,10,15)))),IF(T100="2-Improbable",IF(Z100=1,2,IF(Z100=2,5,IF(Z100=3,9,IF(Z100=4,14,19)))),IF(T100="3-Posible",IF(Z100=1,4,IF(Z100=2,8,IF(Z100=3,13,IF(Z100=4,18,21)))),IF(T100="4-Probable",IF(Z100=1,7,IF(Z100=2,12,IF(Z100=3,17,IF(Z100=4,22,23)))),IF(T100="5-Casi Seguro",IF(Z100=1,11,IF(Z100=2,16,IF(Z100=3,20,IF(Z100=4,24,25))))))))) -> 4 | AC100: =((VLOOKUP(T100,$AH$3:$AJ$7,3,FALSE)*SQRT(U100^2+V100^2+W100^2+X100^2+Y100^2))/(5*SQRT((5)*5^2))) -> 0.075894664
...

Sheet Validación SCE

Sheet Matriz evaluación riesgos EDI
A1: Me gusta revisar las planillas un rato adri después seguir con los
B2: Gold Fields - Operación Salares del Norte.
B3: Matriz de Valoración de Riesgos
B4: Análisis de Criticidad de Equipos, Dispositivos e Instalaciones (ACEDI)
B5: Categorías de consecuencias | E5: Impacto de la consecuencia
E6: 1 - Insignificante | F6: 2 - Menor | G6: 3 - Moderado | H6: 4 - Mayor | I6: 5 - Extremo
B7: Consecuencias económicas | C7: Impacto económico en el negocio | E7: Impacto en margen operacional < USD 50k o pérdida de eficiencia < 2% | F7: Impacto en margen operacional entre USD 50K y USD 200K o pérdida de eficiencia entre 2% y 5% | G7: Impacto en margen operacional entre USD 200K y USD 500K o pérdida de eficiencia entre 5% y 10% | H7: Impacto en margen operacional entre USD 500K y USD 1M o pérdida de eficiencia entre 10% y 20% | I7: Impacto en margen operacional > USD 1M o pérdida de eficiencia > a 20%
C8: Costo operacional | E8: Impacto en margen operacional < USD 50k | F8: Impacto en margen operacional entre USD 50K y USD 200K | G8: Impacto en margen operacional entre USD 200K y USD 500K | H8: Impacto en margen operacional entre USD 500K y USD 1M | I8: Impacto en margen operacional > USD 1M
B9: Consecuencias no económicas | C9: Seguridad y Salud | E9: Efectos o síntomas de bajo nivel atendidos con primeros auxilios sin tratamiento médico adicional, sin efectos posteriores ni generación de pérdida de tiempo. | F9: Lesiones o efectos reversibles que requieren tratamiento médico, pero que no conducen a la restricción de las tareas. | G9: Lesiones, efectos o daños reversibles moderados a una o más personas, que generen pérdida de tiempo. | H9: Fatalidad única y/o daños o efectos irreversibles incapacitantes a una o más personas. | I9: Múltiples fatalidades o enfermedades graves e incapacitantes para múltiples personas.
C10: Medio Ambiente | E10: Impacto ambiental confinado a la localización del evento dentro de la operación y rápidamente reversible, generalmente en un único desplazamiento de atención con el procedimiento de emergencias de la compañía Incidente nivel 1 | F10: Impacto confinado en la zona de influencia dentro de la operación y reversible a corto plazo, atendido por el procedimiento de emergencias de la compañía Incidente nivel 2 | G10: Impacto de recuperación a mediano plazo, confinada en la fuente cercana dentro de las instalaciones de la operación. Incidente nivel 3 | H10: Impacto no confinado en la zona de influencia que requiere una recuperación a largo plazo, dejando algunos daños residuales Incidente nivel 4 | I10: Impacto generalizado - no confinado y que requiere una recuperación a largo plazo, dejando importantes daños residuales Incidente nivel 5
C11: RSC (Comunidad / Imagen / Cumplimento legal) | E11: Impacto leve en comunidad local con expresiones informales de inconformidad. Exposición pública de manera verbal y local. Incumplimiento de requisitos internos con potencial de impacto muy bajo no percibido externamente. | F11: Impacto social relevante en la comunidad local o menor a nivel regional manifestado formalmente. Exposición pública significativa en medios locales. Incumplimiento de requisitos externos con potencial de impacto bajo percibido externamente. | G11: Impacto social permanente en la comunidad local o temporal a nivel regional manifestado formalmente con riesgo de detención de operaciones. Exposición pública en medios nacionales. Incumplimiento de legislación con potencial de impacto moderado, como sanciones, suspensión de permisos, licencias o contratos. | H11: Impacto social permanente y significativo en comunidad regional manifestado formalmente y oposición activa a las operaciones. Exposición pública en medios internacionales. Incumplimiento de legislación con alto potencial de enjuiciamiento o imposición de penalizaciones importantes. | I11: Impacto social permanente y significativo en la región manifestado formalmente y oposición permanente y masiva a las operaciones. Exposición pública y prolongada en medios internacionales. Incumplimiento de legislación que genera suspensión de operaciones y pérdida permanente permisos o licencias
B12: Probabilidad | C12: Referencia de la probabilidad | E12: Matriz de valoración de riesgo
B13: 5 - Casi seguro | C13: El evento no deseado o falla se ha presentado o puede ocurrir de manera recurrente, con frecuencia igual o menor a 3 meses. | E13: 11 - Moderado | F13: 16 - Moderado | G13: 20 - Alto | H13: 24 - Alto | I13: 25 - Alto
B14: 4 - Probable | C14: El evento no deseado o falla se ha presentado de manera frecuente, con historial de ocurrencia de entre 3 meses y 1 año | E14: 7 - Bajo | F14: 12 - Moderado | G14: 15 - Moderado | H14: 22 - Alto | I14: 23 - Alto
B15: 3 - Posible | C15: El evento no deseado o falla se ha presentado ocasionalmente, con historial de ocurrencia de al menos una vez entre 1 y 5 años de operación. | E15: 4 - Bajo | F15: 8 - Moderado | G15: 13 - Moderado | H15: 17 - Moderado | I15: 21 - Alto
B16: 2 - Improbable | C16: El evento no deseado o falla se ha presentado de manera puntual, con historial de ocurrencia de al menos una vez entre 5 y 10 años de operación. | E16: 2 - Bajo | F16: 5 - Bajo | G16: 9 - Moderado | H16: 14 - Moderado | I16: 19 - Alto
B17: 1 - Raro | C17: El evento no deseado o falla no se ha presentado o es probable que ocurra con una frecuencia mayor a 10 años. | E17: 1 - Bajo | F17: 3 - Bajo | G17: 6 - Bajo | H17: 10 - Moderado | I17: 18 - Moderado
B18: Nivel de riesgo | E18: Umbral de tolerancia al riesgo
B19: Alto | E19: Los riesgos superan considerablemente los límites aceptables y requieren atención urgente e inmediata.
B20: Moderado | E20: Los riesgos se encuentran cerca al umbral de tolerancia de riesgo y requiere una gestión proactiva
B21: Bajo | E21: Los riesgos se encuentran abajo del umbral de tolerancia, funcionando adecuadamente una gestión de monitoreo
